Workbook
Name A_impresión_IM: #REF!
Name A_impresión_IM: #REF!
Name A_impresión_IM: #REF!
Name A_impresión_IM: #REF!
Name A_impresión_IM: #REF!
Name A_impresión_IM: #REF!
Name A_impresión_IM: #REF!
Name A_impresión_IM: #REF!
Name A_impresión_IM: #REF!
Name A_impresión_IM: #REF!
Name A_impresión_IM: #REF!
Name A_impresión_IM: #REF!
Name A_impresión_IM: #REF!
Name A_impresión_IM: #REF!
Name A_impresión_IM: #REF!
Name A_impresión_IM: #REF!
Name A_impresión_IM: #REF!
Name A_impresión_IM: #REF!
Name A_impresión_IM: #REF!
Name A_impresión_IM: #REF!
Name A_impresión_IM: #REF!
Name A_impresión_IM: #REF!
Name A_impresión_IM: #REF!
Name A_impresión_IM: #REF!
Name A_impresión_IM: #REF!
Name A_impresión_IM: #REF!
Name A_impresión_IM: #REF!
Name A_impresión_IM: #REF!
Name A_impresión_IM: #REF!
Name A_impresión_IM: #REF!
Name A_impresión_IM: #REF!
Name A_impresión_IM: #REF!
Name A_impresión_IM: #REF!
Name A_impresión_IM: #REF!
Name A_impresión_IM: #REF!
Name A_impresión_IM: #REF!
Name A_impresión_IM: #REF!
Name ANTONE1: #REF!
Name ANTONE1: #REF!
Name ANTONE1: #REF!
Name ANTONE1: #REF!
Name ANTONE1: #REF!
Name ANTONE1: #REF!
Name ANTONE1: #REF!
Name ANTONE1: #REF!
Name ANTONE1: #REF!
Name ANTONE1: #REF!
Name ANTONE1: #REF!
Name ANTONE1: #REF!
Name ANTONE1: #REF!
Name ANTONE1: #REF!
Name ANTONE1: #REF!
Name ANTONE1: #REF!
Name ANTONE1: #REF!
Name ANTONE1: #REF!
Name ANTONE1: #REF!
Name ANTONE1: #REF!
Name ANTONE1: #REF!
Name ANTONE1: #REF!
Name ANTONE1: #REF!

Sheet REPORTE MES 1 (2)
D2: VENTAS ESPERADAS | E2: V. ACUMULADAS | F2: VENTAS REALES | G2: VENTAS ACUMULADAS
B3: VENTAS | C3: 44927 | D3: 5 | E3: =D3 -> 5 | F3: 4 | G3: =F3 -> 4 | P3: VENTAS DEL PERIODO
C4: 44958 | D4: 5 | E4: =E3+D4 -> 10 | F4: 5 | G4: =G3+F4 -> 9 | P4: =F9 -> 3
C5: 44986 | D5: 6 | E5: =E4+D5 -> 16 | F5: 5 | G5: =G4+F5 -> 14
C6: 45017 | D6: 6 | E6: =E5+D6 -> 22 | F6: 5 | G6: =G5+F6 -> 19
C7: 45047 | D7: 7 | E7: =E6+D7 -> 29 | F7: 7 | G7: =G6+F7 -> 26
C8: 45078 | D8: 7 | E8: =E7+D8 -> 36 | F8: 9 | G8: =G7+F8 -> 35
C9: 45108 | D9: 7 | E9: =E8+D9 -> 43 | F9: 3 | G9: =G8+F9 -> 38 | P9: VENTAS ACUMULADAS
C10: 45139 | E10: =IF(D10="","",D10+E9) | G10: =IF(F10="","",F10+G9) | P10: =G9 -> 38
C11: 45170 | E11: =IF(D11="","",D11+E10) | G11: =IF(F11="","",F11+G10)
C12: 45200 | E12: =IF(D12="","",D12+E11) | G12: =IF(F12="","",F12+G11)
C13: 45231 | E13: =IF(D13="","",D13+E12) | G13: =IF(F13="","",F13+G12)
C14: 45261 | E14: =IF(D14="","",D14+E13) | G14: =IF(F14="","",F14+G13)
D16: % PRESUPUESTO | E16: % PRESUPUESTO ACUMULADO | F16: AVANCE REAL % | G16: AVANCE REAL % ACUMULADO | H16: MONTO PRESUPUESTADO mensual | I16: MONTO PRESUPUESTADO ACUMULADO | J16: MONTO REAL EJECUTADO | K16: MONTO REAL EJECUTADO ACUMULADO
B17: AVANCE DE OBRA | C17: 44927 | D17: 0.04 | E17: =D17 -> 0.04 | F17: 0.03 | G17: =F17 -> 0.03 | H17: 6000000 | I17: =H17 -> 6000000 | J17: 6000000 | K17: =J17 -> 6000000
C18: 44958 | D18: 0.04 | E18: =D18+E17 -> 0.08 | F18: 0.04 | G18: =F18+G17 -> 0.07 | H18: 10000000 | I18: =H18+I17 -> 16000000 | J18: 15000000 | K18: =J18+K17 -> 21000000 | L18: Ejecutado | M18: =G25 -> 0.69
C19: 44986 | D19: 0.06 | E19: =D19+E18 -> 0.14 | F19: 0.05 | G19: =F19+G18 -> 0.12 | H19: 12000000 | I19: =H19+I18 -> 28000000 | J19: 10000000 | K19: =J19+K18 -> 31000000 | L19: Por ejecutar | M19: =1-M18 -> 0.31
C20: 45017 | D20: 0.12 | E20: =D20+E19 -> 0.26 | F20: 0.06 | G20: =F20+G19 -> 0.18 | H20: 24000000 | I20: =H20+I19 -> 52000000 | J20: 24000000 | K20: =J20+K19 -> 55000000
C21: 45047 | D21: 0.12 | E21: =D21+E20 -> 0.38 | F21: 0.1 | G21: =F21+G20 -> 0.28 | H21: 24000000 | I21: =H21+I20 -> 76000000 | J21: 22000000 | K21: =J21+K20 -> 77000000
C22: 45078 | D22: 0.15 | E22: =D22+E21 -> 0.53 | F22: 0.12 | G22: =F22+G21 -> 0.4 | H22: 18000000 | I22: =H22+I21 -> 94000000 | J22: 20000000 | K22: =J22+K21 -> 97000000
C23: 45108 | D23: 0.12 | E23: =IF(D23="","",D23+E22) -> 0.65 | F23: 0.14 | G23: =F23+G22 -> 0.54 | H23: 12000000 | I23: =H23+I22 -> 106000000 | J23: 14000000 | K23: =J23+K22 -> 111000000
C24: 45139 | D24: 0.08 | E24: =IF(D24="","",D24+E23) -> 0.73 | F24: 0.15 | G24: =F24+G23 -> 0.69 | H24: 8000000 | I24: =H24+I23 -> 114000000 | J24: 8500000 | K24: =J24+K23 -> 119500000
C25: 45170 | D25: 0.08 | E25: =IF(D25="","",D25+E24) -> 0.81 | G25: =F25+G24 -> 0.69 | H25: 8000000 | I25: =H25+I24 -> 122000000 | K25: =J25+K24 -> 119500000 | L25: Ejecutado | M25: =K25 -> 119500000
C26: 45200 | D26: 0.08 | E26: =IF(D26="","",D26+E25) -> 0.89 | G26: =F26+G25 -> 0.69 | H26: 6000000 | I26: =H26+I25 -> 128000000 | K26: =J26+K25 -> 119500000 | L26: por ejecutar | M26: =I28-K28 -> 11500000
C27: 45231 | D27: 0.08 | E27: =IF(D27="","",D27+E26) -> 0.97 | G27: =F27+G26 -> 0.69 | H27: 2500000 | I27: =H27+I26 -> 130500000 | K27: =J27+K26 -> 119500000
C28: 45261 | D28: 0.03 | E28: =IF(D28="","",D28+E27) -> 1 | G28: =F28+G27 -> 0.69 | H28: 500000 | I28: =H28+I27 -> 131000000 | K28: =J28+K27 -> 119500000

Sheet ARAYA
E2: VENTAS ESPERADAS | F2: V. ACUMULADAS | G2: VENTAS REALES | H2: VENTAS ACUMULADAS
C3: VENTAS | D3: 45231 | E3: 8 | F3: =E3 -> 8 | G3: 0 | H3: =G3 -> 0 | O3: VENTAS DEL PERIODO
D4: 45261 | E4: 8 | F4: =F3+E4 -> 16 | G4: 0 | H4: =H3+G4 -> 0 | O4: =G9 -> 0
D5: 45292 | E5: 8 | F5: =F4+E5 -> 24 | G5: 0 | H5: =H4+G5 -> 0
D6: 45323 | E6: 12 | F6: =F5+E6 -> 36 | G6: 0 | H6: =H5+G6 -> 0
D7: 45352 | E7: 12 | F7: =F6+E7 -> 48 | G7: 0 | H7: =H6+G7 -> 0
D8: 45383 | E8: 12 | F8: =F7+E8 -> 60 | G8: 0 | H8: =H7+G8 -> 0
D9: 45413 | E9: 12 | F9: =F8+E9 -> 72 | G9: 0 | H9: =H8+G9 -> 0 | O9: VENTAS ACUMULADAS
D10: 45444 | E10: 15 | F10: =IF(E10="","",E10+F9) -> 87 | H10: =IF(G10="","",G10+H9) | O10: =H9 -> 0
D11: 45474 | E11: 15 | F11: =IF(E11="","",E11+F10) -> 102 | H11: =IF(G11="","",G11+H10)
D12: 45505 | E12: 15 | F12: =IF(E12="","",E12+F11) -> 117 | H12: =IF(G12="","",G12+H11)
D13: 45536 | E13: 15 | F13: =IF(E13="","",E13+F12) -> 132 | H13: =IF(G13="","",G13+H12)
D14: 45566 | E14: 15 | F14: =IF(E14="","",E14+F13) -> 147 | H14: =IF(G14="","",G14+H13)
E16: % avance | F16: % AVANCE ACUMULADO | G16: AVANCE REAL % | H16: AVANCE REAL % ACUMULADO | I16: MONTO PRESUPUESTADO mensual | J16: MONTO PRESUPUESTADO ACUMULADO | K16: MONTO REAL EJECUTADO | L16: MONTO REAL EJECUTADO ACUMULADO
C17: AVANCE DE OBRA | D17: 45292 | E17: 0.03 | F17: =E17 -> 0.03 | G17: 0 | H17: =G17 -> 0 | I17: 14678820 | J17: =I17 -> 14678820 | K17: 0 | L17: =K17 -> 0
D18: 45323 | E18: 0.06 | F18: =E18+F17 -> 0.09 | G18: 0 | H18: =G18+H17 -> 0 | I18: 29357640 | J18: =I18+J17 -> 44036460 | K18: 0 | L18: =K18+L17 -> 0 | M18: Ejecutado | N18: =H25 -> 0
D19: 45352 | E19: 0.075 | F19: =E19+F18 -> 0.165 | G19: 0 | H19: =G19+H18 -> 0 | I19: 36697050 | J19: =I19+J18 -> 80733510 | K19: 0 | L19: =K19+L18 -> 0 | M19: Por ejecutar | N19: =1-N18 -> 1
D20: 45383 | E20: 0.11 | F20: =E20+F19 -> 0.275 | G20: 0 | H20: =G20+H19 -> 0 | I20: 53822340 | J20: =I20+J19 -> 134555850 | K20: 0 | L20: =K20+L19 -> 0
D21: 45413 | E21: 0.11 | F21: =E21+F20 -> 0.385 | G21: 0 | H21: =G21+H20 -> 0 | I21: 53822340 | J21: =I21+J20 -> 188378190 | K21: 0 | L21: =K21+L20 -> 0
D22: 45444 | E22: 0.11 | F22: =E22+F21 -> 0.495 | G22: 0 | H22: =G22+H21 -> 0 | I22: 53822340 | J22: =I22+J21 -> 242200530 | K22: 0 | L22: =K22+L21 -> 0
D23: 45474 | E23: 0.11 | F23: =IF(E23="","",E23+F22) -> 0.605 | G23: 0 | H23: =G23+H22 -> 0 | I23: 53822340 | J23: =I23+J22 -> 296022870 | K23: 0 | L23: =K23+L22 -> 0
D24: 45505 | E24: 0.11 | F24: =IF(E24="","",E24+F23) -> 0.715 | G24: 0 | H24: =G24+H23 -> 0 | I24: 53822340 | J24: =I24+J23 -> 349845210 | K24: 0 | L24: =K24+L23 -> 0
D25: 45536 | E25: 0.1 | F25: =IF(E25="","",E25+F24) -> 0.815 | G25: 0 | H25: =G25+H24 -> 0 | I25: 48929400 | J25: =I25+J24 -> 398774610 | K25: 0 | L25: =K25+L24 -> 0 | M25: Ejecutado | N25: =L25 -> 0
D26: 45566 | E26: 0.085 | F26: =IF(E26="","",E26+F25) -> 0.9 | G26: 0 | H26: =G26+H25 -> 0 | I26: 41589990 | J26: =I26+J25 -> 440364600 | K26: 0 | L26: =K26+L25 -> 0 | M26: por ejecutar | N26: =J28-L28 -> 522076698
D27: 45597 | E27: 0.042 | F27: =IF(E27="","",E27+F26) -> 0.942 | G27: 0 | H27: =G27+H26 -> 0 | I27: 35229168 | J27: =I27+J26 -> 475593768 | K27: 0 | L27: =K27+L26 -> 0
D28: 45627 | E28: 0.035 | F28: =IF(E28="","",E28+F27) -> 0.977 | G28: 0 | H28: =G28+H27 -> 0 | I28: 46482930 | J28: =I28+J27 -> 522076698 | K28: 0 | L28: =K28+L27 -> 0
D29: 45658 | E29: 0.023 | F29: =IF(E29="","",E29+F28) -> 1 | G29: 0 | H29: =G29+H28 -> 0 | I29: 47950812 | J29: =I29+J28 -> 570027510 | K29: 0 | L29: 0
F30: =IF(E30="","",E30+F29)
B32: ADI
B34: B.- COSTOS DEL PROYECTO | F34: AVANCE EN DOP | I34: ACUMULADO | J34: PRESUPUESTO A LA FECHA | K34: % CUMPLIMIENTO | L34: % AVANCE EN DOP DEL TOTAL | M34: TENDENCIA
B35: PARTIDA | D35: DOP | E35: US $ | F35: 45047 | G35: 45078 | H35: 45108 | K35: Mes Actual
B36: Terreno | D36: 98128296 | E36: 1752291 | K36: =IFERROR(I36/J36,"")
A37: Etapa 1 462 | B37: Costo Urbanismo | D37: 236811000 | E37: 4228767.9 | I37: =SUM(F37:H37) -> 0 | J37: 0 | K37: =IFERROR(I37/J37,"") | L37: =IF((I37/D37)=0,"",(I37/D37))
B38: Micro Urbanismo | D38: 193611000 | E38: 3457339.3 | I38: =SUM(F38:H38) -> 0 | J38: 0 | K38: =IFERROR(I38/J38,"") | L38: =IF((I38/D38)=0,"",(I38/D38))
B39: Macro Urbanismo | D39: 43200000 | E39: 771428.57 | I39: =SUM(F39:H39) -> 0 | J39: 0 | K39: =IFERROR(I39/J39,"") | L39: =IF((I39/D39)=0,"",(I39/D39))
B40: Costo Vivienda | D40: 1123200000 | E40: 20057143 | I40: =SUM(F40:H40) -> 0 | J40: 0 | K40: =IFERROR(I40/J40,"") | L40: =IF((I40/D40)=0,"",(I40/D40))
B41: Gerencia Contrucción: | D41: 163201320 | E41: 2914309.3 | I41: =SUM(F41:H41) -> 0 | J41: 1500000 | K41: =IFERROR(I41/J41,"") -> 0 | L41: =IF((I41/D41)=0,"",(I41/D41))
B42: Indirectos de Obra | D42: 27200220 | E42: 485718.21 | I42: =SUM(F42:H42) -> 0 | J42: 2408610 | K42: =IFERROR(I42/J42,"") -> 0 | L42: =IF((I42/D42)=0,"",(I42/D42))
B43: Total Costos Construcción | D43: =D37+D40+D41+D42 -> 1550412540 | E43: =E37+E40+E41+E42 -> 27685938 | F43: =SUM(F37:F42) -> 0 | G43: =SUM(G37:G42) -> 0 | H43: =SUM(H37:H42) -> 0 | I43: =SUM(I37:I42) -> 0 | J43: =SUM(J37:J42) -> 3908610 | K43: =IFERROR(I43/J43,"") -> 0 | L43: =IF((I43/D43)=0,"",(I43/D43))
B44: Gerencia de la Promotora | D44: 163201320 | E44: 2914309.3 | I44: =SUM(F44:H44) -> 0 | J44: 1500000 | K44: =IFERROR(I44/J44,"") -> 0 | L44: =IF((I44/D44)=0,"",(I44/D44))
B45: Gerencia de Ventas | D45: 176801430 | E45: 3157168.4 | I45: =SUM(F45:H45) -> 0 | J45: 0 | K45: =IFERROR(I45/J45,"") | L45: =IF((I45/D45)=0,"",(I45/D45))
B46: Administración Fiducia | D46: 31008251 | E46: 553718.76 | I46: =SUM(F46:H46) -> 0 | J46: 0 | K46: =IFERROR(I46/J46,"") | L46: =IF((I46/D46)=0,"",(I46/D46))
B47: Publicidad | D47: 40800330 | E47: 728577.32 | H47: 421734.38 | I47: =SUM(F47:H47) -> 421734.38 | J47: 5500000 | K47: =IFERROR(I47/J47,"") -> 0.076678978 | L47: =IF((I47/D47)=0,"",(I47/D47)) -> 0.010336543
B48: Post Ventas | D48: 15504125 | E48: 276859.38 | I48: =SUM(F48:H48) -> 0 | J48: 0 | K48: =IFERROR(I48/J48,"") | L48: =IF((I48/D48)=0,"",(I48/D48))
B49: Total Gastos Operativos | D49: =SUM(D44:D48) -> 4.2731546e+08 | E49: =SUM(E44:E48) -> 7630633.1 | F49: =SUM(F44:F48) -> 0 | G49: =SUM(G44:G48) -> 0 | H49: =SUM(H44:H48) -> 421734.38 | I49: =SUM(I44:I48) -> 421734.38 | J49: =SUM(J44:J48) -> 7000000 | K49: =IFERROR(I49/J49,"") -> 0.060247769 | L49: =IF((I49/D49)=0,"",(I49/D49)) -> 0.00098693921
B50: Permisos legales y Preliminares | D50: 10500000 | E50: 187500 | F50: 694084.83 | I50: =SUM(F50:H50) -> 694084.83 | J50: 2500000 | K50: =IFERROR(I50/J50,"") -> 0.27763393 | L50: =IF((I50/D50)=0,"",(I50/D50)) -> 0.066103317
B51: Diseño y Proyecto | D51: 16200000 | E51: 289285.71 | F51: 1269778.8 | G51: 2019760 | H51: 1858331.1 | I51: =SUM(F51:H51) -> 5147869.9 | J51: 9856000 | K51: =IFERROR(I51/J51,"") -> 0.52230823 | L51: =IF((I51/D51)=0,"",(I51/D51)) -> 0.31776975
B52: Gastos Financieros | D52: 1.24033e+08 | E52: 2214875.1 | I52: =SUM(F52:H52) -> 0 | J52: 0 | K52: =IFERROR(I52/J52,"") | L52: =IF((I52/D52)=0,"",(I52/D52))
B53: Imprevistos | D53: 15504125 | E53: 276859.38 | I53: =SUM(F53:H53) -> 0 | J53: 0 | K53: =IFERROR(I53/J53,"") | L53: =IF((I53/D53)=0,"",(I53/D53))
B54: Total Otros Gastos | D54: =SUM(D50:D53) -> 1.6623713e+08 | E54: =SUM(E50:E53) -> 2968520.2 | F54: =SUM(F50:F53) -> 1963863.6 | G54: =SUM(G50:G53) -> 2019760 | H54: =SUM(H50:H53) -> 1858331.1 | I54: =SUM(I50:I53) -> 5841954.8 | J54: =SUM(J50:J53) -> 12356000 | K54: =IFERROR(I54/J54,"") -> 0.47280307 | L54: =IF((I54/D54)=0,"",(I54/D54)) -> 0.035142298
B55: Costos Totales de Proyecto | D55: =D54+D49+D43+D36 -> 2.2420934e+09 | E55: =E54+E49+E43+E36 -> 40037383 | F55: =F54+F49+F43+F36 -> 1963863.6 | G55: =G54+G49+G43+G36 -> 2019760 | H55: =H54+H49+H43+H36 -> 2280065.5 | I55: =I54+I49+I43+I36 -> 6263689.1 | J55: =J54+J49+J43+J36 -> 23264610 | K55: =IFERROR(I55/J55,"") -> 0.2692368 | L55: =IF((I55/D55)=0,"",(I55/D55)) -> 0.0027936789
J56: =I55-J55 -> -17000921

Sheet budget (6)
A1: D1 | B1: D2 | C1: D2 | D1: PRESUPUESTO ORIGINAL | E1: COMPROMETIDOS | F1: COSTO DE TRABAJO A LA FECHA | G1: COSTO PROYECTADO A LA FECHA | H1: PRECIO UNITARIO DEL PRESUPUESTO | I1: PROYECCIÓN PARA TERMINAR | J1: COSTO TERMINADO AL TERMINAR | K1: PROYECTADO ARRIBA ABAJO DEL PRESUPUESTO
A2: 1 - CONSTRUCCION | B2: 1-1 - TERRENO | C2: 1-1-1 - TERRENO ADI | D2: 7172000.3 | E2: 0 | F2: 0 | G2: 0 | H2: 7172000.3 | I2: 7172000.3 | J2: 7172000.3 | K2: 0
A3: 1 - CONSTRUCCION | B3: 1-1 - TERRENO | C3: 1-1-2 - COSTO ASOCIADO TERRENO | D3: 96213169 | E3: 96213169 | F3: 96213169 | G3: 96213169 | H3: 96213169 | I3: 0 | J3: 96213169 | K3: 0
A4: 1 - CONSTRUCCION | B4: 1-2 - DISEÑO Y PROYECTO | C4: 1-2-1 - DISEÑO Y PROYECTO ADI | D4: -1132808.6 | E4: 0 | F4: 0 | G4: 0 | H4: -1132808.6 | I4: 0 | J4: 0 | K4: -1132808.6
A5: 1 - CONSTRUCCION | B5: 1-2 - DISEÑO Y PROYECTO | C5: 1-2-2 - ESTUDIOS | D5: 5641221.5 | E5: 5641221.5 | F5: 0 | G5: 5641221.5 | H5: 5641221.5 | I5: 0 | J5: 5641221.5 | K5: 0
A6: 1 - CONSTRUCCION | B6: 1-2 - DISEÑO Y PROYECTO | C6: 1-2-3 - DISEÑO Y ARQUITECTURA | D6: 8804294.6 | E6: 8604294.6 | F6: 10000 | G6: 8604294.6 | H6: 8804294.6 | I6: 200000 | J6: 8804294.6 | K6: 0
A7: 1 - CONSTRUCCION | B7: 1-2 - DISEÑO Y PROYECTO | C7: 1-2-4 - INGENIERIAS | D7: 5954647.6 | E7: 5932855.3 | F7: 0 | G7: 5932855.3 | H7: 5954647.6 | I7: 21792.24 | J7: 5954647.6 | K7: 0
A8: 1 - CONSTRUCCION | B8: 1-2 - DISEÑO Y PROYECTO | C8: 1-2-5 - COMPUTOS | D8: 367644.95 | E8: 367644.95 | F8: 0 | G8: 367644.95 | H8: 367644.95 | I8: 0 | J8: 367644.95 | K8: 0
A9: 1 - CONSTRUCCION | B9: 1-3 - PRELIMINARES DE OBRA | C9: 1-3-1 - PRELIMINARES DE OBRA ADI | D9: 2608628.3 | E9: 0 | F9: 0 | G9: 0 | H9: 2608628.3 | I9: 2608628.3 | J9: 2608628.3 | K9: 0
A10: 1 - CONSTRUCCION | B10: 1-3 - PRELIMINARES DE OBRA | C10: 1-3-2 - OBRAS PRELIMINARES AREA CAMPAMENTO | D10: 1897166 | E10: 1897166 | F10: 0 | G10: 1897166 | H10: 1897166 | I10: 0 | J10: 1897166 | K10: 0
A11: 1 - CONSTRUCCION | B11: 1-3 - PRELIMINARES DE OBRA | C11: 1-3-3 - OBRAS PRELIMINARES AREA SHOWROOM | D11: 7141349 | E11: 7141349 | F11: 0 | G11: 7141349 | H11: 7141349 | I11: 0 | J11: 7141349 | K11: 0
A12: 1 - CONSTRUCCION | B12: 1-4 - URBANISMO | C12: 1-4-1 - URBANISMO ADI | D12: 11803487 | E12: 0 | F12: 0 | G12: 0 | H12: 11803487 | I12: 11803487 | J12: 11803487 | K12: 0
A13: 1 - CONSTRUCCION | B13: 1-4 - URBANISMO | C13: 1-4-2 - MOVIMIENTO DE TIERRA | D13: 54584720 | E13: 0 | F13: 0 | G13: 0 | H13: 54584720 | I13: 54584720 | J13: 54584720 | K13: 0
... A48: 2 - OPERATIVO | B48: 2-4 - PUBLICIDAD Y PROMOCION | C48: 2-4-1 - PUBLICIDAD Y PROMOCION ADI | D48: 50231089 | E48: 3786501.9 | F48: 0 | G48: 3786501.9 | H48: 50231089 | I48: 46444587 | J48: 50231089 | K48: 0
A49: 2 - OPERATIVO | B49: 2-4 - PUBLICIDAD Y PROMOCION | C49: 2-4-2 - PUBLICIDAD Y PROMOCION | F49: 390000 | G49: 1300000 | H49: 1300000 | I49: 0 | J49: 1300000 | K49: 0 | L49: ESTA DUPLICADO
A50: 2 - OPERATIVO | B50: 2-5 - POST-VENTAS | C50: 2-5-1 - POST-VENTAS ADI | D50: 19238273 | E50: 0 | F50: 0 | G50: 0 | H50: 19238273 | I50: 19238273 | J50: 19238273 | K50: 0
A51: 2 - OPERATIVO | B51: 2-5 - POST-VENTAS | C51: 2-5-2 - POST-VENTAS | D51: 0 | E51: 0 | F51: 0 | G51: 0 | H51: 0 | I51: 0 | J51: 0 | K51: 0
A52: 3 - OTROS | B52: 3-1 - PERMISOS, LEGALES Y PRELIMINARES | C52: 3-1-1 - PERMISOS,LEGALES Y PRELIMINARES ADI | D52: 11603049 | E52: 0 | F52: 0 | G52: 0 | H52: 11603049 | I52: 11603049 | J52: 11603049 | K52: 0
A53: 3 - OTROS | B53: 3-1 - PERMISOS, LEGALES Y PRELIMINARES | C53: 3-1-2 - PERMISOS,LEGALES Y PRELIMINARES | D53: 3396950.7 | E53: 3396950.7 | F53: 0 | G53: 3396950.7 | H53: 3396950.7 | I53: 0 | J53: 3396950.7 | K53: 0
A54: 3 - OTROS | B54: 3-2 - IMPREVISTOS | C54: 3-2-1 - IMPREVISTOS ADI | D54: 19238273 | E54: 0 | F54: 0 | G54: 0 | H54: 19238273 | I54: 19238273 | J54: 19238273 | K54: 0
A55: 3 - OTROS | B55: 3-2 - IMPREVISTOS | C55: 3-2-2 - IMPREVISTOS | D55: 0 | E55: 0 | F55: 0 | G55: 0 | H55: 0 | I55: 0 | J55: 0 | K55: 0
A56: 3 - OTROS | B56: 3-3 - GASTOS FINANCIEROS | C56: 3-3-1 - GASTOS FINANCIEROS ADI | D56: 173144460 | E56: 0 | F56: 0 | G56: 0 | H56: 173144460 | I56: 173144460 | J56: 173144460 | K56: 0
A57: 3 - OTROS | B57: 3-3 - GASTOS FINANCIEROS | C57: 3-3-2 - GASTOS FINANCIEROS | D57: 0 | E57: 0 | F57: 0 | G57: 0 | H57: 0 | I57: 0 | J57: 0 | K57: 0
D58: =SUM(D2:D57) -> 2803282274 | E58: =SUM(E2:E57) -> 1.3298115e+08 | F58: =SUM(F2:F57) -> 96613169 | G58: =SUM(G2:G57) -> 1.3428115e+08 | H58: =SUM(H2:H57) -> 2804582274 | I58: =SUM(I2:I57) -> 2.6714339e+09 | J58: =SUM(J2:J57) -> 2.8057151e+09 | K58: =SUM(K2:K57) -> -1132808.6

Sheet PRESENTACIÓN MARZO 24
I2: pagos | J2: contratos | L2: pendiente de pagar
B3: PRESUPUESTO A MARZO 2024 | E3: 59.1 | F3: COSTO A LA FECHA | I3: TOTAL A LA FECHA | J3: COMPROMETIDO | K3: PROYECTADO PARA TERMINAR | L3: POR EJECUTAR
B4: PARTIDA | D4: DOP | E4: US $ | F4: 45292 | G4: 45323 | H4: 45352
B5: Terreno | D5: =SUM('budget (6)'!D2:D3) -> 103385169 | E5: =D5/E3 -> 1749326 | I5: =SUM('budget (6)'!F2:F3) -> 96213169 | J5: =SUM('budget (6)'!E2:E3) -> 96213169 | K5: =SUM('budget (6)'!J2:J3) -> 103385169 | L5: =J5-I5 -> 0
B6: Costo Urbanismo | D6: =SUM('budget (6)'!D9:D22) -> 4.5174906e+08 | E6: =D6/$E$3 -> 7643808.1 | I6: =9038515 -> 9038515 | J6: =SUM('budget (6)'!E9:E22) -> 9038515 | K6: =SUM('budget (6)'!J9:J22) -> 4.5174906e+08 | L6: =J6-I6 -> 0
B7: Costo Vivienda | D7: =SUM('budget (6)'!D23:D36) -> 1265953920 | E7: =D7/$E$3 -> 21420540 | I7: =SUM('budget (6)'!F23:F36) -> 0 | J7: =SUM('budget (6)'!E23:E36) -> 0 | K7: =SUM('budget (6)'!J23:J36) -> 1265953920 | L7: =J7-I7 -> 0
B8: Gerencia Construcción: | D8: =SUM('budget (6)'!D37:D38) -> 171770298 | E8: =D8/$E$3 -> 2906434.8 | I8: =SUM('budget (6)'!F37:F38) -> 0 | J8: =SUM('budget (6)'!E37:E38) -> 0 | K8: =SUM('budget (6)'!J37:J38) -> 171770298 | L8: =J8-I8 -> 0
B9: Indirectos de Obra | D9: ='budget (6)'!D39+'budget (6)'!D40 -> 34354060 | E9: =D9/$E$3 -> 581286.97 | I9: ='budget (6)'!F39+'budget (6)'!F40 -> 0 | J9: ='budget (6)'!E39+'budget (6)'!E40 -> 0 | K9: ='budget (6)'!J39+'budget (6)'!J40 -> 34354060 | L9: =J9-I9 -> 0
B10: Total Costos Construcción | D10: =SUM(D6:D9) -> 1923827338 | E10: =SUM(E6:E9) -> 32552070 | I10: =SUM(I6:I9) -> 9038515 | J10: =SUM(J6:J9) -> 9038515 | K10: =SUM(K6:K9) -> 1923827338 | L10: =J10-I10 -> 0
B11: Gerencia de la Promotora | D11: =SUM('budget (6)'!D41:D42) -> 137416238 | E11: =D11/$E$3 -> 2325147.9 | I11: =SUM('budget (6)'!F41:F42) -> 0 | J11: =SUM('budget (6)'!E41:E42) -> 0 | K11: =SUM('budget (6)'!J41:J42) -> 137416238 | L11: =J11-I11 -> 0
B12: Gerencia de Ventas | D12: =SUM('budget (6)'!D43:D45) -> 274832477 | E12: =D12/$E$3 -> 4650295.7 | I12: =SUM('budget (6)'!F43:F45) -> 0 | J12: =SUM('budget (6)'!E43:E45) -> 0 | K12: =SUM('budget (6)'!J43:J45) -> 274832477 | L12: =J12-I12 -> 0
B13: Administración Fiducia | D13: =SUM('budget (6)'!D46:D47) -> 67333957 | E13: =D13/$E$3 -> 1139322.5 | I13: =SUM('budget (6)'!F46:F47) -> 0 | J13: =SUM('budget (6)'!E46:E47) -> 0 | K13: =SUM('budget (6)'!J46:J47) -> 67333957 | L13: =J13-I13 -> 0
B14: Publicidad | D14: =SUM('budget (6)'!D48:D49) -> 50231089 | E14: =D14/$E$3 -> 849933.82 | I14: =446334.38 -> 446334.38 | J14: =SUM('budget (6)'!E48) -> 3786501.9 | K14: 50231089 | L14: =J14-I14 -> 3340167.5
B15: Post Ventas | D15: =SUM('budget (6)'!D50:D51) -> 19238273 | E15: =D15/$E$3 -> 325520.69 | I15: 0 | J15: =SUM('budget (6)'!E50:E51) -> 0 | K15: =SUM('budget (6)'!J50:J51) -> 19238273 | L15: =J15-I15 -> 0
B16: Total Gastos Operativos | D16: =SUM(D11:D15) -> 549052034 | E16: =SUM(E11:E15) -> 9290220.5 | I16: =SUM(I11:I15) -> 446334.38 | J16: =SUM(J11:J15) -> 3786501.9 | K16: =SUM(K11:K15) -> 549052034 | L16: =J16-I16 -> 3340167.5 | N16: PERMISOS | O16: REE,BOLSO BAK
B17: Permisos legales y Preliminares | D17: =SUM('budget (6)'!D52:D53) -> 15000000 | E17: =D17/$E$3 -> 253807.11 | I17: 1576990 | J17: =N17+I17+O17 -> 13841815 | K17: =SUM('budget (6)'!J52:J53) -> 15000000 | L17: =J17-I17 -> 12264825 | N17: 11255347 | O17: 1009477.8
A18: MODIFICAR ADI 22,000,000 | B18: Diseño y Proyecto | D18: 22000000 | E18: =D18/$E$3 -> 372250.42 | I18: =12246486.57 -> 12246487 | J18: =SUM('budget (6)'!E4:E8) -> 20546016 | K18: 22000000 | L18: =J18-I18 -> 8299529.8
B19: Gastos Financieros | D19: ='budget (6)'!D56+'budget (6)'!D57 -> 173144460 | E19: =D19/$E$3 -> 2929686.3 | I19: ='budget (6)'!F56+'budget (6)'!F57 -> 0 | J19: ='budget (6)'!E56+'budget (6)'!E57 -> 0 | K19: ='budget (6)'!J56+'budget (6)'!J57 -> 173144460 | L19: =J19-I19 -> 0
B20: Imprevistos | D20: ='budget (6)'!D54+'budget (6)'!D55 -> 19238273 | E20: =D20/$E$3 -> 325520.69 | I20: ='budget (6)'!F54+'budget (6)'!F55 -> 0 | J20: ='budget (6)'!E54+'budget (6)'!E55 -> 0 | K20: ='budget (6)'!J54+'budget (6)'!J55 -> 19238273 | L20: =J20-I20 -> 0
B21: Total Otros Gastos | D21: =SUM(D17:D20) -> 229382733 | E21: =SUM(E17:E20) -> 3881264.5 | I21: =SUM(I17:I20) -> 13823477 | J21: =SUM(J17:J20) -> 34387831 | K21: =SUM(K17:K20) -> 229382733 | L21: =J21-I21 -> 20564355
B22: Costos Totales de Proyecto | D22: =D5+D10+D16+D21 -> 2805647274 | E22: =E5+E10+E16+E21 -> 47472881 | F22: =F21+F16+F10+F5 -> 0 | G22: =G21+G16+G10+G5 -> 0 | H22: =H21+H16+H10+H5 -> 0 | I22: =I21+I16+I10+I5 -> 1.1952149e+08 | J22: =J21+J16+J10+J5 -> 1.4342602e+08 | K22: =K21+K16+K10+K5 -> 2805647274 | L22: =J22-I22 -> 23904522
I25: ADELANTO AFI | J25: 160000000 | L25: =J26/J25 -> 0.8964126
I26: Gastado y comprometido | J26: =J22 -> 1.4342602e+08
E27: =J27-SUM(I35:I38) -> 1500000 | I27: Disponible | J27: =J25-J26 -> 16573983
E29: PARTIDA | I29: MES 1 | J29: MES 2 | K29: MES 3 | L29: MES 4 | M29: MES 5 | N29: MES 6 | O29: MES 7 | P29: MES 8 | Q29: MES 9 | R29: Total
E30: gerencias | I30: 1000000 | J30: 1000000 | K30: 1000000 | L30: 1000000 | M30: 1000000 | N30: 1000000 | O30: 1000000 | P30: 1000000 | Q30: 1000000 | R30: =SUM(I30:Q30) -> 9000000
E31: promocion | I31: 500000 | J31: 500000 | K31: 500000 | L31: 500000 | M31: 500000 | N31: 500000 | O31: 500000 | P31: 500000 | Q31: 500000 | R31: =SUM(I31:Q31) -> 4500000
E32: atención al cliente | L32: 350000 | M32: 350000 | N32: 350000 | O32: 350000 | P32: 350000 | Q32: 350000 | R32: =SUM(I32:Q32) -> 2100000
I33: =SUM(I30:I32) -> 1500000 | J33: =SUM(J30:J32) -> 1500000 | K33: =SUM(K30:K32) -> 1500000 | L33: =SUM(L30:L32) -> 1850000 | M33: =SUM(M30:M32) -> 1850000 | N33: =SUM(N30:N32) -> 1850000 | O33: =SUM(O30:O32) -> 1850000 | P33: =SUM(P30:P32) -> 1850000 | Q33: =SUM(Q30:Q32) -> 1850000
E34: Acumulado | J34: =I33+J33 -> 3000000 | K34: =J33+J34 -> 4500000 | L34: =K33+K34 -> 6000000 | M34: =L33+L34 -> 7850000 | N34: =M33+M34 -> 9700000 | O34: =N33+N34 -> 11550000 | P34: =O33+O34 -> 13400000 | Q34: =P33+P34 -> 15250000
E36: Disponible | I36: =$J$27-I33 -> 15073983 | J36: =$J$27-J34 -> 13573983 | K36: =$J$27-K34 -> 12073983 | L36: =$J$27-L34 -> 10573983 | M36: =$J$27-M34 -> 8723983.2 | N36: =$J$27-N34 -> 6873983.2 | O36: =$J$27-O34 -> 5023983.2 | P36: =$J$27-P34 -> 3173983.2 | Q36: =$J$27-Q34 -> 1323983.2

Sheet budget (8)
A1: Código de Costo Nivel 1 | B1: Código de Costo Nivel 2 | C1: Código de Costo Nivel 3 | D1: Presupuesto Original | E1: Costos Comprometidos (CONTRATO) | F1: Costos de Trabajo a la Fecha (CUBICADO) | G1: Costos Proyectados | H1: Precio unitario del presupuesto | I1: Proyección para terminar | J1: Costo Estimado al Terminar | K1: Proyectado Arriba/Abajo del Presupuesto
A2: 1 - CONSTRUCCION | B2: 1-1 - TERRENO | C2: 1-1-1 - TERRENO ADI | D2: 7172000.3 | E2: 0 | F2: 0 | G2: 0 | H2: 7172000.3 | I2: 7172000.3 | J2: 7172000.3 | K2: 0
A3: 1 - CONSTRUCCION | B3: 1-1 - TERRENO | C3: 1-1-2 - COSTO ASOCIADO TERRENO | D3: 96213169 | E3: 96272169 | F3: 96272169 | G3: 96272169 | H3: 96213169 | I3: 0 | J3: 96272169 | K3: -59000
A4: 1 - CONSTRUCCION | B4: 1-2 - DISEÑO Y PROYECTO | C4: 1-2-1 - DISEÑO Y PROYECTO ADI | D4: 22191.38 | E4: 0 | F4: 0 | G4: 0 | H4: 22191.38 | I4: 22191.38 | J4: 22191.38 | K4: 0
A5: 1 - CONSTRUCCION | B5: 1-2 - DISEÑO Y PROYECTO | C5: 1-2-2 - ESTUDIOS | D5: 0 | E5: 0 | F5: 0 | G5: 0 | H5: 0
A6: 1 - CONSTRUCCION | B6: 1-2 - DISEÑO Y PROYECTO | C6: 1-2-2 - ESTUDIOS | D6: 5641221.5 | E6: 5641221.5 | F6: 0 | G6: 5641221.5 | H6: 5641221.5 | I6: 0 | J6: 5641221.5 | K6: 0
A7: 1 - CONSTRUCCION | B7: 1-2 - DISEÑO Y PROYECTO | C7: 1-2-3 - DISEÑO Y ARQUITECTURA | D7: 8804294.6 | E7: 8785614.6 | F7: 0 | G7: 8785614.6 | H7: 8804294.6 | I7: 18680.02 | J7: 8804294.6 | K7: 0
A8: 1 - CONSTRUCCION | B8: 1-2 - DISEÑO Y PROYECTO | C8: 1-2-4 - INGENIERIAS | D8: 5954647.6 | E8: 5932855.3 | F8: 0 | G8: 5932855.3 | H8: 5954647.6 | I8: 21792.24 | J8: 5954647.6 | K8: 0
A9: 1 - CONSTRUCCION | B9: 1-2 - DISEÑO Y PROYECTO | C9: 1-2-5 - COMPUTOS | D9: 367644.95 | E9: 367644.95 | F9: 0 | G9: 367644.95 | H9: 367644.95 | I9: 0 | J9: 367644.95 | K9: 0
A10: 1 - CONSTRUCCION | B10: 1-3 - PRELIMINARES DE OBRA | C10: 1-3-1 - PRELIMINARES DE OBRA ADI | D10: 2608628.3 | E10: 0 | F10: 0 | G10: 0 | H10: 2608628.3 | I10: 2608628.3 | J10: 2608628.3 | K10: 0
A11: 1 - CONSTRUCCION | B11: 1-3 - PRELIMINARES DE OBRA | C11: 1-3-2 - OBRAS PRELIMINARES AREA CAMPAMENTO | D11: 1897166.4 | E11: 1897166.4 | F11: 480315 | G11: 1897166.4 | H11: 1897166.4 | I11: 0 | J11: 1897166.4 | K11: 0
A12: 1 - CONSTRUCCION | B12: 1-3 - PRELIMINARES DE OBRA | C12: 1-3-3 - OBRAS PRELIMINARES AREA SHOWROOM | D12: 7141349 | E12: 7141349 | F12: 1209931.5 | G12: 7141349 | H12: 7141349 | I12: 0 | J12: 7141349 | K12: 0
A13: 1 - CONSTRUCCION | B13: 1-4 - URBANISMO | C13: 1-4-1 - URBANISMO ADI | D13: 11813427 | E13: 0 | F13: 0 | G13: 0 | H13: 11813427 | I13: 11813427 | J13: 11813427 | K13: 0
A14: 1 - CONSTRUCCION | B14: 1-4 - URBANISMO | C14: 1-4-2 - MOVIMIENTO DE TIERRA | D14: 54584720 | E14: 0 | F14: 0 | G14: 0 | H14: 54584720 | I14: 54584720 | J14: 54584720 | K14: 0
A15: 1 - CONSTRUCCION | B15: 1-4 - URBANISMO | C15: 1-4-3 - HIDROSANITARIAS | D15: 56232241 | E15: 0 | F15: 0 | G15: 0 | H15: 56232241 | I15: 56232241 | J15: 56232241 | K15: 0
A16: 1 - CONSTRUCCION | B16: 1-4 - URBANISMO | C16: 1-4-4 - SISTEMAS DE AGUAS | D16: 35679323 | E16: 0 | F16: 0 | G16: 0 | H16: 35679323 | I16: 35679323 | J16: 35679323 | K16: 0
A17: 1 - CONSTRUCCION | B17: 1-4 - URBANISMO | C17: 1-4-6 - INFRAESTRUCTURA ELECTRICA | D17: 1.3513803e+08 | E17: 0 | F17: 0 | G17: 0 | H17: 1.3513803e+08 | I17: 1.3513803e+08 | J17: 1.3513803e+08 | K17: 0
... A26: 1 - CONSTRUCCION | B26: 1-5 - EDIFICACIONES | C26: 1-5-3 - SUPERESTRUCTURA | D26: 2.8304295e+08 | E26: 0 | F26: 0 | G26: 0 | H26: 2.8304295e+08 | I26: 2.8304295e+08 | J26: 2.8304295e+08 | K26: 0
A27: 1 - CONSTRUCCION | B27: 1-5 - EDIFICACIONES | C27: 1-5-4 - INSTALACIONES ELECTRICAS | D27: 0 | E27: 0 | F27: 0 | G27: 0 | H27: 0
A28: 1 - CONSTRUCCION | B28: 1-5 - EDIFICACIONES | C28: 1-5-4 - INSTALACIONES ELECTRICAS | D28: 60439200 | E28: 0 | F28: 0 | G28: 0 | H28: 60439200 | I28: 60439200 | J28: 60439200 | K28: 0
A29: 1 - CONSTRUCCION | B29: 1-5 - EDIFICACIONES | C29: 1-5-5 - TELECOMUNICACIONES | D29: 8446912.3 | E29: 0 | F29: 0 | G29: 0 | H29: 8446912.3 | I29: 8446912.3 | J29: 8446912.3 | K29: 0
A30: 1 - CONSTRUCCION | B30: 1-5 - EDIFICACIONES | C30: 1-5-6 - INSTALACIONES SANITARIAS | D30: 1.0100749e+08 | E30: 0 | F30: 0 | G30: 0 | H30: 1.0100749e+08 | I30: 1.0100749e+08 | J30: 1.0100749e+08 | K30: 0
A31: 1 - CONSTRUCCION | B31: 1-5 - EDIFICACIONES | C31: 1-5-7 - INSTALACIONES MECANICAS | D31: 455797.65 | E31: 0 | F31: 0 | G31: 0 | H31: 455797.65 | I31: 455797.65 | J31: 455797.65 | K31: 0
A32: 1 - CONSTRUCCION | B32: 1-5 - EDIFICACIONES | C32: 1-5-8 - ALBANILERIA | D32: 79619986 | E32: 0 | F32: 0 | G32: 0 | H32: 79619986 | I32: 79619986 | J32: 79619986 | K32: 0
A33: 1 - CONSTRUCCION | B33: 1-5 - EDIFICACIONES | C33: 1-5-9 - HERRERIA | D33: 55148949 | E33: 0 | F33: 0 | G33: 0 | H33: 55148949 | I33: 55148949 | J33: 55148949 | K33: 0
A34: 1 - CONSTRUCCION | B34: 1-5 - EDIFICACIONES | C34: 1-5-10 - REVESTIMIENTO | D34: 1.7979257e+08 | E34: 0 | F34: 0 | G34: 0 | H34: 1.7979257e+08 | I34: 1.7979257e+08 | J34: 1.7979257e+08 | K34: 0
A35: 1 - CONSTRUCCION | B35: 1-5 - EDIFICACIONES | C35: 1-5-11 - CARPINTERIA | D35: 1.1340591e+08 | E35: 0 | F35: 0 | G35: 0 | H35: 1.1340591e+08 | I35: 1.1340591e+08 | J35: 1.1340591e+08 | K35: 0
A36: 1 - CONSTRUCCION | B36: 1-5 - EDIFICACIONES | C36: 1-5-12 - VENTANERIA | D36: 95070320 | E36: 0 | F36: 0 | G36: 0 | H36: 95070320 | I36: 95070320 | J36: 95070320 | K36: 0
A37: 1 - CONSTRUCCION | B37: 1-5 - EDIFICACIONES | C37: 1-5-13 - PINTURA | D37: 1.2190433e+08 | E37: 0 | F37: 0 | G37: 0 | H37: 1.2190433e+08 | I37: 1.2190433e+08 | J37: 1.2190433e+08 | K37: 0
A38: 1 - CONSTRUCCION | B38: 1-5 - EDIFICACIONES | C38: 1-5-14 - MISCELANEOS | D38: 74569125 | E38: 0 | F38: 0 | G38: 0 | H38: 74569125 | I38: 74569125 | J38: 74569125 | K38: 0
A39: 1 - CONSTRUCCION | B39: 1-6 - GERENCIA DE CONSTRUCCION | C39: 1-6-1 - GERENCIA DE CONSTRUCCION ADI | D39: 171771292 | E39: 0 | F39: 0 | G39: 0 | H39: 171771292 | I39: 171771292 | J39: 171771292 | K39: 0
... A59: 3 - OTROS | B59: 3-3 - GASTOS FINANCIEROS | C59: 3-3-2 - GASTOS FINANCIEROS | D59: 0 | E59: 0 | F59: 0 | G59: 0 | H59: 0 | I59: 0 | J59: 0 | K59: 0
D60: =SUM(D2:D59) -> 2831861943 | E60: =SUM(E2:E59) -> 2.7193771e+08 | F60: =SUM(F2:F59) -> 98352415 | G60: =SUM(G2:G59) -> 2.7193771e+08 | H60: =SUM(H2:H59) -> 2831861943 | I60: =SUM(I2:I59) -> 2.5599832e+09 | J60: =SUM(J2:J59) -> 2831920943 | K60: =SUM(K2:K59) -> -59000
D62: 2816861943 | E62: 2.6724076e+08 | F62: 98832094 | G62: 2.6724076e+08 | H62: 2816861943 | I62: 2.5496802e+09 | J62: 2816920943 | K62: -59000
D63: Presupuesto Original | E63: Costos Comprometidos | F63: Costos de Trabajo a la Fecha | G63: Costos Proyectados | H63: Precio unitario del presupuesto | I63: Proyección para terminar | J63: Costo Estimado al Terminar | K63: Proyectado Arriba/Abajo del Presupuesto
D64: =D1 -> Presupuesto Original | E64: =E1 -> Costos Comprometidos (CONTRATO) | F64: =F1 -> Costos de Trabajo a la Fecha (CUBICADO) | G64: =G1 -> Costos Proyectados | H64: =H1 -> Precio unitario del presupuesto | I64: =I1 -> Proyección para terminar | J64: =J1 -> Costo Estimado al Terminar | K64: =K1 -> Proyectado Arriba/Abajo del Presupuesto
D65: =D60-D62 -> 15000000 | E65: =E60-E62 -> 4696950.7 | F65: =F60-F62 -> -479678.33 | G65: =G60-G62 -> 4696950.7 | H65: =H60-H62 -> 15000000 | I65: =I60-I62 -> 10303049 | J65: =J60-J62 -> 15000000 | K65: =K60-K62 -> 0

Sheet PRESENTACIÓN ABRIL 24 v0
J1: IMAGEN DEL ADI archivo : Flujo_de_caja_PUNTA_CANA_462_MAR2024_V.0.XLSX al 02/05/24
E2: TC al 7 de mayo
B3: PRESUPUESTO ABRIL 2024 | E3: 59.15 | F3: TOTAL EJECUTADO | G3: COMPROMETIDO | H3: PROYECTADO PARA TERMINAR | I3: POR EJECUTAR
B4: PARTIDA | D4: DOP | E4: US $
B5: Terreno | D5: =SUM('budget (8)'!D2:D3) -> 103385169 | E5: =D5/E3 -> 1747847.3 | F5: =SUM('budget (8)'!F2:F3) -> 96272169 | G5: =SUM('budget (8)'!E2:E3) -> 96272169 | H5: =SUM('budget (8)'!J2:J3) -> 103444169 | I5: =G5-F5 -> 0
B6: Costo Urbanismo | D6: =SUM('budget (8)'!D10:D23) -> 4.51759e+08 | E6: =D6/$E$3 -> 7637514.8 | F6: =SUM('budget (8)'!F10:F23) -> 1690246.5 | G6: =SUM('budget (8)'!E10:E23) -> 9038515.4 | H6: =SUM('budget (8)'!J10:J23) -> 4.51759e+08 | I6: =G6-F6 -> 7348268.9
B7: Costo Vivienda | D7: =SUM('budget (8)'!D24:D38) -> 1265953920 | E7: =D7/$E$3 -> 21402433 | F7: =SUM('budget (8)'!F24:F38) -> 0 | G7: =SUM('budget (8)'!E24:E38) -> 0 | H7: =SUM('budget (8)'!J24:J38) -> 1265953920 | I7: =G7-F7 -> 0
B8: Gerencia Construcción: | D8: =SUM('budget (8)'!D39:D40) -> 171771292 | E8: =D8/$E$3 -> 2903994.8 | F8: =SUM('budget (8)'!F39:F40) -> 0 | G8: =SUM('budget (8)'!E39:E40) -> 0 | H8: =SUM('budget (8)'!J39:J40) -> 171771292 | I8: =G8-F8 -> 0
B9: Indirectos de Obra | D9: =SUM('budget (8)'!D41:D42) -> 34354258 | E9: =D9/$E$3 -> 580798.95 | F9: =SUM('budget (8)'!F41:F42) -> 0 | G9: =SUM('budget (8)'!E41:E42) -> 0 | H9: =SUM('budget (8)'!J41:J42) -> 34354258 | I9: =G9-F9 -> 0
B10: Total Costos Construcción | D10: =SUM(D6:D9) -> 1923838470 | E10: =SUM(E6:E9) -> 32524742 | F10: =SUM(F6:F9) -> 1690246.5 | G10: =SUM(G6:G9) -> 9038515.4 | H10: =SUM(H6:H9) -> 1923838470 | I10: =G10-F10 -> 7348268.9
B11: Gerencia de la Promotora | D11: =SUM('budget (8)'!D43:D44) -> 137417034 | E11: =D11/$E$3 -> 2323195.8 | F11: =SUM('budget (8)'!F43:F44) -> 0 | G11: =SUM('budget (8)'!E43:E44) -> 137416238 | H11: =SUM('budget (8)'!J43:J44) -> 137417034 | I11: =G11-F11 -> 137416238
B12: Gerencia de Ventas | D12: =SUM('budget (8)'!D45:D47) -> 281704919 | E12: =D12/$E$3 -> 4762551.5 | F12: =SUM('budget (8)'!F45:F47) -> 0 | G12: =SUM('budget (8)'!E45:E47) -> 0 | H12: =SUM('budget (8)'!J45:J47) -> 281704919 | I12: =G12-F12 -> 0
B13: Administración Fiducia | D13: =SUM('budget (8)'!D48:D49) -> 67334346 | E13: =D13/$E$3 -> 1138366 | F13: =SUM('budget (8)'!F48:F49) -> 0 | G13: =SUM('budget (8)'!E48:E49) -> 0 | H13: =SUM('budget (8)'!J48:J49) -> 67334346 | I13: =G13-F13 -> 0
B14: Publicidad | D14: =SUM('budget (8)'!D50:D51) -> 51531388 | E14: =D14/$E$3 -> 871198.44 | F14: =SUM('budget (8)'!F50:F51) -> 390000 | G14: =SUM('budget (8)'!E50:E51) -> 5086501.9 | H14: =SUM('budget (8)'!J50:J51) -> 51531388 | I14: =G14-F14 -> 4696501.9
B15: Post Ventas | D15: =SUM('budget (8)'!D52:D53) -> 19238385 | E15: =D15/$E$3 -> 325247.42 | F15: =SUM('budget (8)'!F52:F53) -> 0 | G15: =SUM('budget (8)'!E52:E53) -> 0 | H15: =SUM('budget (8)'!J52:J53) -> 19238385 | I15: =G15-F15 -> 0
B16: Total Gastos Operativos | D16: =SUM(D11:D15) -> 557226072 | E16: =SUM(E11:E15) -> 9420559.1 | F16: =SUM(F11:F15) -> 390000 | G16: =SUM(G11:G15) -> 1.4250274e+08 | H16: =SUM(H11:H15) -> 557226072 | I16: =G16-F16 -> 1.4211274e+08
B17: Permisos legales y Preliminares | D17: =SUM('budget (8)'!D54:D55) -> 15000000 | E17: =D17/$E$3 -> 253592.56 | F17: =SUM('budget (8)'!F54:F55) -> 0 | G17: =SUM('budget (8)'!E54:E55) -> 3396950.7 | H17: =SUM('budget (8)'!J54:J55) -> 15000000 | I17: =G17-F17 -> 3396950.7
B18: Diseño y Proyecto | D18: =SUM('budget (8)'!D5:D9) -> 20767809 | E18: =D18/$E$3 -> 351104.12 | F18: =SUM('budget (8)'!F5:F9) -> 0 | G18: =SUM('budget (8)'!E5:E9) -> 20727336 | H18: =SUM('budget (8)'!J5:J9) -> 20767809 | I18: =G18-F18 -> 20727336
B19: Gastos Financieros | D19: =SUM('budget (8)'!D58:D59) -> 192383847 | E19: =D19/$E$3 -> 3252474.2 | F19: =SUM('budget (8)'!F58:F59) -> 0 | G19: =SUM('budget (8)'!E58:E59) -> 0 | H19: =SUM('budget (8)'!J58:J59) -> 192383847 | I19: =G19-F19 -> 0
B20: Imprevistos | D20: =SUM('budget (8)'!D56:D57) -> 19238385 | E20: =D20/$E$3 -> 325247.42 | F20: =SUM('budget (8)'!F56:F57) -> 0 | G20: =SUM('budget (8)'!E56:E57) -> 0 | H20: =SUM('budget (8)'!J56:J57) -> 19238385 | I20: =G20-F20 -> 0
B21: Total Otros Gastos | D21: =SUM(D17:D20) -> 2.4739004e+08 | E21: =SUM(E17:E20) -> 4182418.3 | F21: =SUM(F17:F20) -> 0 | G21: =SUM(G17:G20) -> 24124287 | H21: =SUM(H17:H20) -> 2.4739004e+08 | I21: =G21-F21 -> 24124287
B22: Costos Totales de Proyecto | D22: =D5+D10+D16+D21 -> 2.8318398e+09 | E22: =E5+E10+E16+E21 -> 47875566 | F22: =F21+F16+F10+F5 -> 98352415 | G22: =G21+G16+G10+G5 -> 2.7193771e+08 | H22: =H21+H16+H10+H5 -> 2.8318988e+09 | I22: =G22-F22 -> 1.735853e+08
K24: Dato del ADI | L24: 2.8318619e+09
K25: Dato Procore | L25: =D22 -> 2.8318398e+09
K26: Diferencia | L26: =L24-L25 -> 22190.772
B30: ADELANTO AFI | D30: 160000000
B31: Gastado y comprometido | D31: =G22 -> 2.7193771e+08
B32: Disponible | D32: =D30-D31 -> -1.1193771e+08
B34: PARTIDA | D34: MES 1 | E34: MES 2 | F34: MES 3 | G34: MES 4 | H34: MES 5 | I34: MES 6 | J34: MES 7 | K34: MES 8 | L34: MES 9 | M34: Total
B35: gerencias | D35: 1000000 | E35: 1000000 | F35: 1000000 | G35: 1000000 | H35: 1000000 | I35: 1000000 | J35: 1000000 | K35: 1000000 | L35: 1000000 | M35: =SUM(D35:L35) -> 9000000
B36: promocion | D36: 500000 | E36: 500000 | F36: 500000 | G36: 500000 | H36: 500000 | I36: 500000 | J36: 500000 | K36: 500000 | L36: 500000 | M36: =SUM(D36:L36) -> 4500000
B37: atención al cliente | G37: 350000 | H37: 350000 | I37: 350000 | J37: 350000 | K37: 350000 | L37: 350000 | M37: =SUM(D37:L37) -> 2100000
D38: =SUM(D35:D37) -> 1500000 | E38: =SUM(E35:E37) -> 1500000 | F38: =SUM(F35:F37) -> 1500000 | G38: =SUM(G35:G37) -> 1850000 | H38: =SUM(H35:H37) -> 1850000 | I38: =SUM(I35:I37) -> 1850000 | J38: =SUM(J35:J37) -> 1850000 | K38: =SUM(K35:K37) -> 1850000 | L38: =SUM(L35:L37) -> 1850000
B39: Acumulado | E39: =D38+E38 -> 3000000 | F39: =E38+E39 -> 4500000 | G39: =F38+F39 -> 6000000 | H39: =G38+G39 -> 7850000 | I39: =H38+H39 -> 9700000 | J39: =I38+I39 -> 11550000 | K39: =J38+J39 -> 13400000 | L39: =K38+K39 -> 15250000
B41: Disponible | D41: =$D$32-D38 -> -1.1343771e+08 | E41: =$D$32-E39 -> -1.1493771e+08 | F41: =$D$32-F39 -> -1.1643771e+08 | G41: =$D$32-G39 -> -1.1793771e+08 | H41: =$D$32-H39 -> -1.1978771e+08 | I41: =$D$32-I39 -> -1.2163771e+08 | J41: =$D$32-J39 -> -1.2348771e+08 | K41: =$D$32-K39 -> -1.2533771e+08 | L41: =$D$32-L39 -> -1.2718771e+08
K43: =1500000*59 -> 88500000
K44: =K43*3% -> 2655000
D45: 160000000 | K45: 2800000
D46: 119521495 | K46: =SUM(K44:K45) -> 5455000
D47: =D45-D46 -> 40478505
D49: =D47-K44-K46 -> 32368505

Sheet budget (9)
D1: ?
A2: Código de Costo Nivel 1 | B2: Código de Costo Nivel 2 | C2: Código de Costo Nivel 3 | D2: Presupuesto Original | E2: Costos Comprometidos | F2: Costos de Trabajo a la Fecha | G2: Costos Proyectados | H2: Precio unitario del presupuesto | I2: Proyección para terminar | J2: Costo Estimado al Terminar | K2: Proyectado Arriba/Abajo del Presupuesto
A3: 1 - CONSTRUCCION | B3: 1-1 - TERRENO | C3: 1-1-1 - TERRENO ADI | D3: 7172000.3 | E3: 0 | F3: 0 | G3: 0 | H3: 7172000.3 | I3: 7172000.3 | J3: 7172000.3 | K3: 0
A4: 1 - CONSTRUCCION | B4: 1-1 - TERRENO | C4: 1-1-2 - COSTO ASOCIADO TERRENO | D4: 96213169 | E4: 96272169 | F4: 96272169 | G4: 96272169 | H4: 96213169 | I4: 0 | J4: 96272169 | K4: -59000
A5: 1 - CONSTRUCCION | B5: 1-2 - DISEÑO Y PROYECTO | C5: 1-2-1 - DISEÑO Y PROYECTO ADI | D5: 22191.38 | E5: 0 | F5: 0 | G5: 0 | H5: 22191.38 | I5: 22191.38 | J5: 22191.38 | K5: 0
A6: 1 - CONSTRUCCION | B6: 1-2 - DISEÑO Y PROYECTO | C6: 1-2-2 - ESTUDIOS | D6: 0 | E6: 0 | F6: 0 | G6: 0 | I6: 0 | J6: 0 | K6: 0
A7: 1 - CONSTRUCCION | B7: 1-2 - DISEÑO Y PROYECTO | C7: 1-2-2 - ESTUDIOS | D7: 5641221.5 | E7: 5641221.5 | F7: 0 | G7: 5641221.5 | H7: 5641221.5 | I7: 0 | J7: 5641221.5 | K7: 0
A8: 1 - CONSTRUCCION | B8: 1-2 - DISEÑO Y PROYECTO | C8: 1-2-3 - DISEÑO Y ARQUITECTURA | D8: 8804294.6 | E8: 8785614.6 | F8: 0 | G8: 8785614.6 | H8: 8804294.6 | I8: 18680.02 | J8: 8804294.6 | K8: 0
A9: 1 - CONSTRUCCION | B9: 1-2 - DISEÑO Y PROYECTO | C9: 1-2-4 - INGENIERIAS | D9: 5954647.6 | E9: 5932855.3 | F9: 0 | G9: 5932855.3 | H9: 5954647.6 | I9: 21792.24 | J9: 5954647.6 | K9: 0
A10: 1 - CONSTRUCCION | B10: 1-2 - DISEÑO Y PROYECTO | C10: 1-2-5 - COMPUTOS | D10: 367644.95 | E10: 367644.95 | F10: 0 | G10: 367644.95 | H10: 367644.95 | I10: 0 | J10: 367644.95 | K10: 0
A11: 1 - CONSTRUCCION | B11: 1-3 - PRELIMINARES DE OBRA | C11: 1-3-1 - PRELIMINARES DE OBRA ADI | D11: 2608628.3 | E11: 0 | F11: 0 | G11: 0 | H11: 2608628.3 | I11: 2608628.3 | J11: 2608628.3 | K11: 0
A12: 1 - CONSTRUCCION | B12: 1-3 - PRELIMINARES DE OBRA | C12: 1-3-2 - OBRAS PRELIMINARES AREA CAMPAMENTO | D12: 1897166.4 | E12: 1897166.4 | F12: 480315 | G12: 1897166.4 | H12: 1897166.4 | I12: 0 | J12: 1897166.4 | K12: 0
A13: 1 - CONSTRUCCION | B13: 1-3 - PRELIMINARES DE OBRA | C13: 1-3-3 - OBRAS PRELIMINARES AREA SHOWROOM | D13: 7141349 | E13: 7141349 | F13: 2079609.8 | G13: 7141349 | H13: 7141349 | I13: 0 | J13: 7141349 | K13: 0
A14: 1 - CONSTRUCCION | B14: 1-4 - URBANISMO | C14: 1-4-1 - URBANISMO ADI | D14: 11813427 | E14: 0 | F14: 0 | G14: 0 | H14: 11813427 | I14: 11813427 | J14: 11813427 | K14: 0
A15: 1 - CONSTRUCCION | B15: 1-4 - URBANISMO | C15: 1-4-2 - MOVIMIENTO DE TIERRA | D15: 54584720 | E15: 0 | F15: 0 | G15: 0 | H15: 54584720 | I15: 54584720 | J15: 54584720 | K15: 0
A16: 1 - CONSTRUCCION | B16: 1-4 - URBANISMO | C16: 1-4-3 - HIDROSANITARIAS | D16: 56232241 | E16: 0 | F16: 0 | G16: 0 | H16: 56232241 | I16: 56232241 | J16: 56232241 | K16: 0
A17: 1 - CONSTRUCCION | B17: 1-4 - URBANISMO | C17: 1-4-4 - SISTEMAS DE AGUAS | D17: 35679323 | E17: 0 | F17: 0 | G17: 0 | H17: 35679323 | I17: 35679323 | J17: 35679323 | K17: 0
A18: 1 - CONSTRUCCION | B18: 1-4 - URBANISMO | C18: 1-4-6 - INFRAESTRUCTURA ELECTRICA | D18: 1.3513803e+08 | E18: 0 | F18: 0 | G18: 0 | H18: 1.3513803e+08 | I18: 1.3513803e+08 | J18: 1.3513803e+08 | K18: 0
... A27: 1 - CONSTRUCCION | B27: 1-5 - EDIFICACIONES | C27: 1-5-3 - SUPERESTRUCTURA | D27: 2.8304295e+08 | E27: 0 | F27: 0 | G27: 0 | H27: 2.8304295e+08 | I27: 2.8304295e+08 | J27: 2.8304295e+08 | K27: 0
A28: 1 - CONSTRUCCION | B28: 1-5 - EDIFICACIONES | C28: 1-5-4 - INSTALACIONES ELECTRICAS | D28: 0 | E28: 0 | F28: 0 | G28: 0 | I28: 0 | J28: 0 | K28: 0
A29: 1 - CONSTRUCCION | B29: 1-5 - EDIFICACIONES | C29: 1-5-4 - INSTALACIONES ELECTRICAS | D29: 60439200 | E29: 0 | F29: 0 | G29: 0 | H29: 60439200 | I29: 60439200 | J29: 60439200 | K29: 0
A30: 1 - CONSTRUCCION | B30: 1-5 - EDIFICACIONES | C30: 1-5-5 - TELECOMUNICACIONES | D30: 8446912.3 | E30: 0 | F30: 0 | G30: 0 | H30: 8446912.3 | I30: 8446912.3 | J30: 8446912.3 | K30: 0
A31: 1 - CONSTRUCCION | B31: 1-5 - EDIFICACIONES | C31: 1-5-6 - INSTALACIONES SANITARIAS | D31: 1.0100749e+08 | E31: 0 | F31: 0 | G31: 0 | H31: 1.0100749e+08 | I31: 1.0100749e+08 | J31: 1.0100749e+08 | K31: 0
A32: 1 - CONSTRUCCION | B32: 1-5 - EDIFICACIONES | C32: 1-5-7 - INSTALACIONES MECANICAS | D32: 455797.65 | E32: 0 | F32: 0 | G32: 0 | H32: 455797.65 | I32: 455797.65 | J32: 455797.65 | K32: 0
A33: 1 - CONSTRUCCION | B33: 1-5 - EDIFICACIONES | C33: 1-5-8 - ALBANILERIA | D33: 79619986 | E33: 0 | F33: 0 | G33: 0 | H33: 79619986 | I33: 79619986 | J33: 79619986 | K33: 0
A34: 1 - CONSTRUCCION | B34: 1-5 - EDIFICACIONES | C34: 1-5-9 - HERRERIA | D34: 55148949 | E34: 0 | F34: 0 | G34: 0 | H34: 55148949 | I34: 55148949 | J34: 55148949 | K34: 0
A35: 1 - CONSTRUCCION | B35: 1-5 - EDIFICACIONES | C35: 1-5-10 - REVESTIMIENTO | D35: 1.7979257e+08 | E35: 0 | F35: 0 | G35: 0 | H35: 1.7979257e+08 | I35: 1.7979257e+08 | J35: 1.7979257e+08 | K35: 0
A36: 1 - CONSTRUCCION | B36: 1-5 - EDIFICACIONES | C36: 1-5-11 - CARPINTERIA | D36: 1.1340591e+08 | E36: 0 | F36: 0 | G36: 0 | H36: 1.1340591e+08 | I36: 1.1340591e+08 | J36: 1.1340591e+08 | K36: 0
A37: 1 - CONSTRUCCION | B37: 1-5 - EDIFICACIONES | C37: 1-5-12 - VENTANERIA | D37: 95070320 | E37: 0 | F37: 0 | G37: 0 | H37: 95070320 | I37: 95070320 | J37: 95070320 | K37: 0
A38: 1 - CONSTRUCCION | B38: 1-5 - EDIFICACIONES | C38: 1-5-13 - PINTURA | D38: 1.2190433e+08 | E38: 0 | F38: 0 | G38: 0 | H38: 1.2190433e+08 | I38: 1.2190433e+08 | J38: 1.2190433e+08 | K38: 0
A39: 1 - CONSTRUCCION | B39: 1-5 - EDIFICACIONES | C39: 1-5-14 - MISCELANEOS | D39: 74569125 | E39: 0 | F39: 0 | G39: 0 | H39: 74569125 | I39: 74569125 | J39: 74569125 | K39: 0
A40: 1 - CONSTRUCCION | B40: 1-6 - GERENCIA DE CONSTRUCCION | C40: 1-6-1 - GERENCIA DE CONSTRUCCION ADI | D40: 0 | E40: 0 | F40: 0 | G40: 0 | I40: 0 | J40: 0 | K40: 0
A41: 1 - CONSTRUCCION | B41: 1-6 - GERENCIA DE CONSTRUCCION | C41: 1-6-1 - GERENCIA DE CONSTRUCCION ADI | D41: 171771292 | E41: 0 | F41: 0 | G41: 0 | H41: 171771292 | I41: 171771292 | J41: 171771292 | K41: 0
A42: 1 - CONSTRUCCION | B42: 1-6 - GERENCIA DE CONSTRUCCION | C42: 1-6-2 - COSTO GERENCIA DE CONSTRUCCION | D42: 0 | E42: 0 | F42: 0 | G42: 0 | H42: 0 | I42: 0 | J42: 0 | K42: 0
A43: 1 - CONSTRUCCION | B43: 1-7 - INDIRECTOS DE OBRA | C43: 1-7-1 - INDIRECTOS DE OBRA ADI | D43: 34354258 | E43: 0 | F43: 0 | G43: 0 | H43: 34354258 | I43: 34354258 | J43: 34354258 | K43: 0
A44: 1 - CONSTRUCCION | B44: 1-7 - INDIRECTOS DE OBRA | C44: 1-7-2 - COSTOS INDIRECTOS DE OBRA | D44: 0 | E44: 0 | F44: 0 | G44: 0 | H44: 0 | I44: 0 | J44: 0 | K44: 0
A45: 2 - OPERATIVO | B45: 2-1 - GERENCIA DE LA PROMOTORA | C45: 2-1-1 - GERENCIA DE LA PROMOTORA ADI | D45: 137417034 | E45: 137416238 | F45: 0 | G45: 137416238 | H45: 137417034 | I45: 796 | J45: 137417034 | K45: 0
A46: 2 - OPERATIVO | B46: 2-1 - GERENCIA DE LA PROMOTORA | C46: 2-1-2 - COSTO GERENCIA DE LA PROMOTORA ADI | D46: 0 | E46: 0 | F46: 0 | G46: 0 | H46: 0 | I46: 0 | J46: 0 | K46: 0
A47: 2 - OPERATIVO | B47: 2-2 - GERENCIA DE VENTAS | C47: 2-2-1 - COSTO GERENCIA DE VENTAS | D47: 0 | E47: 0 | F47: 0 | G47: 0 | H47: 0 | I47: 0 | J47: 0 | K47: 0
A48: 2 - OPERATIVO | B48: 2-2 - GERENCIA DE VENTAS | C48: 2-2-2 - ADMINISTRACION DE VENTAS | D48: 35151584 | E48: 0 | F48: 0 | G48: 0 | H48: 35151584 | I48: 35151584 | J48: 35151584 | K48: 0
A49: 2 - OPERATIVO | B49: 2-2 - GERENCIA DE VENTAS | C49: 2-2-3 - COMISIONES | D49: 246553335 | E49: 0 | F49: 0 | G49: 0 | H49: 246553335 | I49: 246553335 | J49: 246553335 | K49: 0
A50: 2 - OPERATIVO | B50: 2-3 - ADMINISTRACION DE FIDUCIARIA | C50: 2-3-1 - ADMINISTRACION DE FIDUCIARIA ADI | D50: 67334346 | E50: 0 | F50: 0 | G50: 0 | H50: 67334346 | I50: 67334346 | J50: 67334346 | K50: 0
A51: 2 - OPERATIVO | B51: 2-3 - ADMINISTRACION DE FIDUCIARIA | C51: 2-3-2 - COSTO ADMINISTRACION DE FIDUCIARIA | D51: 0 | E51: 0 | F51: 0 | G51: 0 | H51: 0 | I51: 0 | J51: 0 | K51: 0
A52: 2 - OPERATIVO | B52: 2-4 - PUBLICIDAD Y PROMOCION | C52: 2-4-1 - PUBLICIDAD Y PROMOCION ADI | D52: 50231388 | E52: 3786501.9 | F52: 0 | G52: 3786501.9 | H52: 50231388 | I52: 46444886 | J52: 50231388 | K52: 0
... A61: 3 - OTROS | B61: 3-3 - GASTOS FINANCIEROS | C61: 3-3-2 - GASTOS FINANCIEROS | D61: 0 | E61: 0 | F61: 0 | G61: 0 | H61: 0 | I61: 0 | J61: 0 | K61: 0
D63: =SUM(D3:D61) -> 2831861943 | E63: =SUM(E3:E61) -> 2.7427224e+08 | F63: =SUM(F3:F61) -> 103476099 | G63: =SUM(G3:G61) -> 2.7427224e+08 | H63: =SUM(H3:H61) -> 2831861943 | I63: =SUM(I3:I61) -> 2.5576487e+09 | J63: =SUM(J3:J61) -> 2831920943 | K63: =SUM(K3:K61) -> -59000

Sheet PRESENTACIÓN ABRIL 24 v1
E1: cambiar a la fecha del adi marzo 2024 | K1: IMAGEN DEL ADI archivo : Flujo_de_caja_PUNTA_CANA_462_MAR2024_V.0.XLSX al 02/05/24
E2: TC al 7 de mayo | F2: a | G2: b | H2: d | I2: c
B3: PRESUPUESTO ABRIL 2024 | E3: 59.15 | F3: TOTAL EJECUTADO | G3: COMPROMETIDO | H3: POR EJECUTAR | I3: PROYECTADO PARA TERMINAR
B4: PARTIDA | D4: DOP | E4: US $
B5: Terreno | D5: =SUM('budget (9)'!D3:D4) -> 103385169 | E5: =D5/E3 -> 1747847.3 | F5: =SUM('budget (9)'!F3:F4) -> 96272169 | G5: =SUM('budget (9)'!E3:E4) -> 96272169 | H5: =G5-F5 -> 0 | I5: =SUM('budget (9)'!I3:I4) -> 7172000.3 | J5: =D5-(G5+I5) -> -59000
B6: Costo Urbanismo | D6: =SUM('budget (9)'!D11:D24) -> 4.51759e+08 | E6: =D6/$E$3 -> 7637514.8 | F6: =SUM('budget (9)'!F11:F24) -> 2559924.8 | G6: =SUM('budget (9)'!E11:E24) -> 9038515.4 | H6: =G6-F6 -> 6478590.6 | I6: =SUM('budget (9)'!I11:I24) -> 4.4272048e+08 | J6: =D6-(G6+I6) -> 0
B7: Costo Vivienda | D7: =SUM('budget (9)'!D25:D39) -> 1265953920 | E7: =D7/$E$3 -> 21402433 | F7: =SUM('budget (9)'!F25:F39) -> 0 | G7: =SUM('budget (9)'!E25:E39) -> 0 | H7: =G7-F7 -> 0 | I7: =SUM('budget (9)'!I25:I39) -> 1265953920 | J7: =D7-(G7+I7) -> 0
B8: Gerencia Construcción: | D8: =SUM('budget (9)'!D40:D41) -> 171771292 | E8: =D8/$E$3 -> 2903994.8 | F8: =SUM('budget (9)'!F40:F41) -> 0 | G8: =SUM('budget (9)'!E40:E41) -> 0 | H8: =G8-F8 -> 0 | I8: =SUM('budget (9)'!I40:I41) -> 171771292 | J8: =D8-(G8+I8) -> 0
B9: Indirectos de Obra | D9: =SUM('budget (9)'!D42:D43) -> 34354258 | E9: =D9/$E$3 -> 580798.95 | F9: =SUM('budget (9)'!F42:F43) -> 0 | G9: =SUM('budget (9)'!E42:E43) -> 0 | H9: =G9-F9 -> 0 | I9: =SUM('budget (9)'!I42:I43) -> 34354258 | J9: =D9-(G9+I9) -> 0
B10: Total Costos Construcción | D10: =SUM(D6:D9) -> 1923838470 | E10: =SUM(E6:E9) -> 32524742 | F10: =SUM(F6:F9) -> 2559924.8 | G10: =SUM(G6:G9) -> 9038515.4 | H10: =G10-F10 -> 6478590.6 | I10: =SUM(I6:I9) -> 1.9148e+09 | J10: =D10-(G10+I10) -> 0
B11: Gerencia de la Promotora | D11: =SUM('budget (9)'!D44:D45) -> 137417034 | E11: =D11/$E$3 -> 2323195.8 | F11: =SUM('budget (9)'!F44:F45) -> 0 | G11: =SUM('budget (9)'!E44:E45) -> 137416238 | H11: =G11-F11 -> 137416238 | I11: =SUM('budget (9)'!I44:I45) -> 796 | J11: =D11-(G11+I11) -> 0
B12: Gerencia de Ventas | D12: =SUM('budget (9)'!D46:D48) -> 35151584 | E12: =D12/$E$3 -> 594278.68 | F12: =SUM('budget (9)'!F46:F48) -> 0 | G12: =SUM('budget (9)'!E46:E48) -> 0 | H12: =G12-F12 -> 0 | I12: =SUM('budget (9)'!I46:I48) -> 35151584 | J12: =D12-(G12+I12) -> 0
B13: Administración Fiducia | D13: =SUM('budget (9)'!D49:D50) -> 313887681 | E13: =D13/$E$3 -> 5306638.7 | F13: =SUM('budget (9)'!F49:F50) -> 0 | G13: =SUM('budget (9)'!E49:E50) -> 0 | H13: =G13-F13 -> 0 | I13: =SUM('budget (9)'!I49:I50) -> 313887681 | J13: =D13-(G13+I13) -> 0
B14: Publicidad | D14: =SUM('budget (9)'!D51:D52) -> 50231388 | E14: =D14/$E$3 -> 849220.42 | F14: =SUM('budget (9)'!F51:F52) -> 0 | G14: =SUM('budget (9)'!E51:E52) -> 3786501.9 | H14: =G14-F14 -> 3786501.9 | I14: =SUM('budget (9)'!I51:I52) -> 46444886 | J14: =D14-(G14+I14) -> 0
B15: Post Ventas | D15: =SUM('budget (9)'!D53:D54) -> 20538385 | E15: =D15/$E$3 -> 347225.44 | F15: =SUM('budget (9)'!F53:F54) -> 0 | G15: =SUM('budget (9)'!E53:E54) -> 0 | H15: =G15-F15 -> 0 | I15: =SUM('budget (9)'!I53:I54) -> 20538385 | J15: =D15-(G15+I15) -> 0
B16: Total Gastos Operativos | D16: =SUM(D11:D15) -> 557226072 | E16: =SUM(E11:E15) -> 9420559.1 | F16: =SUM(F11:F15) -> 0 | G16: =SUM(G11:G15) -> 1.4120274e+08 | H16: =G16-F16 -> 1.4120274e+08 | I16: =SUM(I11:I15) -> 4.1602333e+08 | J16: =D16-(G16+I16) -> 0
B17: Permisos legales y Preliminares | D17: =SUM('budget (9)'!D55:D56) -> 11603049 | E17: =D17/$E$3 -> 196163.13 | F17: =SUM('budget (9)'!F55:F56) -> 3634527.5 | G17: =SUM('budget (9)'!E55:E56) -> 3634527.5 | H17: =G17-F17 -> 0 | I17: =SUM('budget (9)'!I55:I56) -> 7968521.8 | J17: =D17-(G17+I17) -> 0
B18: Diseño y Proyecto | D18: =SUM('budget (9)'!D5:D10) -> 20790000 | E18: =D18/$E$3 -> 351479.29 | F18: =SUM('budget (9)'!F5:F10) -> 0 | G18: =SUM('budget (9)'!E5:E10) -> 20727336 | H18: =G18-F18 -> 20727336 | I18: =SUM('budget (9)'!I5:I10) -> 62663.64 | J18: =D18-(G18+I18) -> 0
B19: Gastos Financieros | D19: =SUM('budget (9)'!D59:D60) -> 192383847 | E19: =D19/$E$3 -> 3252474.2 | F19: =SUM('budget (9)'!F59:F60) -> 0 | G19: =SUM('budget (9)'!E59:E60) -> 0 | H19: =G19-F19 -> 0 | I19: =SUM('budget (9)'!I59:I60) -> 192383847 | J19: =D19-(G19+I19) -> 0
B20: Imprevistos | D20: =SUM('budget (9)'!D57:D58) -> 22635336 | E20: =D20/$E$3 -> 382676.85 | F20: =SUM('budget (9)'!F57:F58) -> 1009477.9 | G20: =SUM('budget (9)'!E57:E58) -> 3396950.7 | H20: =G20-F20 -> 2387472.8 | I20: =SUM('budget (9)'!I57:I58) -> 19238385 | J20: =D20-(G20+I20) -> 0
B21: Total Otros Gastos | D21: =SUM(D17:D20) -> 247412232 | E21: =SUM(E17:E20) -> 4182793.4 | F21: =SUM(F17:F20) -> 4644005.4 | G21: =SUM(G17:G20) -> 27758815 | H21: =G21-F21 -> 23114809 | I21: =SUM(I17:I20) -> 2.1965342e+08 | J21: =D21-(G21+I21) -> 0
B22: Costos Totales de Proyecto | D22: =D5+D10+D16+D21 -> 2831861943 | E22: =E5+E10+E16+E21 -> 47875942 | F22: =F21+F16+F10+F5 -> 103476099 | G22: =G21+G16+G10+G5 -> 2.7427224e+08 | H22: =G22-F22 -> 1.7079614e+08 | I22: =I21+I16+I10+I5 -> 2.5576487e+09 | J22: =J21+J16+J10+J5 -> -59000
L24: Dato del ADI | M24: 2.8318619e+09
L25: Dato Procore | M25: =D22 -> 2831861943
L26: Diferencia | M26: =M24-M25 -> -0.6079998
B30: ADELANTO AFI | D30: 160000000
B31: Gastado y comprometido
B32: Disponible | D32: =D30-D31 -> 160000000
B34: PARTIDA | D34: MES 1 | E34: MES 2 | F34: MES 3 | G34: MES 4 | H34: MES 5 | I34: MES 6 | K34: MES 7 | L34: MES 8 | M34: MES 9 | N34: Total
B35: gerencias | D35: 1000000 | E35: 1000000 | F35: 1000000 | G35: 1000000 | H35: 1000000 | I35: 1000000 | K35: 1000000 | L35: 1000000 | M35: 1000000 | N35: =SUM(D35:M35) -> 9000000
B36: promocion | D36: 500000 | E36: 500000 | F36: 500000 | G36: 500000 | H36: 500000 | I36: 500000 | K36: 500000 | L36: 500000 | M36: 500000 | N36: =SUM(D36:M36) -> 4500000
A37: meter gastos operativos | B37: atención al cliente | G37: 350000 | H37: 350000 | I37: 350000 | K37: 350000 | L37: 350000 | M37: 350000 | N37: =SUM(D37:M37) -> 2100000
D38: =SUM(D35:D37) -> 1500000 | E38: =SUM(E35:E37) -> 1500000 | F38: =SUM(F35:F37) -> 1500000 | G38: =SUM(G35:G37) -> 1850000 | H38: =SUM(H35:H37) -> 1850000 | I38: =SUM(I35:I37) -> 1850000 | K38: =SUM(K35:K37) -> 1850000 | L38: =SUM(L35:L37) -> 1850000 | M38: =SUM(M35:M37) -> 1850000
B39: Acumulado | E39: =D38+E38 -> 3000000 | F39: =E38+E39 -> 4500000 | G39: =F38+F39 -> 6000000 | H39: =G38+G39 -> 7850000 | I39: =H38+H39 -> 9700000 | K39: =I38+I39 -> 11550000 | L39: =K38+K39 -> 13400000 | M39: =L38+L39 -> 15250000
B41: Disponible | D41: =$D$32-D38 -> 158500000 | E41: =$D$32-E39 -> 157000000 | F41: =$D$32-F39 -> 155500000 | G41: =$D$32-G39 -> 154000000 | H41: =$D$32-H39 -> 152150000 | I41: =$D$32-I39 -> 150300000 | K41: =$D$32-K39 -> 148450000 | L41: =$D$32-L39 -> 146600000 | M41: =$D$32-M39 -> 144750000
L43: =1500000*59 -> 88500000
L44: =L43*3% -> 2655000
D45: 160000000 | L45: 2800000
D46: 119521495 | L46: =SUM(L44:L45) -> 5455000
D47: =D45-D46 -> 40478505
D49: =D47-L44-L46 -> 32368505

Sheet BITACORA Y AJUSTES AL ARCHIVO
B2: FECHA | C2: EXPLICACIÓN | D2: ACCIÓN REQUERIDA | E2: RESPONSABLE | F2: FECHA | G2: SEGUIMIENTO
B3: 45414 | C3: Falta permiso de agua | D3: Actualizar el monto en el ADI | E3: PLA / RQ | F3: 45415
B4: 45414 | C4: Impuesto de transferencia del activo | D4: Actualizar el monto en el ADI | E4: PLA / RQ

Sheet PRESENTACIÓN 2 meses
D1: TOTAL EJECUTADO | H1: COMPROMETIDO | L1: POR EJECUTAR
D3: 45352 | E3: 45383 | F3: 45413 | G3: var% | H3: 45352 | I3: 45383 | J3: 45413 | K3: var% | L3: 45352 | M3: 45383 | N3: 45413 | O3: var%
B4: Terreno | D4: ='PRESENTACIÓN MARZO 24'!I5 -> 96213169 | E4: ='PRESENTACIÓN ABRIL 24 v1'!F5 -> 96272169 | F4: ='PRESENTACIÓN Al 29 de mayo'!#REF! -> #REF! | G4: =(F4/E4)-1 -> #REF! | H4: ='PRESENTACIÓN MARZO 24'!J5 -> 96213169 | I4: ='PRESENTACIÓN ABRIL 24 v1'!G5 -> 96272169 | J4: ='PRESENTACIÓN Al 29 de mayo'!E5 -> 94032040 | L4: ='PRESENTACIÓN MARZO 24'!L5 -> 0 | M4: ='PRESENTACIÓN ABRIL 24 v1'!H5 -> 0 | N4: ='PRESENTACIÓN Al 29 de mayo'!G5 -> 59000
B5: Costo Urbanismo | D5: ='PRESENTACIÓN MARZO 24'!I6 -> 9038515 | E5: ='PRESENTACIÓN ABRIL 24 v1'!F6 -> 2559924.8 | F5: ='PRESENTACIÓN Al 29 de mayo'!#REF! -> #REF! | G5: =(F5-E5) -> #REF! | H5: ='PRESENTACIÓN MARZO 24'!J6 -> 9038515 | I5: ='PRESENTACIÓN ABRIL 24 v1'!G6 -> 9038515.4 | J5: ='PRESENTACIÓN Al 29 de mayo'!E6 -> 9038515.4 | L5: ='PRESENTACIÓN MARZO 24'!L6 -> 0 | M5: ='PRESENTACIÓN ABRIL 24 v1'!H6 -> 6478590.6 | N5: ='PRESENTACIÓN Al 29 de mayo'!G6 -> 0
B6: Costo Vivienda | D6: ='PRESENTACIÓN MARZO 24'!I7 -> 0 | E6: ='PRESENTACIÓN ABRIL 24 v1'!F7 -> 0 | F6: ='PRESENTACIÓN Al 29 de mayo'!#REF! -> #REF! | H6: ='PRESENTACIÓN MARZO 24'!J7 -> 0 | I6: ='PRESENTACIÓN ABRIL 24 v1'!G7 -> 0 | J6: ='PRESENTACIÓN Al 29 de mayo'!E7 -> 0 | L6: ='PRESENTACIÓN MARZO 24'!L7 -> 0 | M6: ='PRESENTACIÓN ABRIL 24 v1'!H7 -> 0 | N6: ='PRESENTACIÓN Al 29 de mayo'!G7 -> 0
B7: Gerencia Construcción: | D7: ='PRESENTACIÓN MARZO 24'!I8 -> 0 | E7: ='PRESENTACIÓN ABRIL 24 v1'!F8 -> 0 | F7: ='PRESENTACIÓN Al 29 de mayo'!#REF! -> #REF! | H7: ='PRESENTACIÓN MARZO 24'!J8 -> 0 | I7: ='PRESENTACIÓN ABRIL 24 v1'!G8 -> 0 | J7: ='PRESENTACIÓN Al 29 de mayo'!E8 -> 171771292 | L7: ='PRESENTACIÓN MARZO 24'!L8 -> 0 | M7: ='PRESENTACIÓN ABRIL 24 v1'!H8 -> 0 | N7: ='PRESENTACIÓN Al 29 de mayo'!G8 -> 171771292
B8: Indirectos de Obra | D8: ='PRESENTACIÓN MARZO 24'!I9 -> 0 | E8: ='PRESENTACIÓN ABRIL 24 v1'!F9 -> 0 | F8: ='PRESENTACIÓN Al 29 de mayo'!#REF! -> #REF! | H8: ='PRESENTACIÓN MARZO 24'!J9 -> 0 | I8: ='PRESENTACIÓN ABRIL 24 v1'!G9 -> 0 | J8: ='PRESENTACIÓN Al 29 de mayo'!E9 -> 0 | L8: ='PRESENTACIÓN MARZO 24'!L9 -> 0 | M8: ='PRESENTACIÓN ABRIL 24 v1'!H9 -> 0 | N8: ='PRESENTACIÓN Al 29 de mayo'!G9 -> 0
B9: Total Costos Construcción | D9: ='PRESENTACIÓN MARZO 24'!I10 -> 9038515 | E9: ='PRESENTACIÓN ABRIL 24 v1'!F10 -> 2559924.8 | F9: ='PRESENTACIÓN Al 29 de mayo'!#REF! -> #REF! | H9: ='PRESENTACIÓN MARZO 24'!J10 -> 9038515 | I9: ='PRESENTACIÓN ABRIL 24 v1'!G10 -> 9038515.4 | J9: ='PRESENTACIÓN Al 29 de mayo'!E10 -> 1.8080981e+08 | L9: ='PRESENTACIÓN MARZO 24'!L10 -> 0 | M9: ='PRESENTACIÓN ABRIL 24 v1'!H10 -> 6478590.6 | N9: ='PRESENTACIÓN Al 29 de mayo'!G10 -> 171771292
B10: Gerencia de la Promotora | D10: ='PRESENTACIÓN MARZO 24'!I11 -> 0 | E10: ='PRESENTACIÓN ABRIL 24 v1'!F11 -> 0 | F10: ='PRESENTACIÓN Al 29 de mayo'!#REF! -> #REF! | H10: ='PRESENTACIÓN MARZO 24'!J11 -> 0 | I10: ='PRESENTACIÓN ABRIL 24 v1'!G11 -> 137416238 | J10: ='PRESENTACIÓN Al 29 de mayo'!E11 -> 137416238 | L10: ='PRESENTACIÓN MARZO 24'!L11 -> 0 | M10: ='PRESENTACIÓN ABRIL 24 v1'!H11 -> 137416238 | N10: ='PRESENTACIÓN Al 29 de mayo'!G11 -> 137416238
B11: Gerencia de Ventas | D11: ='PRESENTACIÓN MARZO 24'!I12 -> 0 | E11: ='PRESENTACIÓN ABRIL 24 v1'!F12 -> 0 | F11: ='PRESENTACIÓN Al 29 de mayo'!#REF! -> #REF! | H11: ='PRESENTACIÓN MARZO 24'!J12 -> 0 | I11: ='PRESENTACIÓN ABRIL 24 v1'!G12 -> 0 | J11: ='PRESENTACIÓN Al 29 de mayo'!E12 -> 35151584 | L11: ='PRESENTACIÓN MARZO 24'!L12 -> 0 | M11: ='PRESENTACIÓN ABRIL 24 v1'!H12 -> 0 | N11: ='PRESENTACIÓN Al 29 de mayo'!G12 -> 35151584
B12: Administración Fiducia | D12: ='PRESENTACIÓN MARZO 24'!I13 -> 0 | E12: ='PRESENTACIÓN ABRIL 24 v1'!F13 -> 0 | F12: ='PRESENTACIÓN Al 29 de mayo'!#REF! -> #REF! | H12: ='PRESENTACIÓN MARZO 24'!J13 -> 0 | I12: ='PRESENTACIÓN ABRIL 24 v1'!G13 -> 0 | J12: ='PRESENTACIÓN Al 29 de mayo'!E13 -> 0 | L12: ='PRESENTACIÓN MARZO 24'!L13 -> 0 | M12: ='PRESENTACIÓN ABRIL 24 v1'!H13 -> 0 | N12: ='PRESENTACIÓN Al 29 de mayo'!G13 -> 0
B13: Publicidad | D13: ='PRESENTACIÓN MARZO 24'!I14 -> 446334.38 | E13: ='PRESENTACIÓN ABRIL 24 v1'!F14 -> 0 | F13: ='PRESENTACIÓN Al 29 de mayo'!#REF! -> #REF! | H13: ='PRESENTACIÓN MARZO 24'!J14 -> 3786501.9 | I13: ='PRESENTACIÓN ABRIL 24 v1'!G14 -> 3786501.9 | J13: ='PRESENTACIÓN Al 29 de mayo'!E14 -> 3839208.5 | L13: ='PRESENTACIÓN MARZO 24'!L14 -> 3340167.5 | M13: ='PRESENTACIÓN ABRIL 24 v1'!H14 -> 3786501.9 | N13: ='PRESENTACIÓN Al 29 de mayo'!G14 -> 2390947.5
B14: Post Ventas | D14: ='PRESENTACIÓN MARZO 24'!I15 -> 0 | E14: ='PRESENTACIÓN ABRIL 24 v1'!F15 -> 0 | F14: ='PRESENTACIÓN Al 29 de mayo'!#REF! -> #REF! | H14: ='PRESENTACIÓN MARZO 24'!J15 -> 0 | I14: ='PRESENTACIÓN ABRIL 24 v1'!G15 -> 0 | J14: ='PRESENTACIÓN Al 29 de mayo'!E15 -> 0 | L14: ='PRESENTACIÓN MARZO 24'!L15 -> 0 | M14: ='PRESENTACIÓN ABRIL 24 v1'!H15 -> 0 | N14: ='PRESENTACIÓN Al 29 de mayo'!G15 -> 0
B15: Total Gastos Operativos | D15: ='PRESENTACIÓN MARZO 24'!I16 -> 446334.38 | E15: ='PRESENTACIÓN ABRIL 24 v1'!F16 -> 0 | F15: ='PRESENTACIÓN Al 29 de mayo'!#REF! -> #REF! | H15: ='PRESENTACIÓN MARZO 24'!J16 -> 3786501.9 | I15: ='PRESENTACIÓN ABRIL 24 v1'!G16 -> 1.4120274e+08 | J15: ='PRESENTACIÓN Al 29 de mayo'!E16 -> 1.7640703e+08 | L15: ='PRESENTACIÓN MARZO 24'!L16 -> 3340167.5 | M15: ='PRESENTACIÓN ABRIL 24 v1'!H16 -> 1.4120274e+08 | N15: ='PRESENTACIÓN Al 29 de mayo'!G16 -> 1.7495877e+08
B16: Permisos legales y Preliminares | D16: ='PRESENTACIÓN MARZO 24'!I17 -> 1576990 | E16: ='PRESENTACIÓN ABRIL 24 v1'!F17 -> 3634527.5 | F16: ='PRESENTACIÓN Al 29 de mayo'!#REF! -> #REF! | H16: ='PRESENTACIÓN MARZO 24'!J17 -> 13841815 | I16: ='PRESENTACIÓN ABRIL 24 v1'!G17 -> 3634527.5 | J16: ='PRESENTACIÓN Al 29 de mayo'!E17 -> 18740000 | L16: ='PRESENTACIÓN MARZO 24'!L17 -> 12264825 | M16: ='PRESENTACIÓN ABRIL 24 v1'!H17 -> 0 | N16: ='PRESENTACIÓN Al 29 de mayo'!G17 -> 13528482
B17: Diseño y Proyecto | D17: ='PRESENTACIÓN MARZO 24'!I18 -> 12246487 | E17: ='PRESENTACIÓN ABRIL 24 v1'!F18 -> 0 | F17: ='PRESENTACIÓN Al 29 de mayo'!#REF! -> #REF! | H17: ='PRESENTACIÓN MARZO 24'!J18 -> 20546016 | I17: ='PRESENTACIÓN ABRIL 24 v1'!G18 -> 20727336 | J17: ='PRESENTACIÓN Al 29 de mayo'!E18 -> 20727336 | L17: ='PRESENTACIÓN MARZO 24'!L18 -> 8299529.8 | M17: ='PRESENTACIÓN ABRIL 24 v1'!H18 -> 20727336 | N17: ='PRESENTACIÓN Al 29 de mayo'!G18 -> 8480849.8
... B20: Total Otros Gastos | D20: ='PRESENTACIÓN MARZO 24'!I21 -> 13823477 | E20: ='PRESENTACIÓN ABRIL 24 v1'!F21 -> 4644005.4 | F20: ='PRESENTACIÓN Al 29 de mayo'!#REF! -> #REF! | H20: ='PRESENTACIÓN MARZO 24'!J21 -> 34387831 | I20: ='PRESENTACIÓN ABRIL 24 v1'!G21 -> 27758815 | J20: ='PRESENTACIÓN Al 29 de mayo'!E21 -> 39467336 | L20: ='PRESENTACIÓN MARZO 24'!L21 -> 20564355 | M20: ='PRESENTACIÓN ABRIL 24 v1'!H21 -> 23114809 | N20: ='PRESENTACIÓN Al 29 de mayo'!G21 -> 22009332
B21: Costos Totales de Proyecto | D21: =D20+D15+D9+D4 -> 1.1952149e+08 | E21: ='PRESENTACIÓN ABRIL 24 v1'!F22 -> 103476099 | F21: ='PRESENTACIÓN Al 29 de mayo'!#REF! -> #REF! | H21: =H20+H15+H9+H4 -> 1.4342602e+08 | I21: ='PRESENTACIÓN ABRIL 24 v1'!G22 -> 2.7427224e+08 | J21: ='PRESENTACIÓN Al 29 de mayo'!E22 -> 4.9071621e+08 | L21: =H21-D21 -> 23904522 | M21: 23114809 | N21: ='PRESENTACIÓN Al 29 de mayo'!G22 -> 3.6879839e+08

Sheet budget (11)
A1: Código de Costo Nivel 1 | B1: Código de Costo Nivel 2 | C1: Código de Costo Nivel 3 | D1: Presupuesto Original | E1: Costos Comprometidos | F1: Costos de Trabajo a la Fecha | G1: Costos Proyectados | H1: Precio unitario del presupuesto | I1: Proyección para terminar | J1: Costo Estimado al Terminar | K1: Proyectado Arriba/Abajo del Presupuesto
A2: 1 - CONSTRUCCION | B2: 1-1 - TERRENO | C2: 1-1-1 - TERRENO ADI | D2: 7113000.3 | E2: 0 | F2: 0 | G2: 0 | H2: 7113000.3 | I2: 7113000.3 | J2: 7113000.3 | K2: 0
A3: 1 - CONSTRUCCION | B3: 1-1 - TERRENO | C3: 1-1-2 - COSTO ASOCIADO TERRENO | D3: 96272169 | E3: 94032040 | F3: 94032040 | G3: 94032040 | H3: 96272169 | I3: 2240128.9 | J3: 96272169 | K3: 0
A4: 1 - CONSTRUCCION | B4: 1-2 - DISEÑO Y PROYECTO | C4: 1-2-1 - DISEÑO Y PROYECTO ADI | D4: 62663.64 | E4: 0 | F4: 0 | G4: 0 | H4: 62663.64 | I4: 62663.64 | J4: 62663.64
A5: 1 - CONSTRUCCION | B5: 1-2 - DISEÑO Y PROYECTO | C5: 1-2-2 - ESTUDIOS | D5: 0 | E5: 0 | F5: 0 | G5: 0 | I5: 0 | J5: 0 | K5: 0
A6: 1 - CONSTRUCCION | B6: 1-2 - DISEÑO Y PROYECTO | C6: 1-2-2 - ESTUDIOS | D6: 5641221.5 | E6: 5641221.5 | F6: 0 | G6: 5641221.5 | H6: 5641221.5 | I6: 0 | J6: 5641221.5 | K6: 0
A7: 1 - CONSTRUCCION | B7: 1-2 - DISEÑO Y PROYECTO | C7: 1-2-3 - DISEÑO Y ARQUITECTURA | D7: 8785614.6 | E7: 8785614.6 | F7: 0 | G7: 8785614.6 | H7: 8785614.6 | I7: 0 | J7: 8785614.6 | K7: 0
A8: 1 - CONSTRUCCION | B8: 1-2 - DISEÑO Y PROYECTO | C8: 1-2-4 - INGENIERIAS | D8: 5932855.3 | E8: 5932855.3 | F8: 0 | G8: 5932855.3 | H8: 5932855.3 | I8: 0 | J8: 5932855.3 | K8: 0
A9: 1 - CONSTRUCCION | B9: 1-2 - DISEÑO Y PROYECTO | C9: 1-2-5 - COMPUTOS | D9: 367644.95 | E9: 367644.95 | F9: 0 | G9: 367644.95 | H9: 367644.95 | I9: 0 | J9: 367644.95 | K9: 0
A10: 1 - CONSTRUCCION | B10: 1-3 - PRELIMINARES DE OBRA. | C10: 1-3-2 - OBRAS PRELIMINARES AREA CAMPAMENTO | D10: 0 | E10: 0 | F10: 0 | G10: 0 | I10: 0 | J10: 0 | K10: 0
A11: 1 - CONSTRUCCION | B11: 1-4 - URBANISMO | C11: 1-4-1 - URBANISMO ADI | D11: 11813427 | E11: 0 | F11: 0 | G11: 0 | H11: 11813427 | I11: 11813427 | J11: 11813427 | K11: 0
A12: 1 - CONSTRUCCION | B12: 1-4 - URBANISMO | C12: 1-4-2 - PRELIMINARES ADI | D12: 2608627.8 | E12: 0 | F12: 0 | G12: 0 | H12: 2608627.8 | I12: 2608627.8 | J12: 2608627.8 | K12: 0
A13: 1 - CONSTRUCCION | B13: 1-4 - URBANISMO | C13: 1-4-3 - PRELIMINARES DE OBRA | D13: 1897166.4 | E13: 1897166.4 | F13: 1806285.8 | G13: 1897166.4 | H13: 1897166.4 | I13: 0 | J13: 1897166.4 | K13: 0
A14: 1 - CONSTRUCCION | B14: 1-4 - URBANISMO | C14: 1-4-3 - PRELIMINARES DE OBRA | D14: 7141349 | E14: 7141349 | F14: 3926696.7 | G14: 7141349 | H14: 7141349 | I14: 0 | J14: 7141349 | K14: 0
A15: 1 - CONSTRUCCION | B15: 1-4 - URBANISMO | C15: 1-4-4 - MOVIMIENTO DE TIERRA | D15: 54584720 | E15: 0 | F15: 0 | G15: 0 | H15: 54584720 | I15: 54584720 | J15: 54584720 | K15: 0
A16: 1 - CONSTRUCCION | B16: 1-4 - URBANISMO | C16: 1-4-5 - HIDROSANITARIAS | D16: 56232241 | E16: 0 | F16: 0 | G16: 0 | H16: 56232241 | I16: 56232241 | J16: 56232241 | K16: 0
A17: 1 - CONSTRUCCION | B17: 1-4 - URBANISMO | C17: 1-4-6 - SISTEMAS DE AGUAS | D17: 35679323 | E17: 0 | F17: 0 | G17: 0 | H17: 35679323 | I17: 35679323 | J17: 35679323 | K17: 0
A18: 1 - CONSTRUCCION | B18: 1-4 - URBANISMO | C18: 1-4-7 - INSFRAESTRUCTURA ELECTRICA | D18: 1.3513803e+08 | E18: 0 | F18: 0 | G18: 0 | H18: 1.3513803e+08 | I18: 1.3513803e+08 | J18: 1.3513803e+08 | K18: 0
A19: 1 - CONSTRUCCION | B19: 1-4 - URBANISMO | C19: 1-4-8 - INSTALACIONES DE GAS | D19: 8535640.9 | E19: 0 | F19: 0 | G19: 0 | H19: 8535640.9 | I19: 8535640.9 | J19: 8535640.9 | K19: 0
A20: 1 - CONSTRUCCION | B20: 1-4 - URBANISMO | C20: 1-4-9 - INSTALACIONES TELECOMUNICACIONES | D20: 14797543 | E20: 0 | F20: 0 | G20: 0 | H20: 14797543 | I20: 14797543 | J20: 14797543 | K20: 0
A21: 1 - CONSTRUCCION | B21: 1-4 - URBANISMO | C21: 1-4-10 - EQUIPAMIENTO URBANISMO | D21: 62873368 | E21: 0 | F21: 0 | G21: 0 | H21: 62873368 | I21: 62873368 | J21: 62873368 | K21: 0
A22: 1 - CONSTRUCCION | B22: 1-4 - URBANISMO | C22: 1-4-11 - VIALIDAD | D22: 26736232 | E22: 0 | F22: 0 | G22: 0 | H22: 26736232 | I22: 26736232 | J22: 26736232 | K22: 0
... A27: 1 - CONSTRUCCION | B27: 1-5 - EDIFICACIONES | C27: 1-5-3 - SUPERESTRUCTURA | D27: 2.8304295e+08 | E27: 0 | F27: 0 | G27: 0 | H27: 2.8304295e+08 | I27: 2.8304295e+08 | J27: 2.8304295e+08 | K27: 0
A28: 1 - CONSTRUCCION | B28: 1-5 - EDIFICACIONES | C28: 1-5-4 - INSTALACIONES ELECTRICAS | D28: 0 | E28: 0 | F28: 0 | G28: 0 | I28: 0 | J28: 0 | K28: 0
A29: 1 - CONSTRUCCION | B29: 1-5 - EDIFICACIONES | C29: 1-5-4 - INSTALACIONES ELECTRICAS | D29: 60439200 | E29: 0 | F29: 0 | G29: 0 | H29: 60439200 | I29: 60439200 | J29: 60439200 | K29: 0
A30: 1 - CONSTRUCCION | B30: 1-5 - EDIFICACIONES | C30: 1-5-5 - TELECOMUNICACIONES | D30: 8446912.3 | E30: 0 | F30: 0 | G30: 0 | H30: 8446912.3 | I30: 8446912.3 | J30: 8446912.3 | K30: 0
A31: 1 - CONSTRUCCION | B31: 1-5 - EDIFICACIONES | C31: 1-5-6 - INSTALACIONES SANITARIAS | D31: 1.0100749e+08 | E31: 0 | F31: 0 | G31: 0 | H31: 1.0100749e+08 | I31: 1.0100749e+08 | J31: 1.0100749e+08 | K31: 0
A32: 1 - CONSTRUCCION | B32: 1-5 - EDIFICACIONES | C32: 1-5-7 - INSTALACIONES MECANICAS | D32: 455797.65 | E32: 0 | F32: 0 | G32: 0 | H32: 455797.65 | I32: 455797.65 | J32: 455797.65 | K32: 0
A33: 1 - CONSTRUCCION | B33: 1-5 - EDIFICACIONES | C33: 1-5-8 - ALBANILERIA | D33: 79619986 | E33: 0 | F33: 0 | G33: 0 | H33: 79619986 | I33: 79619986 | J33: 79619986 | K33: 0
A34: 1 - CONSTRUCCION | B34: 1-5 - EDIFICACIONES | C34: 1-5-9 - HERRERIA | D34: 55148949 | E34: 0 | F34: 0 | G34: 0 | H34: 55148949 | I34: 55148949 | J34: 55148949 | K34: 0
A35: 1 - CONSTRUCCION | B35: 1-5 - EDIFICACIONES | C35: 1-5-10 - REVESTIMIENTO | D35: 1.7979257e+08 | E35: 0 | F35: 0 | G35: 0 | H35: 1.7979257e+08 | I35: 1.7979257e+08 | J35: 1.7979257e+08 | K35: 0
A36: 1 - CONSTRUCCION | B36: 1-5 - EDIFICACIONES | C36: 1-5-11 - CARPINTERIA | D36: 1.1340591e+08 | E36: 0 | F36: 0 | G36: 0 | H36: 1.1340591e+08 | I36: 1.1340591e+08 | J36: 1.1340591e+08 | K36: 0
A37: 1 - CONSTRUCCION | B37: 1-5 - EDIFICACIONES | C37: 1-5-12 - VENTANERIA | D37: 95070320 | E37: 0 | F37: 0 | G37: 0 | H37: 95070320 | I37: 95070320 | J37: 95070320 | K37: 0
A38: 1 - CONSTRUCCION | B38: 1-5 - EDIFICACIONES | C38: 1-5-13 - PINTURA | D38: 1.2190433e+08 | E38: 0 | F38: 0 | G38: 0 | H38: 1.2190433e+08 | I38: 1.2190433e+08 | J38: 1.2190433e+08 | K38: 0
A39: 1 - CONSTRUCCION | B39: 1-5 - EDIFICACIONES | C39: 1-5-14 - MISCELANEOS | D39: 74569125 | E39: 0 | F39: 0 | G39: 0 | H39: 74569125 | I39: 74569125 | J39: 74569125 | K39: 0
A40: 1 - CONSTRUCCION | B40: 1-6 - GERENCIA DE CONSTRUCCION | C40: 1-6-1 - GERENCIA DE CONSTRUCCION ADI | D40: 0 | E40: 0 | F40: 0 | G40: 0 | I40: 0 | J40: 0 | K40: 0
A41: 1 - CONSTRUCCION | B41: 1-6 - GERENCIA DE CONSTRUCCION | C41: 1-6-2 - COSTO GERENCIA DE CONSTRUCCION | D41: 171771292 | F41: 0 | G41: 0 | H41: 171771292 | I41: 171771292 | J41: 171771292 | K41: 0
A42: 1 - CONSTRUCCION | B42: 1-7 - INDIRECTOS DE OBRA | C42: 1-7-2 - COSTOS INDIRECTOS DE OBRA | D42: 34354258 | E42: 0 | F42: 0 | G42: 0 | H42: 34354258 | I42: 34354258 | J42: 34354258 | K42: 0
A43: 2 - OPERATIVO | B43: 2-1 - GERENCIA DE LA PROMOTORA | C43: 2-1-2 - COSTO GERENCIA DE LA PROMOTORA ADI | D43: 137417034 | E43: 137416238 | F43: 0 | G43: 137416238 | H43: 137417034 | I43: 796 | J43: 137417034 | K43: 0
A44: 2 - OPERATIVO | B44: 2-2 - GERENCIA DE VENTAS | C44: 2-2-1 - COSTO GERENCIA DE VENTAS | D44: 0 | E44: 0 | F44: 0 | G44: 0 | I44: 0 | J44: 0 | K44: 0
A45: 2 - OPERATIVO | B45: 2-2 - GERENCIA DE VENTAS | C45: 2-2-2 - ADMINISTRACION DE VENTAS | D45: 35151584 | E45: 0 | F45: 0 | G45: 0 | H45: 35151584 | I45: 35151584 | J45: 35151584 | K45: 0
A46: 2 - OPERATIVO | B46: 2-2 - GERENCIA DE VENTAS | C46: 2-2-3 - COMISIONES | D46: 246553335 | E46: 0 | F46: 0 | G46: 0 | H46: 246553335 | I46: 246553335 | J46: 246553335 | K46: 0
A47: 2 - OPERATIVO | B47: 2-3 - ADMINISTRACION DE FIDUCIARIA | C47: 2-3-2 - COSTO ADMINISTRACION DE FIDUCIARIA | D47: 67334346 | E47: 0 | F47: 0 | G47: 0 | H47: 67334346 | I47: 67334346 | J47: 67334346 | K47: 0
A48: 2 - OPERATIVO | B48: 2-4 - PUBLICIDAD Y PROMOCION | C48: 2-4-1 - PUBLICIDAD Y PROMOCION ADI | D48: 47692179 | E48: 0 | F48: 0 | G48: 0 | H48: 47692179 | I48: 47692179 | J48: 47692179 | K48: 0
A49: 2 - OPERATIVO | B49: 2-4 - PUBLICIDAD Y PROMOCION | C49: 2-4-2 - PUBLICIDAD Y PROMOCION | D49: 3839208.5 | E49: 3839208.5 | F49: 0 | G49: 3839208.5 | H49: 3839208.5 | I49: 0 | J49: 3839208.5 | K49: 0
A50: 2 - OPERATIVO | B50: 2-5 - POST-VENTAS | C50: 2-5-2 - POST-VENTAS | D50: 19238385 | E50: 0 | F50: 0 | G50: 0 | H50: 19238385 | I50: 19238385 | J50: 19238385 | K50: 0
A51: 3 - OTROS | B51: 3-1 - PERMISOS LEGALES Y PRELIMINARES | C51: 3-1-1 - PERMISOS LEGALES Y PRELIMINARES ADI | D51: 3396950.7 | E51: 0 | F51: 0 | G51: 0 | H51: 3396950.7 | I51: 3396950.7 | J51: 3396950.7 | K51: 0
A52: 3 - OTROS | B52: 3-1 - PERMISOS LEGALES Y PRELIMINARES | C52: 3-1-2 - PERMISOS LEGALES Y PRELIMINARES | D52: 11603049 | E52: 9481721.6 | F52: 4644005.4 | G52: 9481721.6 | H52: 11603049 | I52: 2121327.7 | J52: 11603049 | K52: 0
A53: 3 - OTROS | B53: 3-2 - IMPREVISTOS | C53: 3-2-2 - IMPREVISTOS | D53: 19238385 | E53: 0 | F53: 0 | G53: 0 | H53: 19238385 | I53: 19238385 | J53: 19238385 | K53: 0
A54: 3 - OTROS | B54: 3-3 - GASTOS FINANCIEROS | C54: 3-3-2 - GASTOS FINANCIEROS | D54: 192383847 | E54: 0 | F54: 0 | G54: 0 | H54: 192383847 | I54: 192383847 | J54: 192383847 | K54: 0
D55: =SUM(D2:D54) -> 2.8318619e+09 | E55: =SUM(E2:E54) -> 2.7453506e+08 | F55: =SUM(F2:F54) -> 1.0440903e+08 | G55: =SUM(G2:G54) -> 2.7453506e+08 | H55: =SUM(H2:H54) -> 2.8318619e+09 | I55: =SUM(I2:I54) -> 2.5573269e+09 | J55: =SUM(J2:J54) -> 2.8318619e+09 | K55: =SUM(K2:K54) -> 0

Sheet PRESENTACIÓN Al 29 de mayo
J1: IMAGEN DEL ADI archivo : Flujo_de_caja_PUNTA_CANA_462_MAR2024_V.0.XLSX al 02/05/24
E2: a | G2: d | H2: e
B3: PRESUPUESTO MAYO 2024 | D3: 59 | E3: COMPROMETIDO | F3: PAGADO | G3: POR EJECUTAR DE LO COMPROMETIDO | H3: PROYECTADO PARA TERMINAR
B4: PARTIDA | C4: DOP | D4: US $
A5: 1 | B5: Terreno | C5: =SUM('budget (11)'!D2:D3) -> 103385169 | D5: =C5/D3 -> 1752291 | E5: =SUM('budget (11)'!E2:E3) -> 94032040 | F5: 93973040 | G5: =E5-F5 -> 59000 | H5: =SUM('budget (11)'!I2:I3) -> 9353129.2 | I5: =C5-(E5+H5) -> 0
B6: Costo Urbanismo | C6: =SUM('budget (11)'!D11:D24) -> 4.51759e+08 | D6: =C6/$D$3 -> 7656932.2 | E6: =SUM('budget (11)'!E11:E24) -> 9038515.4 | F6: 9038515.4 | G6: =E6-F6 -> 0 | H6: =SUM('budget (11)'!I11:I24) -> 4.4272048e+08 | I6: =C6-(E6+H6) -> 0
B7: Costo Vivienda | C7: =SUM('budget (11)'!D25:D39) -> 1265953920 | D7: =C7/$D$3 -> 21456846 | E7: =SUM('budget (11)'!E25:E39) -> 0 | F7: 0 | G7: =E7-F7 -> 0 | H7: =SUM('budget (11)'!I25:I39) -> 1265953920 | I7: =C7-(E7+H7) -> 0
B8: Gerencia Construcción: | C8: =SUM('budget (11)'!D40:D41) -> 171771292 | D8: =C8/$D$3 -> 2911377.8 | E8: 171771292 | F8: 0 | G8: =E8-F8 -> 171771292 | H8: =SUM('budget (11)'!I40:I41) -> 171771292 | I8: =C8-(E8+H8) -> -171771292
B9: Indirectos de Obra | C9: =SUM('budget (11)'!D42) -> 34354258 | D9: =C9/$D$3 -> 582275.56 | E9: =SUM('budget (11)'!E42) -> 0 | F9: 0 | G9: =E9-F9 -> 0 | H9: =SUM('budget (11)'!I42) -> 34354258 | I9: =C9-(E9+H9) -> 0
B10: Total Costos Construcción | C10: =SUM(C6:C9) -> 1923838470 | D10: =SUM(D6:D9) -> 32607432 | E10: =SUM(E6:E9) -> 1.8080981e+08 | F10: =SUM(F6:F9) -> 9038515.4 | G10: =E10-F10 -> 171771292 | H10: =SUM(H6:H9) -> 1.9148e+09 | I10: =C10-(E10+H10) -> -171771292
B11: Gerencia de la Promotora | C11: =SUM('budget (11)'!D43) -> 137417034 | D11: =C11/$D$3 -> 2329102.3 | E11: =SUM('budget (11)'!E43) -> 137416238 | F11: 0 | G11: =E11-F11 -> 137416238 | H11: =SUM('budget (11)'!I43) -> 796 | I11: =C11-(E11+H11) -> 0
B12: Gerencia de Ventas | C12: =SUM('budget (11)'!D45:D46) -> 281704919 | D12: =C12/$D$3 -> 4774659.6 | E12: =1%*3515158425 -> 35151584 | F12: 0 | G12: =E12-F12 -> 35151584 | H12: =SUM('budget (11)'!I45:I46) -> 281704919 | I12: =C12-(E12+H12) -> -35151584
B13: Administración Fiducia | C13: =SUM('budget (11)'!D47) -> 67334346 | D13: =C13/$D$3 -> 1141260.1 | E13: =SUM('budget (11)'!E47) -> 0 | F13: 0 | G13: =E13-F13 -> 0 | H13: =SUM('budget (11)'!I47) -> 67334346 | I13: =C13-(E13+H13) -> 0
A14: 1 | B14: Publicidad | C14: =SUM('budget (11)'!D48:D49) -> 51531388 | D14: =C14/$D$3 -> 873413.36 | E14: =SUM('budget (11)'!E48:E49) -> 3839208.5 | F14: 1448261 | G14: =E14-F14 -> 2390947.5 | H14: =SUM('budget (11)'!I48:I49) -> 47692179 | I14: =C14-(E14+H14) -> 0
B15: Post Ventas | C15: =SUM('budget (11)'!D50) -> 19238385 | D15: =C15/$D$3 -> 326074.32 | E15: =SUM('budget (11)'!E50) -> 0 | F15: 0 | G15: =E15-F15 -> 0 | H15: =SUM('budget (11)'!I50) -> 19238385 | I15: =C15-(E15+H15) -> 0
B16: Total Gastos Operativos | C16: =SUM(C11:C15) -> 5.5722607e+08 | D16: =SUM(D11:D15) -> 9444509.7 | E16: =SUM(E11:E15) -> 1.7640703e+08 | F16: =SUM(F11:F15) -> 1448261 | G16: =E16-F16 -> 1.7495877e+08 | H16: =SUM(H11:H15) -> 4.1597063e+08 | I16: =C16-(E16+H16) -> -35151584
B17: Permisos legales y Preliminares | C17: =SUM('budget (11)'!D51:D52) -> 15000000 | D17: =C17/$D$3 -> 254237.29 | E17: =18740000 -> 18740000 | F17: 5211518.3 | G17: =E17-F17 -> 13528482 | H17: =SUM('budget (11)'!I51:I52) -> 5518278.4 | I17: =C17-(E17+H17) -> -9258278.4
B18: Diseño y Proyecto | C18: =SUM('budget (11)'!D4:D10) -> 20790000 | D18: =C18/$D$3 -> 352372.88 | E18: =SUM('budget (11)'!E4:E10) -> 20727336 | F18: 12246487 | G18: =E18-F18 -> 8480849.8 | H18: =SUM('budget (11)'!I4:I10) -> 62663.64 | I18: =C18-(E18+H18) -> 0
B19: Gastos Financieros | C19: =SUM('budget (11)'!D54) -> 192383847 | D19: =C19/$D$3 -> 3260743.2 | E19: =SUM('budget (11)'!E54) -> 0 | F19: 0 | G19: =E19-F19 -> 0 | H19: =SUM('budget (11)'!I54) -> 192383847 | I19: =C19-(E19+H19) -> 0
B20: Imprevistos | C20: =SUM('budget (11)'!D53) -> 19238385 | D20: =C20/$D$3 -> 326074.32 | E20: =SUM('budget (11)'!E53) -> 0 | F20: 0 | G20: =E20-F20 -> 0 | H20: =SUM('budget (11)'!I53) -> 19238385 | I20: =C20-(E20+H20) -> 0
B21: Total Otros Gastos | C21: =SUM(C17:C20) -> 247412232 | D21: =SUM(D17:D20) -> 4193427.7 | E21: =SUM(E17:E20) -> 39467336 | F21: =SUM(F17:F20) -> 17458005 | G21: =E21-F21 -> 22009332 | H21: =SUM(H17:H20) -> 2.1720317e+08 | I21: =C21-(E21+H21) -> -9258278.4
B22: TOTALES | C22: =C5+C10+C16+C21 -> 2.8318619e+09 | D22: =D5+D10+D16+D21 -> 47997660 | E22: =E21+E16+E10+E5 -> 4.9071621e+08 | F22: =F21+F16+F10+F5 -> 1.2191782e+08 | G22: =E22-F22 -> 3.6879839e+08 | H22: =H21+H16+H10+H5 -> 2.5573269e+09 | I22: =I21+I16+I10+I5 -> -2.1618115e+08
G23: =G17 -> 13528482
F24: 160000000 | H24: permisos por iniciar | K24: Dato del ADI | L24: 2.8318619e+09
F25: =F24-F22 -> 38082179 | G25: =E18-F18 -> 8480849.8 | H25: diseño por pagar | K25: Dato Procore | L25: =C22 -> 2.8318619e+09
F26: =SUM(G23:G26) -> 24400279 | G26: =E14-F14 -> 2390947.5 | H26: Publicidade por pagar | K26: Diferencia | L26: =L24-L25 -> -0.55799961
E27: diponible | F27: =F25-F26 -> 13681900
B30: Total Gastos Operativos
B31: Permisos legales y Preliminares
B32: Diseño y Proyecto
B33: Gastos Financieros
B34: Imprevistos
B35: Total Otros Gastos
B36: TOTALES
B39: APORTE AFI | C39: 160000000
B40: Gastado y comprometido | C40: =F22+F26 -> 1.463181e+08 | D40: =C40/C39 -> 0.91448813
B41: Disponible | C41: =C39-C40 -> 13681900 | D41: =C41/C39 -> 0.085511874

Sheet BG 2024
B2: Balance Sheet
B3: Fideicomiso Irrevocable de Desarrollo Inmobiliario y Administración Araya
B4: As at 31 May 2024
C6: Account | D6: 45443
B8: Assets
C9: Current Assets
C10: Anticipos a Proveedores | D10: 18577271
C11: Total Current Assets | D11: 18577271
C12: Non-current Assets
C13: Costos de Construccion | D13: 5732982.5
C14: Costos Operativos | D14: 201571.1
C15: Otros Costos (123906) | D15: 4442435.3
C16: Terreno | D16: 94032040
C17: Total Non-current Assets | D17: 1.0440903e+08
B18: Total Assets | D18: 1.229863e+08
B20: Liabilities
C21: Current Liabilities
C22: Cuentas por Pagar Comerciales | D22: 1068478.9
C23: Otras Cuentas por Pagar | D23: 1028476.6
C24: Total Current Liabilities | D24: 2096955.5
B25: Total Liabilities | D25: 2096955.5
C27: Net Assets | D27: 1.2088934e+08
B29: Equity
C30: Aporte Fideicomitente AFI Universal | D30: 1.2088934e+08
B31: Total Equity | D31: 1.2088934e+08

Sheet FLUJO Y DISPONIBLE
D2: 59.9
B3: 160000000 | C3: =B3-C4 -> 65967960 | D3: =C3-(SUM(D5:D8)) -> 41084982
B4: TERRENO | C4: 94032040
B5: DISENO Y PROYECTO | D5: =D10*$D$2 -> 9215810.2
B6: PRELIMINARES DEL PROYECTO | D6: =D11*$D$2 -> 781278.1
B7: PERMISOS | D7: =D12*$D$2 -> 11511124
B8: PUBLICIDAD | D8: =D13*$D$2 -> 3374766
D10: 153853.26
D11: 13043.04
D12: 192172.35
D13: 56340
C16: FECHA1 | D16: ACUMULADO MAY0 2024 | E16: 45444 | F16: 45474 | G16: 45505 | H16: 45536 | I16: 45566 | J16: 45597 | K16: 45627
B17: APORTE INICIAL | C17: 160000000
B18: DISPONIBLE | D18: =C17-D19 -> 41084982 | E18: =D18-E19 -> 40084982 | F18: =E18-F19 -> 39084982 | G18: =F18-G19 -> 38084982 | H18: =G18-H19 -> 37084982 | I18: =H18-I19 -> 36084982 | J18: =I18-J19 -> 35084982 | K18: =J18-K19 -> 34084982
B19: TOTAL GASTO | D19: =SUM(D21:D35) -> 1.1891502e+08 | E19: =SUM(E21:E35) -> 1000000 | F19: =SUM(F21:F35) -> 1000000 | G19: =SUM(G21:G35) -> 1000000 | H19: =SUM(H21:H35) -> 1000000 | I19: =SUM(I21:I35) -> 1000000 | J19: =SUM(J21:J35) -> 1000000 | K19: =SUM(K21:K35) -> 1000000
A21: ETAPA 0 | B21: TERRENO | D21: =C4 -> 94032040
B22: DISENO Y PROYECTO | D22: =D5 -> 9215810.2
B23: PRELIMINARES DEL PROYECTO | D23: =D6 -> 781278.1
B24: PERMISOS | D24: =D7 -> 11511124
B25: PUBLICIDAD | D25: =D8 -> 3374766
A29: ETAPA ARRANQUE | B29: GERENCIA CONSTRUCCIÓN | E29: 1000000 | F29: 1000000 | G29: 1000000 | H29: 1000000 | I29: 1000000 | J29: 1000000 | K29: 1000000

Sheet PRESENTACIÓN290524 ajuste
J1: IMAGEN DEL ADI archivo : Flujo_de_caja_PUNTA_CANA_462_MAR2024_V.0.XLSX al 02/05/24
B3: PRESUPUESTO MAYO 2024 | D3: 59 | E3: TOTAL EJECUTADO | F3: COMPROMETIDO | G3: POR EJECUTAR | H3: PROYECTADO PARA TERMINAR
B4: PARTIDA | C4: DOP | D4: US $
B5: Terreno | C5: =SUM('budget (11)'!D2:D3) -> 103385169 | D5: =C5/D3 -> 1752291 | E5: =SUM('budget (11)'!F2:F3) -> 94032040 | F5: =SUM('budget (11)'!E2:E3) -> 94032040 | G5: =F5-E5 -> 0 | H5: =SUM('budget (11)'!I2:I3) -> 9353129.2 | I5: =C5-(F5+H5) -> 0
B6: Costo Urbanismo | C6: =SUM('budget (11)'!D11:D24) -> 4.51759e+08 | D6: =C6/$D$3 -> 7656932.2 | E6: =SUM('budget (11)'!F11:F24) -> 5732982.5 | F6: =SUM('budget (11)'!E11:E24) -> 9038515.4 | G6: =F6-E6 -> 3305532.9 | H6: =SUM('budget (11)'!I11:I24) -> 4.4272048e+08 | I6: =C6-(F6+H6) -> 0
B7: Costo Vivienda | C7: =SUM('budget (11)'!D25:D39) -> 1265953920 | D7: =C7/$D$3 -> 21456846 | E7: =SUM('budget (11)'!F25:F39) -> 0 | F7: =SUM('budget (11)'!E25:E39) -> 0 | G7: =F7-E7 -> 0 | H7: =SUM('budget (11)'!I25:I39) -> 1265953920 | I7: =C7-(F7+H7) -> 0
B8: Gerencia Construcción: | C8: =SUM('budget (11)'!D40:D41) -> 171771292 | D8: =C8/$D$3 -> 2911377.8 | E8: =SUM('budget (11)'!F40:F41) -> 0 | F8: =SUM('budget (11)'!E40:E41) -> 0 | G8: =F8-E8 -> 0 | H8: =SUM('budget (11)'!I40:I41) -> 171771292 | I8: =C8-(F8+H8) -> 0
B9: Indirectos de Obra | C9: =SUM('budget (11)'!D42) -> 34354258 | D9: =C9/$D$3 -> 582275.56 | E9: =SUM('budget (11)'!F42) -> 0 | F9: =SUM('budget (11)'!E42) -> 0 | G9: =F9-E9 -> 0 | H9: =SUM('budget (11)'!I42) -> 34354258 | I9: =C9-(F9+H9) -> 0
B10: Total Costos Construcción | C10: =SUM(C6:C9) -> 1923838470 | D10: =SUM(D6:D9) -> 32607432 | E10: =SUM(E6:E9) -> 5732982.5 | F10: =SUM(F6:F9) -> 9038515.4 | G10: =F10-E10 -> 3305532.9 | H10: =SUM(H6:H9) -> 1.9148e+09 | I10: =C10-(F10+H10) -> 0
B11: Gerencia de la Promotora | C11: =SUM('budget (11)'!D43) -> 137417034 | D11: =C11/$D$3 -> 2329102.3 | E11: =SUM('budget (11)'!F43) -> 0 | F11: =SUM('budget (11)'!E43) -> 137416238 | G11: =F11-E11 -> 137416238 | H11: =SUM('budget (11)'!I43) -> 796 | I11: =C11-(F11+H11) -> 0
B12: Gerencia de Ventas | C12: =SUM('budget (11)'!D45:D46) -> 281704919 | D12: =C12/$D$3 -> 4774659.6 | E12: =SUM('budget (11)'!F45:F46) -> 0 | F12: =SUM('budget (11)'!E45:E46) -> 0 | G12: =F12-E12 -> 0 | H12: =SUM('budget (11)'!I45:I46) -> 281704919 | I12: =C12-(F12+H12) -> 0
B13: Administración Fiducia | C13: =SUM('budget (11)'!D47) -> 67334346 | D13: =C13/$D$3 -> 1141260.1 | E13: =SUM('budget (11)'!F47) -> 0 | F13: =SUM('budget (11)'!E47) -> 0 | G13: =F13-E13 -> 0 | H13: =SUM('budget (11)'!I47) -> 67334346 | I13: =C13-(F13+H13) -> 0
B14: Publicidad | C14: =SUM('budget (11)'!D48:D49) -> 51531388 | D14: =C14/$D$3 -> 873413.36 | E14: =SUM('budget (11)'!F48:F49) -> 0 | F14: =SUM('budget (11)'!E48:E49) -> 3839208.5 | G14: =F14-E14 -> 3839208.5 | H14: =SUM('budget (11)'!I48:I49) -> 47692179 | I14: =C14-(F14+H14) -> 0
B15: Post Ventas | C15: =SUM('budget (11)'!D50) -> 19238385 | D15: =C15/$D$3 -> 326074.32 | E15: =SUM('budget (11)'!F50) -> 0 | F15: =SUM('budget (11)'!E50) -> 0 | G15: =F15-E15 -> 0 | H15: =SUM('budget (11)'!I50) -> 19238385 | I15: =C15-(F15+H15) -> 0
B16: Total Gastos Operativos | C16: =SUM(C11:C15) -> 5.5722607e+08 | D16: =SUM(D11:D15) -> 9444509.7 | E16: =SUM(E11:E15) -> 0 | F16: =SUM(F11:F15) -> 1.4125545e+08 | G16: =F16-E16 -> 1.4125545e+08 | H16: =SUM(H11:H15) -> 4.1597063e+08 | I16: =C16-(F16+H16) -> 0
B17: Permisos legales y Preliminares | C17: =SUM('budget (11)'!D51:D52) -> 15000000 | D17: =C17/$D$3 -> 254237.29 | E17: =SUM('budget (11)'!F51:F52) -> 4644005.4 | F17: =SUM('budget (11)'!E51:E52) -> 9481721.6 | G17: =F17-E17 -> 4837716.2 | H17: =SUM('budget (11)'!I51:I52) -> 5518278.4 | I17: =C17-(F17+H17) -> 0
B18: Diseño y Proyecto | C18: =SUM('budget (11)'!D4:D10) -> 20790000 | D18: =C18/$D$3 -> 352372.88 | E18: =SUM('budget (11)'!F4:F10) -> 0 | F18: =SUM('budget (11)'!E4:E10) -> 20727336 | G18: =F18-E18 -> 20727336 | H18: =SUM('budget (11)'!I4:I10) -> 62663.64 | I18: =C18-(F18+H18) -> 0
B19: Gastos Financieros | C19: =SUM('budget (11)'!D54) -> 192383847 | D19: =C19/$D$3 -> 3260743.2 | E19: =SUM('budget (11)'!F54) -> 0 | F19: =SUM('budget (11)'!E54) -> 0 | G19: =F19-E19 -> 0 | H19: =SUM('budget (11)'!I54) -> 192383847 | I19: =C19-(F19+H19) -> 0
B20: Imprevistos | C20: =SUM('budget (11)'!D53) -> 19238385 | D20: =C20/$D$3 -> 326074.32 | E20: =SUM('budget (11)'!F53) -> 0 | F20: =SUM('budget (11)'!E53) -> 0 | G20: =F20-E20 -> 0 | H20: =SUM('budget (11)'!I53) -> 19238385 | I20: =C20-(F20+H20) -> 0
B21: Total Otros Gastos | C21: =SUM(C17:C20) -> 247412232 | D21: =SUM(D17:D20) -> 4193427.7 | E21: =SUM(E17:E20) -> 4644005.4 | F21: =SUM(F17:F20) -> 30209058 | G21: =F21-E21 -> 25565053 | H21: =SUM(H17:H20) -> 2.1720317e+08 | I21: =C21-(F21+H21) -> 0
B22: Costos Totales de Proyecto | C22: =C5+C10+C16+C21 -> 2.8318619e+09 | D22: =D5+D10+D16+D21 -> 47997660 | E22: =E21+E16+E10+E5 -> 1.0440903e+08 | F22: =F21+F16+F10+F5 -> 2.7453506e+08 | G22: =F22-E22 -> 1.7012603e+08 | H22: =H21+H16+H10+H5 -> 2.5573269e+09 | I22: =I21+I16+I10+I5 -> 0
H23: ='PRESENTACIÓN ABRIL 24 v1'!I22 -> 2.5576487e+09
K24: Dato del ADI | L24: 2.8318619e+09
K25: Dato Procore | L25: =C22 -> 2.8318619e+09
K26: Diferencia | L26: =L24-L25 -> -0.55799961
B30: ADELANTO AFI | C30: 160000000
B31: Gastado y comprometido
B32: Disponible | C32: =C30-C31 -> 160000000
B34: PARTIDA | C34: MES 1 | D34: MES 2 | E34: MES 3 | F34: MES 4 | G34: MES 5 | H34: MES 6 | I34: MES 7 | J34: MES 8 | K34: MES 9 | L34: Total
B35: gerencias | C35: 1000000 | D35: 1000000 | E35: 1000000 | F35: 1000000 | G35: 1000000 | H35: 1000000 | I35: 1000000 | J35: 1000000 | K35: 1000000 | L35: =SUM(C35:K35) -> 9000000
B36: promocion | C36: 500000 | D36: 500000 | E36: 500000 | F36: 500000 | G36: 500000 | H36: 500000 | I36: 500000 | J36: 500000 | K36: 500000 | L36: =SUM(C36:K36) -> 4500000
B37: atención al cliente | F37: 350000 | G37: 350000 | H37: 350000 | I37: 350000 | J37: 350000 | K37: 350000 | L37: =SUM(C37:K37) -> 2100000
C38: =SUM(C35:C37) -> 1500000 | D38: =SUM(D35:D37) -> 1500000 | E38: =SUM(E35:E37) -> 1500000 | F38: =SUM(F35:F37) -> 1850000 | G38: =SUM(G35:G37) -> 1850000 | H38: =SUM(H35:H37) -> 1850000 | I38: =SUM(I35:I37) -> 1850000 | J38: =SUM(J35:J37) -> 1850000 | K38: =SUM(K35:K37) -> 1850000
B39: Acumulado | D39: =C38+D38 -> 3000000 | E39: =D38+D39 -> 4500000 | F39: =E38+E39 -> 6000000 | G39: =F38+F39 -> 7850000 | H39: =G38+G39 -> 9700000 | I39: =H38+H39 -> 11550000 | J39: =I38+I39 -> 13400000 | K39: =J38+J39 -> 15250000
B41: Disponible | C41: =$C$32-C38 -> 158500000 | D41: =$C$32-D39 -> 157000000 | E41: =$C$32-E39 -> 155500000 | F41: =$C$32-F39 -> 154000000 | G41: =$C$32-G39 -> 152150000 | H41: =$C$32-H39 -> 150300000 | I41: =$C$32-I39 -> 148450000 | J41: =$C$32-J39 -> 146600000 | K41: =$C$32-K39 -> 144750000
K43: =1500000*59 -> 88500000
K44: =K43*3% -> 2655000
C45: 160000000 | K45: 2800000
C46: 119521495 | K46: =SUM(K44:K45) -> 5455000
C47: =C45-C46 -> 40478505
C49: =C47-K44-K46 -> 32368505
C57: =36000/873000 -> 0.041237113

Sheet FLUJO Y DISPONIBLE (2)
D2: 59.9
B3: 160000000 | C3: =B3-C4 -> 65967960 | D3: =C3-(SUM(D5:D8)) -> 41084982
B4: TERRENO | C4: 94032040
B5: DISENO Y PROYECTO | D5: =D10*$D$2 -> 9215810.2
B6: PRELIMINARES DEL PROYECTO | D6: =D11*$D$2 -> 781278.1
B7: PERMISOS | D7: =D12*$D$2 -> 11511124
B8: PUBLICIDAD | D8: =D13*$D$2 -> 3374766
D10: 153853.26
D11: 13043.04
D12: 192172.35
D13: 56340
C16: FECHA1 | D16: ACUMULADO MAY0 2024 | E16: 45444 | F16: 45474 | G16: 45505 | H16: 45536 | I16: 45566 | J16: 45597 | K16: 45627
B17: APORTE INICIAL | C17: 160000000
B18: DISPONIBLE | D18: =C17-D19 -> 38082179 | E18: =D18-E19 -> 19932179 | F18: =E18-F19 -> 9682178.9 | G18: =F18-G19 -> 2432178.9 | H18: =G18-H19 -> -1717821.1 | I18: =H18-I19 -> -3467821.1 | J18: =I18-J19 -> -5217821.1 | K18: =J18-K19 -> -6967821.1
B19: TOTAL GASTO | D19: =SUM(D21:D34) -> 1.2191782e+08 | E19: =SUM(E21:E34) -> 18150000 | F19: =SUM(F21:F34) -> 10250000 | G19: =SUM(G21:G34) -> 7250000 | H19: =SUM(H21:H34) -> 4150000 | I19: =SUM(I21:I34) -> 1750000 | J19: =SUM(J21:J34) -> 1750000 | K19: =SUM(K21:K34) -> 1750000
B21: TERRENO | D21: ='PRESENTACIÓN Al 29 de mayo'!$F$5 -> 93973040
B22: DISENO Y PROYECTO | D22: ='PRESENTACIÓN Al 29 de mayo'!$F$18 -> 12246487 | E22: 3000000 | F22: 3000000 | G22: 3000000
B23: PRELIMINARES DEL PROYECTO | D23: ='PRESENTACIÓN Al 29 de mayo'!$F$17 -> 5211518.3 | E23: 6000000 | F23: 6000000
B24: URBANISMO | D24: ='PRESENTACIÓN Al 29 de mayo'!$F$6 -> 9038515.4
B25: PUBLICIDAD | D25: ='PRESENTACIÓN Al 29 de mayo'!$F$14 -> 1448261 | H25: 2400000
B28: Gerencia de Construcción | E28: 750000 | F28: 750000 | G28: 750000 | H28: 750000 | I28: 750000 | J28: 750000 | K28: 750000
B29: Impuesto de transferencia | E29: 2700000
B30: IFC (lote 1 y lote 2) | E30: 3000000
B31: Comisión de terreno (Lote 1 y 2) | E31: 2700000
B32: Atención al cliente | F32: 500000 | G32: 500000 | H32: 500000 | I32: 500000 | J32: 500000 | K32: 500000
B33: Promocion | G33: 3000000 | H33: 500000 | I33: 500000 | J33: 500000 | K33: 500000
E36: =SUM(E28:E35) -> 9150000
B42: 4837716.2
B43: 6800000 | C43: permisos por iniciar
B44: 8480849.8 | C44: diseño por pagar
B45: 2390947.5 | C45: Publicidade por pagar
B46: =SUM(B42:B45) -> 22509514

Sheet PRESENTACIÓN Al 30062024
J1: IMAGEN DEL ADI archivo : Flujo_de_caja_PUNTA_CANA_462_MAR2024_V.0.XLSX al 02/05/24
E2: a | G2: d | H2: e
B3: PRESUPUESTO JUNIO 2024 | D3: 59 | E3: COMPROMETIDO | F3: PAGADO | G3: POR EJECUTAR DE LO COMPROMETIDO | H3: PROYECTADO PARA TERMINAR
B4: PARTIDA | C4: DOP | D4: US $
A5: 1 | B5: Terreno | C5: =SUM('budget (11)'!D2:D3) -> 103385169 | D5: =C5/D3 -> 1752291 | E5: =+'Finanzas 06.24'!L48+7030718.17 -> 94172342 | F5: =+'Finanzas 06.24'!G48+7030718.17 -> 93973040 | G5: =E5-F5 -> 199302 | H5: =+#REF!-7030718.17 -> #REF! | I5: =C5-(E5+H5) -> #REF!
B6: Costo Urbanismo | C6: =SUM('budget (11)'!D11:D24) -> 4.51759e+08 | D6: =C6/$D$3 -> 7656932.2 | E6: =+'Finanzas 06.24'!L53 -> 9038515.4 | F6: =+'Finanzas 06.24'!G53 -> 9038515.4 | G6: =E6-F6 -> 0 | H6: =+#REF! -> #REF! | I6: =C6-(E6+H6) -> #REF!
B7: Costo Vivienda | C7: =SUM('budget (11)'!D25:D39) -> 1265953920 | D7: =C7/$D$3 -> 21456846 | E7: =SUM('budget (11)'!E25:E39) -> 0 | F7: 0 | G7: =E7-F7 -> 0 | H7: =+#REF! -> #REF! | I7: =C7-(E7+H7) -> #REF!
B8: Gerencia Construcción: | C8: =SUM('budget (11)'!D40:D41) -> 171771292 | D8: =C8/$D$3 -> 2911377.8 | E8: =+'Finanzas 06.24'!L27 -> 171771292 | F8: 0 | G8: =E8-F8 -> 171771292 | H8: =+#REF! -> #REF! | I8: =C8-(E8+H8) -> #REF!
B9: Indirectos de Obra | C9: =SUM('budget (11)'!D42) -> 34354258 | D9: =C9/$D$3 -> 582275.56 | E9: =SUM('budget (11)'!E42) -> 0 | F9: 0 | G9: =E9-F9 -> 0 | H9: =+#REF! -> #REF! | I9: =C9-(E9+H9) -> #REF!
B10: Total Costos Construcción | C10: =SUM(C6:C9) -> 1923838470 | D10: =SUM(D6:D9) -> 32607432 | E10: =SUM(E6:E9) -> 1.8080981e+08 | F10: =SUM(F6:F9) -> 9038515.4 | G10: =E10-F10 -> 171771292 | H10: =SUM(H6:H9) -> #REF! | I10: =C10-(E10+H10) -> #REF!
B11: Gerencia de la Promotora | C11: =SUM('budget (11)'!D43) -> 137417034 | D11: =C11/$D$3 -> 2329102.3 | E11: =+'Finanzas 06.24'!L29 -> 137416238 | F11: =+'Finanzas 06.24'!G29 -> 0 | G11: =E11-F11 -> 137416238 | H11: =+#REF! -> #REF! | I11: =C11-(E11+H11) -> #REF!
B12: Gerencia de Ventas | C12: =SUM('budget (11)'!D45:D46) -> 281704919 | D12: =C12/$D$3 -> 4774659.6 | E12: =+'Finanzas 06.24'!L31 -> 35155869 | F12: =+'Finanzas 06.24'!G31 -> 0 | G12: =E12-F12 -> 35155869 | H12: =+#REF! -> #REF! | I12: =C12-(E12+H12) -> #REF!
B13: Administración Fiducia | C13: =SUM('budget (11)'!D47) -> 67334346 | D13: =C13/$D$3 -> 1141260.1 | E13: =+'Finanzas 06.24'!L2 -> 237853.9 | F13: =+'Finanzas 06.24'!G2 -> 0 | G13: =E13-F13 -> 237853.9 | H13: =+#REF! -> #REF! | I13: =C13-(E13+H13) -> #REF!
A14: 1 | B14: Publicidad | C14: =SUM('budget (11)'!D48:D49) -> 51531388 | D14: =C14/$D$3 -> 873413.36 | E14: =+GETPIVOTDATA("Suma de Costos Comprometidos",'Resumen de Costos Comprometidos'!$A$3,"Código de costo Nivel 2","2-4 - PUBLICIDAD Y PROMOCION") -> 3654563 | F14: =+'Finanzas 06.24'!G43 -> 1896969.5 | G14: =E14-F14 -> 1757593.5 | H14: =+#REF! -> #REF! | I14: =C14-(E14+H14) -> #REF!
B15: Post Ventas | C15: =SUM('budget (11)'!D50) -> 19238385 | D15: =C15/$D$3 -> 326074.32 | E15: =SUM('budget (11)'!E50) -> 0 | F15: 0 | G15: =E15-F15 -> 0 | H15: =+#REF! -> #REF! | I15: =C15-(E15+H15) -> #REF!
B16: Total Gastos Operativos | C16: =SUM(C11:C15) -> 5.5722607e+08 | D16: =SUM(D11:D15) -> 9444509.7 | E16: =SUM(E11:E15) -> 1.7646452e+08 | F16: =SUM(F11:F15) -> 1896969.5 | G16: =E16-F16 -> 1.7456755e+08 | H16: =SUM(H11:H15) -> #REF! | I16: =C16-(E16+H16) -> #REF!
B17: Permisos legales y Preliminares | C17: =SUM('budget (11)'!D51:D52) -> 15000000 | D17: =C17/$D$3 -> 254237.29 | E17: 18740000 | F17: =+'Finanzas 06.24'!G33 -> 7858239.6 | G17: =E17-F17 -> 10881760 | H17: =+#REF! -> #REF! | I17: =C17-(E17+H17) -> #REF!
B18: Diseño y Proyecto | C18: =SUM('budget (11)'!D4:D10) -> 20790000 | D18: =C18/$D$3 -> 352372.88 | E18: 20727336 | F18: =+'Finanzas 06.24'!G4 -> 13343403 | G18: =E18-F18 -> 7383933.1 | H18: =+#REF! -> #REF! | I18: =C18-(E18+H18) -> #REF!
B19: Gastos Financieros | C19: =SUM('budget (11)'!D54) -> 192383847 | D19: =C19/$D$3 -> 3260743.2 | E19: =SUM('budget (11)'!E54) -> 0 | F19: 0 | G19: =E19-F19 -> 0 | H19: =+#REF! -> #REF! | I19: =C19-(E19+H19) -> #REF!
B20: Imprevistos | C20: =SUM('budget (11)'!D53) -> 19238385 | D20: =C20/$D$3 -> 326074.32 | E20: =SUM('budget (11)'!E53) -> 0 | F20: 0 | G20: =E20-F20 -> 0 | H20: =+#REF! -> #REF! | I20: =C20-(E20+H20) -> #REF!
B21: Total Otros Gastos | C21: =SUM(C17:C20) -> 247412232 | D21: =SUM(D17:D20) -> 4193427.7 | E21: =SUM(E17:E20) -> 39467336 | F21: =SUM(F17:F20) -> 21201643 | G21: =E21-F21 -> 18265693 | H21: =SUM(H17:H20) -> #REF! | I21: =C21-(E21+H21) -> #REF!
B22: TOTALES | C22: =C5+C10+C16+C21 -> 2.8318619e+09 | D22: =D5+D10+D16+D21 -> 47997660 | E22: =E21+E16+E10+E5 -> 4.9091401e+08 | F22: =F21+F16+F10+F5 -> 1.2611017e+08 | G22: =E22-F22 -> 3.6480384e+08 | H22: =H21+H16+H10+H5 -> #REF! | I22: =I21+I16+I10+I5 -> #REF!
G23: =G17 -> 10881760
F24: 160000000 | H24: permisos por iniciar | K24: Dato del ADI | L24: 2.8318619e+09
F25: =F24-F22 -> 33889833 | G25: =E18-F18 -> 7383933.1 | H25: diseño por pagar | K25: Dato Procore | L25: =C22 -> 2.8318619e+09
F26: =+G13+G14+G17+G18 -> 20261141 | G26: =E14-F14 -> 1757593.5 | H26: Publicidade por pagar | K26: Diferencia | L26: =L24-L25 -> -0.55799961
E27: diponible | F27: =F25-F26 -> 13628692
B30: Total Gastos Operativos
B31: Permisos legales y Preliminares
B32: Diseño y Proyecto
B33: Gastos Financieros
B34: Imprevistos
B35: Total Otros Gastos
B36: TOTALES
B39: APORTE AFI | C39: 160000000
B40: Gastado y comprometido | C40: =F22+F26 -> 1.4637131e+08 | D40: =C40/C39 -> 0.91482068
B41: Disponible | C41: =C39-C40 -> 13628692 | D41: =C41/C39 -> 0.085179324

Sheet Finanzas 06.24
A1: Budget Code > Cost Code Tier 2 Description | B1: Budget Code > Cost Code Tier 2 | C1: Budget Line Item > Original Budget Amount | D1: Commitment > Number | E1: Commitment > Title | F1: Commitment > Payment Terms | G1: Commitment > Payments Issued | H1: Commitment > Percent Paid | I1: Company (Vendor) > Name | J1: Commitment Line Item > Number | K1: Commitment Line Item > Description | L1: Commitment Line Item > Amount
A2: ADMINISTRACION DE FIDUCIARIA | C2: 67334346 | G2: 0 | L2: =SUM(L3) -> 237853.9
B3: 3 | C3: 67334346 | D3: PO--003 | E3: REEMBOLSO GASTOS POR LA PROMOTORA | G3: 0 | I3: GRUPO BAK SRL | J3: 2 | K3: REEMBOLSO COMISION POR ESTRUCTURACION FT B0100006940 | L3: 237853.9
A4: DISEÑO Y PROYECTO | C4: 20727336 | G4: =SUM(G5:G26) -> 13343403 | L4: =SUM(L5:L26) -> 19952058
B5: 2 | C5: 8785614.6 | D5: SC--007 | E5: Conceptuales y Diseños (Diseno y Proyecto) | G5: 928260 | I5: INVERSIONES BRICKET C A | J5: 1 | K5: Conceptuales y Diseños | L5: 1998189
B6: 2 | C6: 8785614.6 | D6: SC--013 | E6: Proyecto de Planta de Tratamiento (Diseno y Proyecto) | G6: 458400 | I6: CONPROIN C A | J6: 1 | K6: Proyecto de Planta de Tratamiento | L6: 586456
B7: 2 | C7: 8785614.6 | D7: SC--006 | E7: Diseño Arquitectonico de Edificios y Urb (Diseno y Proyecto) | G7: 2521200 | I7: CONTEXTO URBANO | J7: 1 | K7: Diseño Arqutectonico de Edificios y Urb | L7: 4876762
B8: 2 | C8: 8785614.6 | D8: PO--013 | E8: REEMBOLSO GASTOS VARIOS ARAYA ENE-ABR-24 | G8: 0 | I8: GRUPO BAK SRL | J8: 1 | K8: RESPONSABILIDAD ARQUITECTONICA ONEIDA FRIAS | L8: 65555.56
B9: 2 | C9: 8785614.6 | D9: SC--002 | E9: Replanteo de Edificios, Vias y Recreativas (Diseno y proyecto) | G9: 53226.25 | I9: FRANCISCO AQUINO & ASOCIADOS SRL | J9: 1 | K9: Replanteo de Edificios, Vias y Recreativas | L9: 130588.15
B10: 2 | C10: 8785614.6 | D10: SC--003 | E10: Diseño Vial y Terraceria | G10: 276500 | I10: FRANCISCO AQUINO & ASOCIADOS SRL | J10: 1 | K10: Diseño Vial y Terraceria | L10: 678380
B11: 2 | C11: 8785614.6 | D11: SC--014 | E11: ANDRES MONTERO LANDSCAPE ARCHITECTURE( Paisajismo) (Diseno y Proyecto) | G11: 247800 | I11: ANDRES MONTERO LANDSCAPE ARCHITECTURE | J11: 1 | K11: LANDSCAPE ARCHITECTURE( Paisajismo) | L11: 315239.4
B12: 2 | C12: 6300500.3 | D12: SC--016 | E12: Ajustes en Calculos cambios en diseño y Computos BIM | G12: 434969.03 | I12: CONCONCRETOS PROYECTOS S A S | L12: 686637.2
B13: 2 | C13: 5932855.3 | D13: SC--025 | E13: Diseno Estructural de Portal entrada, Portería, Comunal piscina, Comunal Gimnasio,Comunal social | G13: 0 | I13: DISENOS ESTRUCTURALES AL LIMITE D E L SRL | J13: 1 | K13: Calculo Estructural de Portal entrada, Portería, Comunal Social, Comunal Gimnasio,Comunal Piscina | L13: 252520
B14: 2 | C14: 5932855.3 | D14: SC--008 | E14: Diseño EstructuralEdificios (Diseno y Proyecto) | G14: 3305186.6 | I14: CONCONCRETOS PROYECTOS S A S | J14: 1 | K14: Diseño EstructuralEdificios | L14: 3825551.1
B15: 2 | C15: 5932855.3 | D15: SC--022 | E15: Calculo estructural del tanque de agua y redes (Diseno y Proyecto) | G15: 0 | I15: DISENOS ESTRUCTURALES AL LIMITE D E L SRL | J15: 1 | K15: Calculo estructural del tanque de agua y redes | L15: 135700
B16: 2 | C16: 5932855.3 | D16: SC--020 | E16: Diseño de Drenaje, sistema de impulsion | G16: 0 | I16: CONCONCRETOS PROYECTOS S A S | J16: 1 | K16: Diseño de Drenaje, sistema de impulsion | L16: 164685.57
B17: 2 | C17: 5932855.3 | D17: SC--026 | E17: Sistema de Tratado de Agua Potable (Diseno y Proyecto) | G17: 174050 | I17: COMPAÑIA OPERADORA DEL AGUA TECCA SAS | J17: 1 | K17: Sistema de Tratado de Agua Potable | L17: 348690
B18: 2 | C18: 5932855.3 | D18: SC--012 | E18: Estructura de Planta de Tratamiento y PISCINAS(ninosy adultos) ( (Diseno y Proyecto) | G18: 72726 | I18: DISENOS ESTRUCTURALES AL LIMITE D E L SRL | J18: 1 | K18: Estructura de Planta de Tratamiento | L18: 81420
B19: 2 | C19: 5932855.3 | D19: SC--041 | E19: Redes Electricas Internas Areas Comunes (Portería, Comunal Piscina, Comunal Social y Comunal Gimnasio) | G19: 0 | I19: ALETHIA ASPACIA CRUZ DE RUIZ 001-1629463-8 | J19: 1 | K19: REDES ELECTRICAS AREAS COMUNES | L19: 10000
B20: 2 | C20: 5932855.3 | D20: SC--027 | E20: DISEÑO REDES DE ÁREAS COMUNES | G20: 0 | I20: SiHiSa | J20: 1 | K20: Diseno Redes COMUNAL PISCINA,SOCIAL,GYM;PISCINAS Y PORTERIA | L20: 154462
B21: 2 | C21: 5641221.5 | D21: SC--005 | E21: Estudio de Infiltracion y Extraccion (Diseno y Proyecto) | G21: 247600 | I21: PERFORADO DOMINICANO SRL | J21: 1 | K21: Estudio de Infiltracion y Extraccion | L21: 288628
B22: 2 | C22: 5641221.5 | D22: SC--034 | E22: Estudio de Trafico | G22: 762810.83 | I22: GRUPO ICAT SRL | J22: 1 | K22: Estudio de Trafico | L22: 881242.59
B23: 2 | C23: 5641221.5 | D23: SC--033 | E23: Estudio de Impacto Ambiental | G23: 409320 | I23: ECOTURISMO MUNDIAL Y PROYECTOS AMBIENTALES SRL(EMPACA) | J23: 1 | K23: Estudio de Impacto Ambiental | L23: 820656
B24: 2 | C24: 5641221.5 | D24: SC--018 | E24: Re estudio del agua por Infiltración Debil y calidad del agua (Diseno y Proyecto) | G24: 273000 | I24: HIDROPOZO SRL | J24: 1 | K24: Re estudio del agua por Infiltracion Debil y calidad del agua | L24: 278099.52
... B26: 2 | C26: 5641221.5 | D26: SC--004 | E26: Estudio de Suelos y Diseño de Pavimento (Diseno y proyecto) | G26: 2792626.4 | I26: STEFAN ALVAREZ & ASOCIADOS, SRL | J26: 1 | K26: Estudio de Suelos y Diseño de Pavimento | L26: 2926553.4
A27: GERENCIA DE CONSTRUCCION | C27: 171771292 | G27: =+G28 -> 0 | L27: =SUM(L28) -> 171771292
B28: 6 | C28: 171771292 | D28: SC--039 | E28: GERENCIA DE CONSTRUCCION ARAYA | I28: TECNICA MMHB SRL RNC 130-67304-7 | J28: 1 | K28: GERENCIA DE CONSTRUCCION | L28: 171771292
A29: GERENCIA DE LA PROMOTORA | C29: 137417034 | G29: =+G30 -> 0 | L29: =SUM(L30:L30) -> 137416238
B30: 1 | C30: 137417034 | D30: SC--038 | E30: GERENCIA DE ADMINISTRACION | G30: 0 | I30: GRUPO BAK SRL | J30: 1 | K30: GERENCIA DE ADMINISTRACION | L30: 137416238
A31: GERENCIA DE VENTAS | C31: 35151584 | G31: =+G32 -> 0 | L31: =SUM(L32) -> 35155869
B32: 2 | C32: 35151584 | D32: SC--040 | E32: GERENCIA DE VENTAS | G32: 0 | I32: ACERVO INMOBILIARIO SRL | J32: 1 | K32: GERENCIA DE VENTAS | L32: 35155869
A33: PERMISOS LEGALES Y PRELIMINARES | C33: 11603049 | G33: =SUM(G34:G42) -> 7858239.6 | L33: =SUM(L34:L42) -> 12074455
B34: 1 | C34: 11603049 | D34: PO--010 | E34: DERECHO USO DEL AGUA PARA LA CONSTRUCCION | G34: 2638181.1 | I34: INSTITUTO NACIONAL DE AGUAS POTABLES Y ALCANTARILLADOS | J34: 1 | K34: DERECHO USO DEL AGUA PARA LA CONSTRUCCION | L34: 2638181.1
B35: 1 | C35: 11603049 | D35: PO--006 | E35: PERMISO USO DE SUELO | G35: 1290711 | I35: AYUNTAMIENTO DE HIGUEY | J35: 1 | K35: PERMISO USO DE SUELO AYUNTAMIENTO | L35: 1290711
B36: 1 | C36: 11603049 | D36: PO--009 | E36: PERMISO USO DE SUELO | G36: 1293711.6 | I36: DISTRITO MUNICIPAL TURISTICO VERON PUNTA CANA | J36: 1 | K36: PERMISO AYUNTAMIENTO VERON | L36: 1293711.6
B37: 1 | C37: 11603049 | D37: PO--007 | E37: REVISION AMBIENTAL ARAYA | G37: 1050104.3 | I37: MINISTERIO DE MEDIO AMBIENTE Y RECURSOS NATURALES | J37: 1 | K37: REVISION AUTORIZACION AMBIENTAL | L37: 3500347.7
B38: 1 | C38: 11603049 | D38: SC--031 | E38: Limpieza y Desbroce (Preliminares del proyecto) | G38: 231472.06 | I38: REMIX S A | J38: 1 | K38: Limpieza y Desbroce (Preliminares de Proyecto) | L38: 585972.87
B39: 1 | C39: 11603049 | D39: PO--008 | E39: COPIA DE PLANOS | G39: 0 | I39: CENTRO COPIADORA NACO S R L | J39: 1 | K39: COPIA DE PLANOS | L39: 7741.85
B40: 1 | C40: 11603049 | D40: PO--003 | E40: REEMBOLSO GASTOS POR LA PROMOTORA | G40: 0 | I40: GRUPO BAK SRL | J40: 1 | K40: REEMBOLSO GASTOS POR LA PROMOTORA | L40: 865638.1
B41: 1 | C41: 11603049 | D41: SC--032 | E41: Relleno de caliche para estudio de suelos (Preliminares del proyecto) | G41: 1354059.5 | I41: REMIX S A | J41: 1 | K41: Relleno de caliche para estudio de suelos (Preliminares del proyecto) | L41: 1801499.9
B42: 1 | C42: 11603049 | D42: PO--013 | E42: REEMBOLSO GASTOS VARIOS ARAYA ENE-ABR-24 | G42: 0 | I42: GRUPO BAK SRL | J42: 2 | K42: REEMBOLSO GASTOS DE PERMISOLOGIAS | L42: 90650.57
A43: PUBLICIDAD Y PROMOCION | C43: 3839208.5 | G43: =SUM(G44:G47) -> 1896969.5 | L43: =SUM(L44:L47) -> 3654563
B44: 4 | C44: 3839208.5 | D44: PO--002 | E44: LANZAMIENTO COMERCIAL Y VALIDACION DE PRODUCTO | G44: 222000 | I44: PANAMERICAN CREATIVE MINDS INC | J44: 2 | K44: VALIDACION DE PRODUCTO | L44: 752475
B45: 4 | C45: 3839208.5 | D45: SC--030 | E45: RENDERS | G45: 88920 | I45: RANCEL SANTIAGO VASQUEZ AZAR | J45: 1 | K45: RENDERS | L45: 145920
B46: 4 | C46: 3839208.5 | D46: PO--002 | E46: LANZAMIENTO COMERCIAL Y VALIDACION DE PRODUCTO | G46: =707326.5-222000 -> 485326.5 | I46: PANAMERICAN CREATIVE MINDS INC | J46: 1 | K46: LANZAMIENTO COMERCIAL | L46: 1655445
B47: 4 | C47: 3839208.5 | D47: SC--028 | E47: ARQUETIPO DE MARCA PROPUESTA DE LOGO ETC | G47: 1100723 | I47: EM2 ENTERTAINMENT SAS | J47: 1 | K47: ARQUETIPO DE MARCA PROPUESTA DE LOGO ETC | L47: 1100723
A48: TERRENO | C48: 96272169 | G48: =SUM(G49:G52) -> 86942322 | L48: =SUM(L49:L52) -> 87141624
B49: 1 | C49: 96272169 | D49: PO--013 | E49: REEMBOLSO GASTOS VARIOS ARAYA ENE-ABR-24 | G49: 0 | I49: GRUPO BAK SRL | J49: 3 | K49: REEMBOLSO FT CORTINA B0100000825 TASACION TERRENO | L49: 106200
B50: 1 | C50: 96272169 | D50: PO--012 | E50: TASACION TERRENO | G50: 0 | I50: CORTINA RUA SRL | J50: 1 | K50: TASACION TERRENO | L50: 59000
B51: 1 | C51: 96272169 | D51: PO--011 | E51: TASACION DE TERRENO | G51: 0 | I51: INGENIERIA AVANZADA SRL | J51: 1 | K51: TASACION TERRENO | L51: 34102
B52: 1 | C52: 96272169 | D52: SC--029 | E52: LOTE 1 TERRENO ARAYA | G52: 86942322 | I52: ADMINISTRADORA DE FONDOS DE INVERSION UNIVERSAL S A | J52: 1 | K52: APORTE TERRENO LOTE 1 | L52: 86942322
A53: URBANISMO | C53: 9038515.4 | G53: =SUM(G54:G55) -> 9038515.4 | L53: =SUM(L54:L55) -> 9038515.4
B54: 4 | C54: 7141349 | D54: SC--037 | E54: Preliminares de obra-Showroom | G54: =+L54 -> 7141349 | I54: TECNICA MMHB SRL RNC 130-67304-7 | J54: 1 | K54: Obras preliminares showrroom | L54: 7141349
B55: 4 | C55: 1897166.4 | D55: SC--036 | E55: Preliminares de obra-Instalaciones provisionales-campamento | G55: =+L55 -> 1897166.4 | I55: TECNICA MMHB SRL RNC 130-67304-7 | J55: 1 | K55: obras preliminares area campamento | L55: 1897166.4
A56: Grand Totals | C56: 5.5315453e+08 | G56: =+G2+G4+G27+G29+G31+G33+G43+G48+G53 -> 1.1907945e+08 | H56: =+H2+H4+H27+H29+H31+H33+H43+H48+H53 -> 0 | I56: =+I2+I4+I27+I29+I31+I33+I43+I48+I53 -> 0 | J56: =+J2+J4+J27+J29+J31+J33+J43+J48+J53 -> 0 | K56: =+K2+K4+K27+K29+K31+K33+K43+K48+K53 -> 0 | L56: =+L2+L4+L27+L29+L31+L33+L43+L48+L53 -> 4.7644247e+08

Sheet FLUJO Y DISPONIBLE (3)
D2: 59.9
B3: 160000000 | C3: =B3-C4 -> 65967960 | D3: =C3-(SUM(D5:D8)) -> 41084982
B4: TERRENO | C4: 94032040
B5: DISENO Y PROYECTO | D5: =D10*$D$2 -> 9215810.2
B6: PRELIMINARES DEL PROYECTO | D6: =D11*$D$2 -> 781278.1
B7: PERMISOS | D7: =D12*$D$2 -> 11511124
B8: PUBLICIDAD | D8: =D13*$D$2 -> 3374766
D10: 153853.26
D11: 13043.04
D12: 192172.35
D13: 56340
C16: FECHA1 | D16: ACUMULADO JULIO 2024 | E16: 45505 | F16: 45536 | G16: 45566 | H16: 45597 | I16: 45627 | J16: 45658 | K16: 45689
B17: APORTE INICIAL | C17: 160000000
B18: DISPONIBLE | D18: =C17-D19 -> 25726926 | E18: =D18-E19 -> 15519576 | F18: =E18-F19 -> 3489656.2 | G18: =F18-G19 -> -3868013.8 | H18: =G18-H19 -> -6268933.8 | I18: =H18-I19 -> -8342053.8 | J18: =I18-J19 -> -10415174 | K18: =J18-K19 -> -12488294
B19: TOTAL GASTO | D19: =SUM(D21:D31) -> 1.3427307e+08 | E19: =SUM(E21:E31) -> 10207350 | F19: =SUM(F21:F31) -> 12029920 | G19: =SUM(G21:G31) -> 7357670 | H19: =SUM(H21:H31) -> 2400920 | I19: =SUM(I21:I31) -> 2073120 | J19: =SUM(J21:J31) -> 2073120 | K19: =SUM(K21:K31) -> 2073120
B21: TERRENO | D21: =+'PRESENTACIÓN Al 31072024'!I5 -> 94172342
B22: DISENO Y PROYECTO | D22: =+'PRESENTACIÓN Al 31072024'!I18 -> 17077188 | E22: 1500000 | F22: 1500000
B23: PRELIMINARES DEL PROYECTO | D23: =+'PRESENTACIÓN Al 31072024'!I17+'PRESENTACIÓN Al 31072024'!I13 -> 10816750 | E23: 2000000 | F23: 2000000 | G23: 4100000
B24: URBANISMO | D24: =+'PRESENTACIÓN Al 31072024'!I6 -> 9038515.3 | E24: 3700000
B25: PROMOCION Y PUBLICIDAD | D25: =+'PRESENTACIÓN Al 31072024'!I14 -> 2228058.5 | E25: =37875*59.6 -> 2257350 | F25: =80200*59.6 -> 4779920 | G25: =42075*59.6 -> 2507670 | H25: =27700*59.6 -> 1650920 | I25: =22200*59.6 -> 1323120 | J25: =22200*59.6 -> 1323120 | K25: =22200*59.6 -> 1323120
B28: Gerencias | D28: =+'PRESENTACIÓN Al 31072024'!I8+'PRESENTACIÓN Al 31072024'!I11 -> 940220.11 | E28: 750000 | F28: 750000 | G28: 750000 | H28: 750000 | I28: 750000 | J28: 750000 | K28: 750000
B29: Impuesto de transferencia
B30: IFC (lote 1 y lote 2) | F30: 3000000
E33: =SUM(E28:E32) -> 750000
B39: 4837716.2
B40: 6800000 | C40: permisos por iniciar
B41: 8480849.8 | C41: diseño por pagar
B42: 2390947.5 | C42: Publicidade por pagar
B43: =SUM(B39:B42) -> 22509514

Sheet Resumen de Costos Comprometidos
A3: Etiquetas de fila | B3: Suma de Presupuesto Proyectado | C3: Suma de Costos Comprometidos | D3: Suma de Costos de Trabajo a la Fecha
A4: 1-1 - TERRENO | B4: 103385169 | C4: 87141624 | D4: 87141624
A5: 1-2 - DISEÑO Y PROYECTO | B5: 20590000 | C5: 19952058 | D5: 8175286.8
A6: 1-3 - PRELIMINARES DE OBRA. | B6: 0 | C6: 0 | D6: 0
A7: 1-4 - URBANISMO | B7: 4.51759e+08 | C7: 9038515.4 | D7: 7467449.3
A8: 1-5 - EDIFICACIONES | B8: 1265953920 | C8: 0 | D8: 0
A9: 1-6 - GERENCIA DE CONSTRUCCION | B9: 171771292 | C9: 171771292 | D9: 776107.84
A10: 1-7 - INDIRECTOS DE OBRA | B10: 34354258 | C10: 0 | D10: 0
A11: 2-1 - GERENCIA DE LA PROMOTORA | B11: 137417034 | C11: 137416238 | D11: 161175.97
A12: 2-2 - GERENCIA DE VENTAS | B12: 281704919 | C12: 35155869 | D12: 0
A13: 2-3 - ADMINISTRACION DE FIDUCIARIA | B13: 67334346 | C13: 237853.9 | D13: 237853.9
A14: 2-4 - PUBLICIDAD Y PROMOCION | B14: 51531388 | C14: 3654563 | D14: 2285058.5
A15: 2-5 - POST-VENTAS | B15: 19238385 | C15: 0 | D15: 0
... A19: Total general | B19: 2.8316619e+09 | C19: 4.7644247e+08 | D19: 1.1404127e+08

Sheet budget
A1: Subproyecto | B1: Código de costo Nivel 1 | C1: Código de costo Nivel 2 | D1: Código de costo Nivel 3 | E1: Código de costo Nivel 4 | F1: Código de costo Nivel 5 | G1: Tipo de costo | H1: Budget Code | I1: Budget Code Description | J1: Presupuesto Original | K1: Modificaciones de Presupuesto | L1: OC Aprobadas | M1: Presupuesto Revisado | N1: Cambios Pendientes al Presupuesto | O1: Presupuesto Proyectado | P1: Costos Comprometidos | Q1: Costos indirectos | R1: Costos de Trabajo a la Fecha | S1: Cambios Pendientes al Costo | T1: Costos Proyectados | U1: Cantidad por unidad del presupuesto | V1: Unidad de medida del presupuesto | W1: Precio unitario del presupuesto | X1: Proyección para terminar | Y1: Costo Estimado al Terminar
A2: Ninguno | B2: 1 - CONSTRUCCION | C2: 1-1 - TERRENO | D2: 1-1-1 - TERRENO ADI | E2: 1-1-1-MTOTALTE - TERRENO ADI | F2: Ninguno | G2: T - Total | H2: 1-1-1-MTOTALTE.T | I2: TERRENO ADI.Total | J2: 7113000.3 | K2: 0 | L2: 0 | M2: 7113000.3 | N2: 0 | O2: 7113000.3 | P2: 0 | Q2: 0 | R2: 0 | S2: 0 | T2: 0 | U2: 1 | W2: 7113000.3 | X2: 7113000.3 | Y2: 7113000.3
A3: Ninguno | B3: 1 - CONSTRUCCION | C3: 1-1 - TERRENO | D3: 1-1-2 - COSTO ASOCIADO TERRENO | E3: 1-1-2-COSTTE - COSTO ASOCIADO TERRENO | F3: Ninguno | G3: T - Total | H3: 1-1-2-COSTTE.T | I3: COSTO ASOCIADO TERRENO.Total | J3: 96272169 | K3: 0 | L3: 0 | M3: 96272169 | N3: 0 | O3: 96272169 | P3: 87141624 | Q3: 0 | R3: 87141624 | S3: 0 | T3: 94172342 | U3: 1 | V3: suma global | W3: 96272169 | X3: 2099826.9 | Y3: 96272169
A4: Ninguno | B4: 1 - CONSTRUCCION | C4: 1-2 - DISEÑO Y PROYECTO | D4: 1-2-1 - DISEÑO Y PROYECTO ADI | E4: 1-2-1-MTOTALDP - DISEÑO Y PROYECTO ADI | F4: Ninguno | G4: T - Total | H4: 1-2-1-MTOTALDP.T | I4: DISEÑO Y PROYECTO ADI.Total | J4: 62663.64 | K4: 0 | L4: 0 | M4: 62663.64 | N4: 0 | O4: 62663.64 | P4: 0 | Q4: 0 | R4: 0 | S4: 0 | T4: 0 | U4: 1 | V4: suma global | W4: 62663.64 | X4: 62663.64 | Y4: 62663.64
A5: Ninguno | B5: 1 - CONSTRUCCION | C5: 1-2 - DISEÑO Y PROYECTO | D5: 1-2-2 - ESTUDIOS | E5: 1-2-2-DIPRO01 - ESTUDIOS | F5: Ninguno | G5: OT - Otros | H5: 1-2-2-DIPRO01.OT | I5: ESTUDIOS.Otros | J5: 0 | K5: 0 | L5: 0 | M5: 0 | N5: 0 | O5: 0 | P5: 0 | Q5: 0 | R5: 0 | S5: 0 | T5: 0 | X5: 0 | Y5: 0
A6: Ninguno | B6: 1 - CONSTRUCCION | C6: 1-2 - DISEÑO Y PROYECTO | D6: 1-2-2 - ESTUDIOS | E6: 1-2-2-DIPRO01 - ESTUDIOS | F6: Ninguno | G6: T - Total | H6: 1-2-2-DIPRO01.T | I6: ESTUDIOS.Total | J6: 5641221.5 | K6: 0 | L6: 0 | M6: 5641221.5 | N6: 0 | O6: 5641221.5 | P6: 5641221.5 | Q6: 0 | R6: 2120698.7 | S6: 0 | T6: 5641221.5 | U6: 1 | V6: suma global | W6: 5641221.5 | X6: 0 | Y6: 5641221.5
A7: Ninguno | B7: 1 - CONSTRUCCION | C7: 1-2 - DISEÑO Y PROYECTO | D7: 1-2-3 - DISEÑO Y ARQUITECTURA | E7: 1-2-3-DIPRO02 - DISEÑO Y ARQUITECTURA | F7: Ninguno | G7: T - Total | H7: 1-2-3-DIPRO02.T | I7: DISEÑO Y ARQUITECTURA.Total | J7: 8785614.6 | K7: 0 | L7: 0 | M7: 8785614.6 | N7: 0 | O7: 8585614.6 | P7: 8651170.1 | Q7: 0 | R7: 1460979.7 | S7: 0 | T7: 8651170.1 | U7: 1 | V7: suma global | W7: 8585614.6 | X7: 0 | Y7: 8651170.1
A8: Ninguno | B8: 1 - CONSTRUCCION | C8: 1-2 - DISEÑO Y PROYECTO | D8: 1-2-4 - INGENIERIAS | E8: 1-2-4-DIPRO03 - INGENIERIAS | F8: Ninguno | G8: T - Total | H8: 1-2-4-DIPRO03.T | I8: INGENIERIAS.Total | J8: 5932855.3 | K8: 0 | L8: 0 | M8: 5932855.3 | N8: 0 | O8: 5932855.3 | P8: 5340673.7 | Q8: 0 | R8: 4274616.1 | S8: 0 | T8: 5340673.7 | U8: 1 | V8: suma global | W8: 5932855.3 | X8: 592181.68 | Y8: 5932855.3
A9: Ninguno | B9: 1 - CONSTRUCCION | C9: 1-2 - DISEÑO Y PROYECTO | D9: 1-2-5 - COMPUTOS | E9: 1-2-5-DIPRO04 - COMPUTOS | F9: Ninguno | G9: T - Total | H9: 1-2-5-DIPRO04.T | I9: COMPUTOS.Total | J9: 367644.95 | K9: 0 | L9: 0 | M9: 367644.95 | N9: 0 | O9: 367644.95 | P9: 318992.25 | Q9: 0 | R9: 318992.25 | S9: 0 | T9: 318992.25 | U9: 1 | V9: suma global | W9: 367644.95 | X9: 48652.7 | Y9: 367644.95
A10: Ninguno | B10: 1 - CONSTRUCCION | C10: 1-3 - PRELIMINARES DE OBRA. | D10: 1-3-2 - OBRAS PRELIMINARES AREA CAMPAMENTO | E10: 1-3-2-1 - OBRAS PRELIMINARES AREA CAMPAMENTO | F10: Ninguno | G10: T - Total | H10: 1-3-2-1.T | I10: OBRAS PRELIMINARES AREA CAMPAMENTO.Total | J10: 0 | K10: 0 | L10: 0 | M10: 0 | N10: 0 | O10: 0 | P10: 0 | Q10: 0 | R10: 0 | S10: 0 | T10: 0 | X10: 0 | Y10: 0
A11: Ninguno | B11: 1 - CONSTRUCCION | C11: 1-4 - URBANISMO | D11: 1-4-1 - URBANISMO ADI | E11: 1-4-1-MTOTALURB - URBANISMO ADI | F11: Ninguno | G11: T - Total | H11: 1-4-1-MTOTALURB.T | I11: URBANISMO ADI.Total | J11: 11813427 | K11: 0 | L11: 0 | M11: 11813427 | N11: 0 | O11: 11813427 | P11: 0 | Q11: 0 | R11: 0 | S11: 0 | T11: 0 | U11: 1 | V11: suma global | W11: 11813427 | X11: 11813427 | Y11: 11813427
A12: Ninguno | B12: 1 - CONSTRUCCION | C12: 1-4 - URBANISMO | D12: 1-4-2 - PRELIMINARES ADI | E12: 1-4-2-MTOTALPRELI - PRELIMINARES ADI | F12: Ninguno | G12: T - Total | H12: 1-4-2-MTOTALPRELI.T | I12: PRELIMINARES ADI.Total | J12: 2608627.8 | K12: 0 | L12: 0 | M12: 2608627.8 | N12: 0 | O12: 2608627.8 | P12: 0 | Q12: 0 | R12: 0 | S12: 0 | T12: 0 | U12: 1 | W12: 2608627.8 | X12: 2608627.8 | Y12: 2608627.8
A13: Ninguno | B13: 1 - CONSTRUCCION | C13: 1-4 - URBANISMO | D13: 1-4-3 - PRELIMINARES DE OBRA | E13: 1-4-3-PRELIMOBRA1 - PRELIMINARES AREA CAMPAMENTO | F13: Ninguno | G13: T - Total | H13: 1-4-3-PRELIMOBRA1.T | I13: PRELIMINARES AREA CAMPAMENTO.Total | J13: 1897166.4 | K13: 0 | L13: 0 | M13: 1897166.4 | N13: 0 | O13: 1897166.4 | P13: 1897166.4 | Q13: 0 | R13: 1897166.4 | S13: 0 | T13: 1897166.4 | U13: 1 | W13: 1897166.4 | X13: 0 | Y13: 1897166.4
A14: Ninguno | B14: 1 - CONSTRUCCION | C14: 1-4 - URBANISMO | D14: 1-4-3 - PRELIMINARES DE OBRA | E14: 1-4-3-PRELIMOBRA2 - PRELIMINARES AREA SHOWROOM | F14: Ninguno | G14: T - Total | H14: 1-4-3-PRELIMOBRA2.T | I14: PRELIMINARES AREA SHOWROOM.Total | J14: 7141349 | K14: 0 | L14: 0 | M14: 7141349 | N14: 0 | O14: 7141349 | P14: 7141349 | Q14: 0 | R14: 5570282.9 | S14: 0 | T14: 7141349 | U14: 1 | W14: 7141349 | X14: 0 | Y14: 7141349
A15: Ninguno | B15: 1 - CONSTRUCCION | C15: 1-4 - URBANISMO | D15: 1-4-4 - MOVIMIENTO DE TIERRA | E15: 1-4-4-URB01 - MOVIMIENTO DE TIERRA | F15: Ninguno | G15: T - Total | H15: 1-4-4-URB01.T | I15: MOVIMIENTO DE TIERRA.Total | J15: 54584720 | K15: 0 | L15: 0 | M15: 54584720 | N15: 0 | O15: 54584720 | P15: 0 | Q15: 0 | R15: 0 | S15: 0 | T15: 0 | U15: 1 | V15: suma global | W15: 54584720 | X15: 54584720 | Y15: 54584720
A16: Ninguno | B16: 1 - CONSTRUCCION | C16: 1-4 - URBANISMO | D16: 1-4-5 - HIDROSANITARIAS | E16: 1-4-5-URB02 - HIDROSANITARIAS | F16: Ninguno | G16: T - Total | H16: 1-4-5-URB02.T | I16: HIDROSANITARIAS.Total | J16: 56232241 | K16: 0 | L16: 0 | M16: 56232241 | N16: 0 | O16: 56232241 | P16: 0 | Q16: 0 | R16: 0 | S16: 0 | T16: 0 | U16: 1 | V16: suma global | W16: 56232241 | X16: 56232241 | Y16: 56232241
A17: Ninguno | B17: 1 - CONSTRUCCION | C17: 1-4 - URBANISMO | D17: 1-4-6 - SISTEMAS DE AGUAS | E17: 1-4-6-URB03 - SISTEMA DE AGUAS | F17: Ninguno | G17: T - Total | H17: 1-4-6-URB03.T | I17: SISTEMA DE AGUAS.Total | J17: 35679323 | K17: 0 | L17: 0 | M17: 35679323 | N17: 0 | O17: 35679323 | P17: 0 | Q17: 0 | R17: 0 | S17: 0 | T17: 0 | U17: 1 | V17: suma global | W17: 35679323 | X17: 35679323 | Y17: 35679323
A18: Ninguno | B18: 1 - CONSTRUCCION | C18: 1-4 - URBANISMO | D18: 1-4-7 - INSFRAESTRUCTURA ELECTRICA | E18: 1-4-7-URB04 - INSFRAESTRUCTURA ELECTRICA | F18: Ninguno | G18: T - Total | H18: 1-4-7-URB04.T | I18: INSFRAESTRUCTURA ELECTRICA.Total | J18: 1.3513803e+08 | K18: 0 | L18: 0 | M18: 1.3513803e+08 | N18: 0 | O18: 1.3513803e+08 | P18: 0 | Q18: 0 | R18: 0 | S18: 0 | T18: 0 | U18: 1 | V18: suma global | W18: 1.3513803e+08 | X18: 1.3513803e+08 | Y18: 1.3513803e+08
A19: Ninguno | B19: 1 - CONSTRUCCION | C19: 1-4 - URBANISMO | D19: 1-4-8 - INSTALACIONES DE GAS | E19: 1-4-8-URB05 - INSTALACIONES DE GAS | F19: Ninguno | G19: T - Total | H19: 1-4-8-URB05.T | I19: INSTALACIONES DE GAS.Total | J19: 8535640.9 | K19: 0 | L19: 0 | M19: 8535640.9 | N19: 0 | O19: 8535640.9 | P19: 0 | Q19: 0 | R19: 0 | S19: 0 | T19: 0 | U19: 1 | V19: suma global | W19: 8535640.9 | X19: 8535640.9 | Y19: 8535640.9
A20: Ninguno | B20: 1 - CONSTRUCCION | C20: 1-4 - URBANISMO | D20: 1-4-9 - INSTALACIONES TELECOMUNICACIONES | E20: 1-4-9-URB6 - INSTALACIONES TELECOMUNICACIONES | F20: Ninguno | G20: T - Total | H20: 1-4-9-URB6.T | I20: INSTALACIONES TELECOMUNICACIONES.Total | J20: 14797543 | K20: 0 | L20: 0 | M20: 14797543 | N20: 0 | O20: 14797543 | P20: 0 | Q20: 0 | R20: 0 | S20: 0 | T20: 0 | U20: 1 | V20: suma global | W20: 14797543 | X20: 14797543 | Y20: 14797543
A21: Ninguno | B21: 1 - CONSTRUCCION | C21: 1-4 - URBANISMO | D21: 1-4-10 - EQUIPAMIENTO URBANISMO | E21: 1-4-10-URB7 - EQUIPAMIENTO URBANO | F21: Ninguno | G21: T - Total | H21: 1-4-10-URB7.T | I21: EQUIPAMIENTO URBANO.Total | J21: 62873368 | K21: 0 | L21: 0 | M21: 62873368 | N21: 0 | O21: 62873368 | P21: 0 | Q21: 0 | R21: 0 | S21: 0 | T21: 0 | U21: 1 | V21: suma global | W21: 62873368 | X21: 62873368 | Y21: 62873368
A22: Ninguno | B22: 1 - CONSTRUCCION | C22: 1-4 - URBANISMO | D22: 1-4-11 - VIALIDAD | E22: 1-4-11-URB8 - VIALIDAD | F22: Ninguno | G22: T - Total | H22: 1-4-11-URB8.T | I22: VIALIDAD.Total | J22: 26736232 | K22: 0 | L22: 0 | M22: 26736232 | N22: 0 | O22: 26736232 | P22: 0 | Q22: 0 | R22: 0 | S22: 0 | T22: 0 | U22: 1 | V22: suma global | W22: 26736232 | X22: 26736232 | Y22: 26736232
A23: Ninguno | B23: 1 - CONSTRUCCION | C23: 1-4 - URBANISMO | D23: 1-4-12 - PAISAJISMO | E23: 1-4-12-URB9 - PAISAJISMO | F23: Ninguno | G23: T - Total | H23: 1-4-12-URB9.T | I23: PAISAJISMO.Total | J23: 27763646 | K23: 0 | L23: 0 | M23: 27763646 | N23: 0 | O23: 27763646 | P23: 0 | Q23: 0 | R23: 0 | S23: 0 | T23: 0 | U23: 1 | W23: 27763646 | X23: 27763646 | Y23: 27763646
A24: Ninguno | B24: 1 - CONSTRUCCION | C24: 1-4 - URBANISMO | D24: 1-4-13 - OBRAS EXTERIORES | E24: 1-4-13-URB10 - OBRAS EXTERIORES | F24: Ninguno | G24: T - Total | H24: 1-4-13-URB10.T | I24: OBRAS EXTERIORES.Total | J24: 5957690 | K24: 0 | L24: 0 | M24: 5957690 | N24: 0 | O24: 5957690 | P24: 0 | Q24: 0 | R24: 0 | S24: 0 | T24: 0 | U24: 1 | W24: 5957690 | X24: 5957690 | Y24: 5957690
A25: Ninguno | B25: 1 - CONSTRUCCION | C25: 1-5 - EDIFICACIONES | D25: 1-5-1 - EDIFICACIONES ADI | E25: 1-5-1-MTOTALEDIF - EDIFICACIONES ADI | F25: 1-5-1-MTOTALEDIF-MTOTALEDIF - EDIFICACIONES ADI | G25: T - Total | H25: 1-5-1-MTOTALEDIF-MTOTALEDIF.T | I25: EDIFICACIONES ADI.Total | J25: 7612585 | K25: 0 | L25: 0 | M25: 7612585 | N25: 0 | O25: 7612585 | P25: 0 | Q25: 0 | R25: 0 | S25: 0 | T25: 0 | U25: 1 | V25: suma global | W25: 7612585 | X25: 7612585 | Y25: 7612585
A26: Ninguno | B26: 1 - CONSTRUCCION | C26: 1-5 - EDIFICACIONES | D26: 1-5-2 - INSFRAESTRUCTURA | E26: 1-5-2-EDIF02 - INSFRAESTRUCTURA | F26: Ninguno | G26: T - Total | H26: 1-5-2-EDIF02.T | I26: INSFRAESTRUCTURA.Total | J26: 85437792 | K26: 0 | L26: 0 | M26: 85437792 | N26: 0 | O26: 85437792 | P26: 0 | Q26: 0 | R26: 0 | S26: 0 | T26: 0 | U26: 1 | V26: suma global | W26: 85437792 | X26: 85437792 | Y26: 85437792
A27: Ninguno | B27: 1 - CONSTRUCCION | C27: 1-5 - EDIFICACIONES | D27: 1-5-3 - SUPERESTRUCTURA | E27: 1-5-3-EDIF02 - SUPERESTRUCTURA | F27: Ninguno | G27: T - Total | H27: 1-5-3-EDIF02.T | I27: SUPERESTRUCTURA.Total | J27: 2.8304295e+08 | K27: 0 | L27: 0 | M27: 2.8304295e+08 | N27: 0 | O27: 2.8304295e+08 | P27: 0 | Q27: 0 | R27: 0 | S27: 0 | T27: 0 | U27: 1 | V27: suma global | W27: 2.8304295e+08 | X27: 2.8304295e+08 | Y27: 2.8304295e+08
A28: Ninguno | B28: 1 - CONSTRUCCION | C28: 1-5 - EDIFICACIONES | D28: 1-5-4 - INSTALACIONES ELECTRICAS | E28: 1-5-4-EDIF04 - INSTALACIONES ELECTRICAS | F28: Ninguno | G28: OT - Otros | H28: 1-5-4-EDIF04.OT | I28: INSTALACIONES ELECTRICAS.Otros | J28: 0 | K28: 0 | L28: 0 | M28: 0 | N28: 0 | O28: 0 | P28: 0 | Q28: 0 | R28: 0 | S28: 0 | T28: 0 | X28: 0 | Y28: 0
A29: Ninguno | B29: 1 - CONSTRUCCION | C29: 1-5 - EDIFICACIONES | D29: 1-5-4 - INSTALACIONES ELECTRICAS | E29: 1-5-4-EDIF04 - INSTALACIONES ELECTRICAS | F29: Ninguno | G29: T - Total | H29: 1-5-4-EDIF04.T | I29: INSTALACIONES ELECTRICAS.Total | J29: 60439200 | K29: 0 | L29: 0 | M29: 60439200 | N29: 0 | O29: 60439200 | P29: 0 | Q29: 0 | R29: 0 | S29: 0 | T29: 0 | U29: 1 | V29: suma global | W29: 60439200 | X29: 60439200 | Y29: 60439200
A30: Ninguno | B30: 1 - CONSTRUCCION | C30: 1-5 - EDIFICACIONES | D30: 1-5-5 - TELECOMUNICACIONES | E30: 1-5-5-EDIF05 - TELECOMUNICACIONES | F30: Ninguno | G30: T - Total | H30: 1-5-5-EDIF05.T | I30: TELECOMUNICACIONES.Total | J30: 8446912.3 | K30: 0 | L30: 0 | M30: 8446912.3 | N30: 0 | O30: 8446912.3 | P30: 0 | Q30: 0 | R30: 0 | S30: 0 | T30: 0 | U30: 1 | V30: suma global | W30: 8446912.3 | X30: 8446912.3 | Y30: 8446912.3
A31: Ninguno | B31: 1 - CONSTRUCCION | C31: 1-5 - EDIFICACIONES | D31: 1-5-6 - INSTALACIONES SANITARIAS | E31: 1-5-6-EDIF06 - INSTALACIONES SANITARIAS | F31: Ninguno | G31: T - Total | H31: 1-5-6-EDIF06.T | I31: INSTALACIONES SANITARIAS.Total | J31: 1.0100749e+08 | K31: 0 | L31: 0 | M31: 1.0100749e+08 | N31: 0 | O31: 1.0100749e+08 | P31: 0 | Q31: 0 | R31: 0 | S31: 0 | T31: 0 | U31: 1 | V31: suma global | W31: 1.0100749e+08 | X31: 1.0100749e+08 | Y31: 1.0100749e+08
A32: Ninguno | B32: 1 - CONSTRUCCION | C32: 1-5 - EDIFICACIONES | D32: 1-5-7 - INSTALACIONES MECANICAS | E32: 1-5-7-EDIF07 - INSTALACIONES MECANICAS | F32: Ninguno | G32: T - Total | H32: 1-5-7-EDIF07.T | I32: INSTALACIONES MECANICAS.Total | J32: 455797.65 | K32: 0 | L32: 0 | M32: 455797.65 | N32: 0 | O32: 455797.65 | P32: 0 | Q32: 0 | R32: 0 | S32: 0 | T32: 0 | U32: 1 | V32: suma global | W32: 455797.65 | X32: 455797.65 | Y32: 455797.65
A33: Ninguno | B33: 1 - CONSTRUCCION | C33: 1-5 - EDIFICACIONES | D33: 1-5-8 - ALBANILERIA | E33: 1-5-8-EDIF08 - ALBANILERIA | F33: Ninguno | G33: T - Total | H33: 1-5-8-EDIF08.T | I33: ALBANILERIA.Total | J33: 79619986 | K33: 0 | L33: 0 | M33: 79619986 | N33: 0 | O33: 79619986 | P33: 0 | Q33: 0 | R33: 0 | S33: 0 | T33: 0 | U33: 1 | V33: suma global | W33: 79619986 | X33: 79619986 | Y33: 79619986
A34: Ninguno | B34: 1 - CONSTRUCCION | C34: 1-5 - EDIFICACIONES | D34: 1-5-9 - HERRERIA | E34: 1-5-9-EDIF09 - HERRERIA | F34: Ninguno | G34: T - Total | H34: 1-5-9-EDIF09.T | I34: HERRERIA.Total | J34: 55148949 | K34: 0 | L34: 0 | M34: 55148949 | N34: 0 | O34: 55148949 | P34: 0 | Q34: 0 | R34: 0 | S34: 0 | T34: 0 | U34: 1 | V34: suma global | W34: 55148949 | X34: 55148949 | Y34: 55148949
A35: Ninguno | B35: 1 - CONSTRUCCION | C35: 1-5 - EDIFICACIONES | D35: 1-5-10 - REVESTIMIENTO | E35: 1-5-10-EDIF10 - REVESTIMIENTO | F35: Ninguno | G35: T - Total | H35: 1-5-10-EDIF10.T | I35: REVESTIMIENTO.Total | J35: 1.7979257e+08 | K35: 0 | L35: 0 | M35: 1.7979257e+08 | N35: 0 | O35: 1.7979257e+08 | P35: 0 | Q35: 0 | R35: 0 | S35: 0 | T35: 0 | U35: 1 | V35: suma global | W35: 1.7979257e+08 | X35: 1.7979257e+08 | Y35: 1.7979257e+08
A36: Ninguno | B36: 1 - CONSTRUCCION | C36: 1-5 - EDIFICACIONES | D36: 1-5-11 - CARPINTERIA | E36: 1-5-11-EDIF11 - CARPINTERIA | F36: Ninguno | G36: T - Total | H36: 1-5-11-EDIF11.T | I36: CARPINTERIA.Total | J36: 1.1340591e+08 | K36: 0 | L36: 0 | M36: 1.1340591e+08 | N36: 0 | O36: 1.1340591e+08 | P36: 0 | Q36: 0 | R36: 0 | S36: 0 | T36: 0 | U36: 1 | V36: suma global | W36: 1.1340591e+08 | X36: 1.1340591e+08 | Y36: 1.1340591e+08
A37: Ninguno | B37: 1 - CONSTRUCCION | C37: 1-5 - EDIFICACIONES | D37: 1-5-12 - VENTANERIA | E37: 1-5-12-EDIF12 - VENTANERIA | F37: Ninguno | G37: OT - Otros | H37: 1-5-12-EDIF12.OT | I37: VENTANERIA.Otros | J37: 95070320 | K37: 0 | L37: 0 | M37: 95070320 | N37: 0 | O37: 95070320 | P37: 0 | Q37: 0 | R37: 0 | S37: 0 | T37: 0 | U37: 1 | V37: suma global | W37: 95070320 | X37: 95070320 | Y37: 95070320
A38: Ninguno | B38: 1 - CONSTRUCCION | C38: 1-5 - EDIFICACIONES | D38: 1-5-13 - PINTURA | E38: 1-5-13-EDIF13 - PINTURA | F38: Ninguno | G38: T - Total | H38: 1-5-13-EDIF13.T | I38: PINTURA.Total | J38: 1.2190433e+08 | K38: 0 | L38: 0 | M38: 1.2190433e+08 | N38: 0 | O38: 1.2190433e+08 | P38: 0 | Q38: 0 | R38: 0 | S38: 0 | T38: 0 | U38: 1 | V38: suma global | W38: 1.2190433e+08 | X38: 1.2190433e+08 | Y38: 1.2190433e+08
A39: Ninguno | B39: 1 - CONSTRUCCION | C39: 1-5 - EDIFICACIONES | D39: 1-5-14 - MISCELANEOS | E39: 1-5-14-URB14 - MISCELANEOS | F39: Ninguno | G39: T - Total | H39: 1-5-14-URB14.T | I39: MISCELANEOS.Total | J39: 74569125 | K39: 0 | L39: 0 | M39: 74569125 | N39: 0 | O39: 74569125 | P39: 0 | Q39: 0 | R39: 0 | S39: 0 | T39: 0 | U39: 1 | V39: suma global | W39: 74569125 | X39: 74569125 | Y39: 74569125
A40: Ninguno | B40: 1 - CONSTRUCCION | C40: 1-6 - GERENCIA DE CONSTRUCCION | D40: 1-6-1 - GERENCIA DE CONSTRUCCION ADI | E40: 1-6-1-MTOTALGECO - GERENCIA DE CONSTRUCCION ADI | F40: Ninguno | G40: OT - Otros | H40: 1-6-1-MTOTALGECO.OT | I40: GERENCIA DE CONSTRUCCION ADI.Otros | J40: 0 | K40: 0 | L40: 0 | M40: 0 | N40: 0 | O40: 0 | P40: 0 | Q40: 0 | R40: 0 | S40: 0 | T40: 0 | X40: 0 | Y40: 0
A41: Ninguno | B41: 1 - CONSTRUCCION | C41: 1-6 - GERENCIA DE CONSTRUCCION | D41: 1-6-2 - COSTO GERENCIA DE CONSTRUCCION | E41: 1-6-2-COSTGE - COSTO GERENCIA DE CONSTRUCCION | F41: Ninguno | G41: T - Total | H41: 1-6-2-COSTGE.T | I41: COSTO GERENCIA DE CONSTRUCCION.Total | J41: 171771292 | K41: 0 | L41: 0 | M41: 171771292 | N41: 0 | O41: 171771292 | P41: 171771292 | Q41: 0 | R41: 776107.84 | S41: 0 | T41: 171771292 | U41: 1 | V41: suma global | W41: 171771292 | X41: 0 | Y41: 171771292
A42: Ninguno | B42: 1 - CONSTRUCCION | C42: 1-7 - INDIRECTOS DE OBRA | D42: 1-7-2 - COSTOS INDIRECTOS DE OBRA | E42: 1-7-2-COSTIND - COSTOS INDIRECTOS DE OBRA | F42: Ninguno | G42: T - Total | H42: 1-7-2-COSTIND.T | I42: COSTOS INDIRECTOS DE OBRA.Total | J42: 34354258 | K42: 0 | L42: 0 | M42: 34354258 | N42: 0 | O42: 34354258 | P42: 0 | Q42: 0 | R42: 0 | S42: 0 | T42: 0 | U42: 1 | V42: suma global | W42: 34354258 | X42: 34354258 | Y42: 34354258
A43: Ninguno | B43: 2 - OPERATIVO | C43: 2-1 - GERENCIA DE LA PROMOTORA | D43: 2-1-2 - COSTO GERENCIA DE LA PROMOTORA ADI | E43: 2-1-2-COSTGEPRO - COSTO GERENCIA DE LA PROMOTORA | F43: Ninguno | G43: T - Total | H43: 2-1-2-COSTGEPRO.T | I43: COSTO GERENCIA DE LA PROMOTORA.Total | J43: 137417034 | K43: 0 | L43: 0 | M43: 137417034 | N43: 0 | O43: 137417034 | P43: 137416238 | Q43: 0 | R43: 161175.97 | S43: 0 | T43: 137416238 | U43: 1 | V43: suma global | W43: 137417034 | X43: 796 | Y43: 137417034
A44: Ninguno | B44: 2 - OPERATIVO | C44: 2-2 - GERENCIA DE VENTAS | D44: 2-2-1 - COSTO GERENCIA DE VENTAS | E44: 2-2-1-MTOTALGEVE - GERENCIA DE VENTAS ADI | F44: Ninguno | G44: T - Total | H44: 2-2-1-MTOTALGEVE.T | I44: GERENCIA DE VENTAS ADI.Total | J44: 0 | K44: 0 | L44: 0 | M44: 0 | N44: 0 | O44: 0 | P44: 0 | Q44: 0 | R44: 0 | S44: 0 | T44: 0 | X44: 0 | Y44: 0
A45: Ninguno | B45: 2 - OPERATIVO | C45: 2-2 - GERENCIA DE VENTAS | D45: 2-2-2 - ADMINISTRACION DE VENTAS | E45: 2-2-2-COSTGEVEN01 - ADMINISTRACION DE VENTAS | F45: Ninguno | G45: T - Total | H45: 2-2-2-COSTGEVEN01.T | I45: ADMINISTRACION DE VENTAS.Total | J45: 35151584 | K45: 0 | L45: 0 | M45: 35151584 | N45: 0 | O45: 35151584 | P45: 35155869 | Q45: 0 | R45: 0 | S45: 0 | T45: 35155869 | U45: 1 | V45: suma global | W45: 35151584 | X45: 0 | Y45: 35155869
A46: Ninguno | B46: 2 - OPERATIVO | C46: 2-2 - GERENCIA DE VENTAS | D46: 2-2-3 - COMISIONES | E46: 2-2-3-COSTGEVEN02 - COMISIONES | F46: Ninguno | G46: T - Total | H46: 2-2-3-COSTGEVEN02.T | I46: COMISIONES.Total | J46: 246553335 | K46: 0 | L46: 0 | M46: 246553335 | N46: 0 | O46: 246553335 | P46: 0 | Q46: 0 | R46: 0 | S46: 0 | T46: 0 | U46: 1 | V46: suma global | W46: 246553335 | X46: 246553335 | Y46: 246553335
A47: Ninguno | B47: 2 - OPERATIVO | C47: 2-3 - ADMINISTRACION DE FIDUCIARIA | D47: 2-3-2 - COSTO ADMINISTRACION DE FIDUCIARIA | E47: 2-3-2-ADMFE - COSTO ADMINISTRACION DE FIDUCIARIA | F47: Ninguno | G47: T - Total | H47: 2-3-2-ADMFE.T | I47: COSTO ADMINISTRACION DE FIDUCIARIA.Total | J47: 67334346 | K47: 0 | L47: 0 | M47: 67334346 | N47: 0 | O47: 67334346 | P47: 237853.9 | Q47: 0 | R47: 237853.9 | S47: 0 | T47: 237853.9 | U47: 1 | V47: suma global | W47: 67334346 | X47: 67096492 | Y47: 67334346
A48: Ninguno | B48: 2 - OPERATIVO | C48: 2-4 - PUBLICIDAD Y PROMOCION | D48: 2-4-1 - PUBLICIDAD Y PROMOCION ADI | E48: 2-4-1-MTOTALPU - PUBLICIDAD Y PROMOCION ADI | F48: Ninguno | G48: T - Total | H48: 2-4-1-MTOTALPU.T | I48: PUBLICIDAD Y PROMOCION ADI.Total | J48: 47692179 | K48: 0 | L48: 0 | M48: 47692179 | N48: 0 | O48: 47692179 | P48: 0 | Q48: 0 | R48: 0 | S48: 0 | T48: 0 | U48: 1 | V48: suma global | W48: 47692179 | X48: 47692179 | Y48: 47692179
A49: Ninguno | B49: 2 - OPERATIVO | C49: 2-4 - PUBLICIDAD Y PROMOCION | D49: 2-4-2 - PUBLICIDAD Y PROMOCION | E49: 2-4-2-COSTPUPROM - PUBLICIDAD Y PROMOCION | F49: Ninguno | G49: T - Total | H49: 2-4-2-COSTPUPROM.T | I49: PUBLICIDAD Y PROMOCION.Total | J49: 3839208.5 | K49: 0 | L49: 0 | M49: 3839208.5 | N49: 0 | O49: 3839208.5 | P49: 3654563 | Q49: 0 | R49: 2285058.5 | S49: 0 | T49: 3654563 | U49: 1 | V49: suma global | W49: 3839208.5 | X49: 184645.58 | Y49: 3839208.5
A50: Ninguno | B50: 2 - OPERATIVO | C50: 2-5 - POST-VENTAS | D50: 2-5-2 - POST-VENTAS | E50: 2-5-2-COSTPOSTVEN - POST-VENTAS | F50: Ninguno | G50: T - Total | H50: 2-5-2-COSTPOSTVEN.T | I50: POST-VENTAS.Total | J50: 19238385 | K50: 0 | L50: 0 | M50: 19238385 | N50: 0 | O50: 19238385 | P50: 0 | Q50: 0 | R50: 0 | S50: 0 | T50: 0 | U50: 1 | V50: suma global | W50: 19238385 | X50: 19238385 | Y50: 19238385
A51: Ninguno | B51: 3 - OTROS | C51: 3-1 - PERMISOS LEGALES Y PRELIMINARES | D51: 3-1-1 - PERMISOS LEGALES Y PRELIMINARES ADI | E51: 3-1-1-MTOTALPER - PERMISOS LEGALES Y PRELIMINARES ADI | F51: Ninguno | G51: T - Total | H51: 3-1-1-MTOTALPER.T | I51: PERMISOS LEGALES Y PRELIMINARES ADI.Total | J51: 3396950.7 | K51: 0 | L51: 0 | M51: 3396950.7 | N51: 0 | O51: 3396950.7 | P51: 0 | Q51: 0 | R51: 0 | S51: 0 | T51: 0 | U51: 1 | V51: suma global | W51: 3396950.7 | X51: 3396950.7 | Y51: 3396950.7
A52: Ninguno | B52: 3 - OTROS | C52: 3-1 - PERMISOS LEGALES Y PRELIMINARES | D52: 3-1-2 - PERMISOS LEGALES Y PRELIMINARES | E52: 3-1-2-PERM03 - PERMISOS LEGALES Y PRELIMINARES | F52: Ninguno | G52: T - Total | H52: 3-1-2-PERM03.T | I52: PERMISOS LEGALES Y PRELIMINARES.Total | J52: 11603049 | K52: 0 | L52: 0 | M52: 11603049 | N52: 0 | O52: 11603049 | P52: 12074455 | Q52: 0 | R52: 7796718.8 | S52: 0 | T52: 12074455 | U52: 1 | V52: suma global | W52: 11603049 | X52: 0 | Y52: 12074455
A53: Ninguno | B53: 3 - OTROS | C53: 3-2 - IMPREVISTOS | D53: 3-2-2 - IMPREVISTOS | E53: 3-2-2-COSTIMPRE - COSTO IMPREVISTOS | F53: Ninguno | G53: T - Total | H53: 3-2-2-COSTIMPRE.T | I53: COSTO IMPREVISTOS.Total | J53: 19238385 | K53: 0 | L53: 0 | M53: 19238385 | N53: 0 | O53: 19238385 | P53: 0 | Q53: 0 | R53: 0 | S53: 0 | T53: 0 | U53: 1 | V53: suma global | W53: 19238385 | X53: 19238385 | Y53: 19238385
A54: Ninguno | B54: 3 - OTROS | C54: 3-3 - GASTOS FINANCIEROS | D54: 3-3-2 - GASTOS FINANCIEROS | E54: 3-3-2-COSTGAFI - GASTOS FINANCIEROS | F54: Ninguno | G54: T - Total | H54: 3-3-2-COSTGAFI.T | I54: GASTOS FINANCIEROS.Total | J54: 192383847 | K54: 0 | L54: 0 | M54: 192383847 | N54: 0 | O54: 192383847 | P54: 0 | Q54: 0 | R54: 0 | S54: 0 | T54: 0 | U54: 1 | V54: suma global | W54: 192383847 | X54: 192383847 | Y54: 192383847

Sheet BCE 06.24
A1: Balance Sheet
A2: Fideicomiso Irrevocable de Desarrollo Inmobiliario y Administración Araya
A3: As at 30 June 2024
B5: Account | C5: 30 Jun 2024
A7: Assets
B8: Bank
B9: Banesco DOP -Cta. Corriente No.99100010856 | C9: 30000
B10: Banesco USD -Cta. Ahorro No.99200013780 | C10: 177012.04 | D10: [FX]
B11: Total Bank | C11: =SUM(C9:C10) -> 207012.04
B12: Current Assets
B13: Anticipos a Proveedores | C13: 11540173
B14: Total Current Assets | C14: =C13 -> 11540173
B15: Non-current Assets
B16: Costos de Construccion | C16: 14595081
B17: Costos Operativos | C17: 2684088.3
B18: Otros Costos (123906) | C18: 7796718.8
B19: Terreno | C19: 87141624
B20: Total Non-current Assets | C20: =SUM(C16:C19) -> 1.1221751e+08
A21: Total Assets | C21: =(0 + ((C11 + C14) + C20)) -> 1.239647e+08
A23: Liabilities
B24: Current Liabilities
B25: Cuentas por Pagar Comerciales | C25: 4508384.2 | E25: =+C14+C20 -> 1.2375768e+08 | F25: =+E25-C25 -> 1.192493e+08
B26: Otras Cuentas por Pagar | C26: 1068618.5 | F26: =+'PRESENTACIÓN Al 30062024'!F22 -> 1.2611017e+08
B27: Ret 100% ITBIS. Personas Fsicas | C27: 20520 | F27: =+F25-F26 -> -6860866.8
B28: Retencin 30% ITBIS Juridica | C28: 85402.08
B29: Retencin ISR Exterior 27% | C29: 1566553.1
B30: Retencin ISR Personas Fsicas 10% | C30: 11400
B31: Total Current Liabilities | C31: =SUM(C25:C30) -> 7260877.8
A32: Total Liabilities | C32: =(0 + C31) -> 7260877.8
B34: Net Assets | C34: =(C21 - C32) -> 1.1670382e+08
A36: Equity
B37: Aporte Fideicomitente AFI Universal | C37: 1.1670523e+08
B38: Current Year Earnings | C38: -1411.3
A39: Total Equity | C39: =SUM(C37:C38) -> 1.1670382e+08
A42: [FX] Exchange rates used to convert foreign currency into DOP are shown below. Rates are provided by XE.com unless otherwise stated.
A43: 30 Jun 2024
A44: 0.0169480 USD (United States Dollar) – on 1 Jul 2024

Sheet PRESENTACIÓN Al 31072024
M1: IMAGEN DEL ADI archivo : Flujo_de_caja_PUNTA_CANA_462_MAR2024_V.0.XLSX al 02/05/24
E2: a | J2: d | K2: e
B3: PRESUPUESTO JUNIO 2024 | D3: 59 | E3: COMPROMETIDO | F3: EJECUTADO | G3: CXP DE LO EJECUTADO | H3: ANTICIPOS PAGADOS | I3: PAGADO | J3: POR EJECUTAR DE LO COMPROMETIDO | K3: PROYECTADO PARA TERMINAR
B4: PARTIDA | C4: DOP | D4: US $
A5: 1 | B5: Terreno | C5: =SUM('budget (11)'!D2:D3) -> 103385169 | D5: =C5/D3 -> 1752291 | E5: =+'Finanzas 06.24'!L48+7030718.17 -> 94172342 | F5: =+'Resumen de Costos 07.24 '!B9 -> 94172342 | G5: 0 | I5: =+F5-G5 -> 94172342 | J5: =E5-I5 -> 0.010000005 | K5: =+#REF!-7030718.17 -> #REF! | L5: =C5-(E5+K5) -> #REF!
B6: Costo Urbanismo | C6: =SUM('budget (11)'!D11:D24) -> 4.51759e+08 | D6: =C6/$D$3 -> 7656932.2 | E6: =+'Finanzas 06.24'!L53 -> 9038515.4 | F6: 7467449.3 | H6: 1571066 | I6: =+F6-G6+H6 -> 9038515.3 | J6: =E6-I6 -> 0.07 | K6: =+#REF! -> #REF! | L6: =C6-(E6+K6) -> #REF!
B7: Costo Vivienda | C7: =SUM('budget (11)'!D25:D39) -> 1265953920 | D7: =C7/$D$3 -> 21456846 | E7: =SUM('budget (11)'!E25:E39) -> 0 | I7: =+F7-G7+H7 -> 0 | J7: =E7-I7 -> 0 | K7: =+#REF! -> #REF! | L7: =C7-(E7+K7) -> #REF!
B8: Gerencia Construcción: | C8: =SUM('budget (11)'!D40:D41) -> 171771292 | D8: =C8/$D$3 -> 2911377.8 | E8: =+'Finanzas 06.24'!L27 -> 171771292 | F8: =+'Resumen de Costos 07.24 '!B14 -> 779044.14 | I8: =+F8-G8+H8 -> 779044.14 | J8: =E8-I8 -> 1.7099225e+08 | K8: =+#REF! -> #REF! | L8: =C8-(E8+K8) -> #REF!
B9: Indirectos de Obra | C9: =SUM('budget (11)'!D42) -> 34354258 | D9: =C9/$D$3 -> 582275.56 | E9: =SUM('budget (11)'!E42) -> 0 | I9: =+F9-G9+H9 -> 0 | J9: =E9-I9 -> 0 | K9: =+#REF! -> #REF! | L9: =C9-(E9+K9) -> #REF!
B10: Total Costos Construcción | C10: =SUM(C6:C9) -> 1923838470 | D10: =SUM(D6:D9) -> 32607432 | E10: =SUM(E6:E9) -> 1.8080981e+08 | F10: =SUM(F6:F9) -> 8246493.5 | G10: =SUM(G6:G9) -> 0 | H10: =SUM(H6:H9) -> 1571066 | I10: =SUM(I6:I9) -> 9817559.5 | J10: =E10-I10 -> 1.7099225e+08 | K10: =SUM(K6:K9) -> #REF! | L10: =C10-(E10+K10) -> #REF!
B11: Gerencia de la Promotora | C11: =SUM('budget (11)'!D43) -> 137417034 | D11: =C11/$D$3 -> 2329102.3 | E11: =+'Finanzas 06.24'!L29 -> 137416238 | F11: =+'Resumen de Costos 07.24 '!B18 -> 161175.97 | I11: =+F11-G11+H11 -> 161175.97 | J11: =E11-I11 -> 1.3725506e+08 | K11: =+#REF! -> #REF! | L11: =C11-(E11+K11) -> #REF!
B12: Gerencia de Ventas | C12: =SUM('budget (11)'!D45:D46) -> 281704919 | D12: =C12/$D$3 -> 4774659.6 | E12: 35151584 | I12: =+F12-G12+H12 -> 0 | J12: =E12-I12 -> 35151584 | K12: =+#REF! -> #REF! | L12: =C12-(E12+K12) -> #REF!
B13: Administración Fiducia | C13: =SUM('budget (11)'!D47) -> 67334346 | D13: =C13/$D$3 -> 1141260.1 | E13: =+'Finanzas 06.24'!L2 -> 237853.9 | F13: =+'Resumen de Costos 07.24 '!B19 -> 237853.9 | I13: =+F13-G13+H13 -> 237853.9 | J13: =E13-I13 -> 0 | K13: =+#REF! -> #REF! | L13: =C13-(E13+K13) -> #REF!
A14: 1 | B14: Publicidad | C14: =SUM('budget (11)'!D48:D49) -> 51531388 | D14: =C14/$D$3 -> 873413.36 | E14: 7464595.3 | F14: =+'Resumen de Costos 07.24 '!B20 -> 3687524 | G14: =+'CXP 07.24'!F20 -> 1459465.5 | I14: =+F14-G14+H14 -> 2228058.5 | J14: =E14-I14 -> 5236536.9 | K14: =+#REF! -> #REF! | L14: =C14-(E14+K14) -> #REF!
B15: Post Ventas | C15: =SUM('budget (11)'!D50) -> 19238385 | D15: =C15/$D$3 -> 326074.32 | E15: =SUM('budget (11)'!E50) -> 0 | I15: =+F15-G15+H15 -> 0 | J15: =E15-I15 -> 0 | K15: =+#REF! -> #REF! | L15: =C15-(E15+K15) -> #REF!
B16: Total Gastos Operativos | C16: =SUM(C11:C15) -> 5.5722607e+08 | D16: =SUM(D11:D15) -> 9444509.7 | E16: =SUM(E11:E15) -> 1.8027027e+08 | F16: =SUM(F11:F15) -> 4086553.8 | G16: =SUM(G11:G15) -> 1459465.5 | H16: =SUM(H11:H15) -> 0 | I16: =SUM(I11:I15) -> 2627088.3 | J16: =E16-I16 -> 1.7764318e+08 | K16: =SUM(K11:K15) -> #REF! | L16: =C16-(E16+K16) -> #REF!
B17: Permisos legales y Preliminares | C17: =SUM('budget (11)'!D51:D52) -> 15000000 | D17: =C17/$D$3 -> 254237.29 | E17: 18740000 | F17: =+'Resumen de Costos 07.24 '!B24 -> 7854532.5 | H17: =+'ANTICIPO 07.24'!E9 -> 2724363.7 | I17: =+F17-G17+H17 -> 10578896 | J17: =E17-I17 -> 8161103.8 | K17: =+#REF! -> #REF! | L17: =C17-(E17+K17) -> #REF!
B18: Diseño y Proyecto | C18: =SUM('budget (11)'!D4:D10) -> 20790000 | D18: =C18/$D$3 -> 352372.88 | E18: 20395153 | F18: =+'Resumen de Costos 07.24 '!B12 -> 19211666 | G18: =+'CXP 07.24'!F14 -> 2877278.3 | H18: =+'ANTICIPO 07.24'!E5 -> 742800 | I18: =+F18-G18+H18 -> 17077188 | J18: =E18-I18 -> 3317964.6 | K18: =+#REF! -> #REF! | L18: =C18-(E18+K18) -> #REF!
B19: Gastos Financieros | C19: =SUM('budget (11)'!D54) -> 192383847 | D19: =C19/$D$3 -> 3260743.2 | E19: =SUM('budget (11)'!E54) -> 0 | I19: =+F19-G19+H19 -> 0 | J19: =E19-I19 -> 0 | K19: =+#REF! -> #REF! | L19: =C19-(E19+K19) -> #REF!
B20: Imprevistos | C20: =SUM('budget (11)'!D53) -> 19238385 | D20: =C20/$D$3 -> 326074.32 | E20: =SUM('budget (11)'!E53) -> 0 | I20: =+F20-G20+H20 -> 0 | J20: =E20-I20 -> 0 | K20: =+#REF! -> #REF! | L20: =C20-(E20+K20) -> #REF!
B21: Total Otros Gastos | C21: =SUM(C17:C20) -> 247412232 | D21: =SUM(D17:D20) -> 4193427.7 | E21: =SUM(E17:E20) -> 39135153 | F21: =SUM(F17:F20) -> 27066199 | G21: =SUM(G17:G20) -> 2877278.3 | H21: =SUM(H17:H20) -> 3467163.7 | I21: =SUM(I17:I20) -> 27656084 | J21: =E21-I21 -> 11479068 | K21: =SUM(K17:K20) -> #REF! | L21: =C21-(E21+K21) -> #REF!
B22: TOTALES | C22: =C5+C10+C16+C21 -> 2.8318619e+09 | D22: =D5+D10+D16+D21 -> 47997660 | E22: =E21+E16+E10+E5 -> 4.9438757e+08 | F22: =F21+F16+F10+F5 -> 1.3357159e+08 | G22: =G21+G16+G10+G5 -> 4336743.8 | H22: =H21+H16+H10+H5 -> 5038229.7 | I22: =I21+I16+I10+I5 -> 1.3427307e+08 | J22: =E22-I22 -> 3.601145e+08 | K22: =K21+K16+K10+K5 -> #REF! | L22: =L21+L16+L10+L5 -> #REF!
E23: =+E22-E8-E11-E12 -> 1.5004846e+08 | J23: =J17 -> 8161103.8
G24: Aportes AFI | H24: =+'BCE 07.24'!C37 -> 1.3373595e+08 | I24: 160000000 | K24: permisos por iniciar | N24: Dato del ADI | O24: 2.8318619e+09
G25: Balance Bancos | H25: =-'BCE 07.24'!C11 -> -1534106.5 | I25: =I24-I22 -> 25726926 | J25: =E18-I18 -> 3317964.6 | K25: diseño por pagar | N25: Dato Procore | O25: =C22 -> 2.8318619e+09
G26: Retenciones por pagar | H26: =+'BCE 07.24'!C26+'BCE 07.24'!C27+'BCE 07.24'!C28+'BCE 07.24'!C29+'BCE 07.24'!C30 -> 527534.29 | I26: =+J13+J14+J17+J18+J6 -> 16715605 | J26: =E14-I14 -> 5236536.9 | K26: Publicidade por pagar | N26: Diferencia | O26: =O24-O25 -> -0.55799961
E27: diponible | G27: Pagado según balanza | H27: =SUM(H24:H26) -> 1.3272938e+08 | I27: =I25-I26 -> 9011320.8
G28: Pagado según reportes | H28: =+I22 -> 1.3427307e+08
G29: Diferencial cambiario | H29: =+H27-H28 -> -1543697.8 | I29: =+'BCE 07.24'!C38+'PRESENTACIÓN Al 31072024'!H29 -> -1571066
B32: Total Gastos Operativos
B33: Permisos legales y Preliminares
B34: Diseño y Proyecto
B35: Gastos Financieros
B36: Imprevistos
B37: Total Otros Gastos
B38: TOTALES
B41: APORTE AFI | C41: 160000000
B42: Gastado y comprometido | C42: =I22+I26 -> 1.5098868e+08 | D42: =C42/C41 -> 0.94367924
B43: Disponible | C43: =C41-C42 -> 9011320.8 | D43: =C43/C41 -> 0.056320755

Sheet BCE 07.24
A1: Balance Sheet
A2: Fideicomiso Irrevocable de Desarrollo Inmobiliario y Administración Araya
A3: As at 31 July 2024
B5: Account | C5: 31 Jul 2024
A7: Assets
B8: Bank
B9: Banesco DOP -Cta. Corriente No.99100010856 | C9: 1067418.9
B10: Banesco USD -Cta. Ahorro No.99200013780 | C10: 466687.59 | D10: [FX]
B11: Total Bank | C11: =SUM(C9:C10) -> 1534106.5
B12: Current Assets
B13: Anticipos a Proveedores | C13: 3467163.7
B14: Total Current Assets | C14: =C13 -> 3467163.7
B15: Non-current Assets
B16: Costos de Construccion | C16: 27458160
B17: Costos Operativos | C17: 4086553.8
B18: Otros Costos (123906) | C18: 7854532.5
B19: Terreno | C19: 94172342
B20: Total Non-current Assets | C20: =SUM(C16:C19) -> 1.3357159e+08 | E20: =+#REF! -> #REF!
A21: Total Assets | C21: =(0 + ((C11 + C14) + C20)) -> 1.3857286e+08
A23: Liabilities
B24: Current Liabilities
B25: Cuentas por Pagar Comerciales | C25: 4336743.8
B26: Otras Cuentas por Pagar | C26: 26550
B27: Ret 100% ITBIS. Personas Fsicas | C27: 16092
B28: Retencin 30% ITBIS Juridica | C28: 159727.69
B29: Retencin ISR Exterior 27% | C29: 316224.6
B30: Retencin ISR Personas Fsicas 10% | C30: 8940
B31: Total Current Liabilities | C31: =SUM(C25:C30) -> 4864278.1
A32: Total Liabilities | C32: =(0 + C31) -> 4864278.1
B34: Net Assets | C34: =(C21 - C32) -> 1.3370858e+08
A36: Equity
B37: Aporte Fideicomitente AFI Universal | C37: 1.3373595e+08
B38: Current Year Earnings | C38: -27368.24
A39: Total Equity | C39: =SUM(C37:C38) -> 1.3370858e+08
A42: [FX] Exchange rates used to convert foreign currency into DOP are shown below. Rates are provided by XE.com unless otherwise stated.
A43: 31 Jul 2024
A44: 0.0170489 USD (United States Dollar) – on 1 Aug 2024

Sheet Resumen de Costos 07.24 
A1: Account Transactions
A2: Fideicomiso Irrevocable de Desarrollo Inmobiliario y Administración Araya
A3: For the period 1 January 2014 to 31 July 2024
A5: COSTOS | B5: Debit (DOP) | C5: Credit (DOP)
A7: 123902 - Terreno
A8: Terreno | B8: 94172342 | C8: 0
A9: Total 123902 - Terreno | B9: =SUM(B8) -> 94172342 | C9: 0
A11: 123903 - Costos de Construccion
A12: Diseño y Proyecto | B12: 19211666 | C12: 0
A13: Costo Urbanismo | B13: 7467449.3 | C13: 0
A14: Gerencia de Construcción | B14: 779044.14 | C14: 0
A15: Total 123903 - Costos de Construccion | B15: =SUM(B12:B14) -> 27458160 | C15: 0
A17: 123904 - Costos Operativos
A18: Gerencia de la Promotora | B18: 161175.97 | C18: 0
A19: Administración Fiduciaria | B19: 237853.9 | C19: 0
A20: Publicidad: Medios Tradicionales y Digitales | B20: 3687524 | C20: 0
A21: Total 123904 - Costos Operativos | B21: =SUM(B18:B20) -> 4086553.8 | C21: 0
A23: 123906 - Otros Costos (123906)
A24: Permisos, Legales y Preliminares | B24: 7854532.5 | C24: 0
A25: Total 123906 - Otros Costos (123906) | B25: =SUM(B24) -> 7854532.5 | C25: 0
A27: Total | B27: =+B9+B15+B21+B25 -> 1.3357159e+08 | C27: 0

Sheet Finanzas 08.24
A1: Budget Code > Cost Code Tier 2 Description | B1: Columnas personalizadas > Monto Total Presupuestado | C1: Commitment Line Item > Amount | D1: Commitment > Payments Issued | E1: Columnas personalizadas > Restante
A2: TERRENO | B2: 103385169 | C2: 94172342 | D2: 93973040 | E2: =+C2-D2 -> 199302
A3: DISEÃ‘O Y PROYECTO | B3: 20790000 | C3: 20784948 | D3: =14942869.17+2025354.08 -> 16968223 | E3: =+C3-D3 -> 3816724.3
A4: URBANISMO | B4: 451759000 | C4: =9038515.39+2518299.79 -> 11556815 | D4: 9038515 | E4: =+C4-D4 -> 2518300.2
A5: EDIFICACIONES | B5: 1265953920 | E5: =+C5-D5 -> 0
A6: GERENCIA DE CONSTRUCCION | B6: 171771292 | C6: 171771292 | D6: 9038515 | E6: =+C6-D6 -> 162732777
A7: INDIRECTOS DE OBRA | B7: 34354258 | E7: =+C7-D7 -> 0
A8: GERENCIA DE LA PROMOTORA | B8: 137417034 | C8: 137416238 | D8: 161175.97 | E8: =+C8-D8 -> 1.3725506e+08
A9: GERENCIA DE VENTAS | B9: 281704919 | C9: 35151584 | D9: 0 | E9: =+C9-D9 -> 35151584
A10: ADMINISTRACION DE FIDUCIARIA | B10: 67334346 | C10: 237853.9 | D10: 0 | E10: =+C10-D10 -> 237853.9
A11: PUBLICIDAD Y PROMOCION | B11: 51531388 | C11: =7507475.33+2082233.67 -> 9589709 | D11: =2249437.93+1674645.92 -> 3924083.9 | E11: =+C11-D11 -> 5665625.2
A12: POST-VENTAS | B12: 19238385 | E12: =+C12-D12 -> 0
A13: PERMISOS LEGALES Y PRELIMINARES | B13: 15000000 | C13: 12132268 | D13: 7882792.6 | E13: =+C13-D13 -> 4249475.9
A14: IMPREVISTOS | B14: 19238385 | E14: =+C14-D14 -> 0
A15: GASTOS FINANCIEROS | B15: 192383847 | E15: =+C15-D15 -> 0
B16: =SUM(B2:B15) -> 2.8318619e+09 | C16: =SUM(C2:C15) -> 492813050 | D16: =SUM(D2:D15) -> 1.4098635e+08 | E16: =SUM(E2:E15) -> 3.518267e+08

Sheet CXP 07.24
A1: Payable Invoice Summary
A2: Fideicomiso Irrevocable de Desarrollo Inmobiliario y Administración Araya
A3: For the period 1 July 2014 to 31 July 2024
A5: Status contains Accepted, Approved, Awaiting Approval, Billed, Current, Draft, Invoiced, Sent
A7: Invoice Date | B7: Contact | C7: Reference | D7: Gross (DOP) | E7: Payments / Debits (DOP) | F7: Balance (DOP) | G7: COSTOS DE OBRA
A8: 45453 | B8: ADVANCEBAU LLC | C8: INT.061024 | D8: 446042 | E8: 385727.8 | F8: 60314.2 | G8: Diseño y Proyecto
A9: 45453 | B9: ECOTURISMO MUNDIAL Y PROYECTOS AMBIENTALES SRL(EMPACA) | C9: B0100004526 | D9: 820656 | E9: 409320 | F9: 411336 | G9: Diseño y Proyecto
A10: 45456 | B10: CONCONCRETOS PROYECTOS S A S | C10: INT.8763 PARTE-1 | D10: 3825551.1 | E10: 3533442.1 | F10: 292109.02 | G10: Diseño y Proyecto
A11: 45474 | B11: CONTEXTO URBANO | C11: INT-18632 | D11: 4876762 | E11: 3557991.9 | F11: 1318770.1 | G11: Diseño y Proyecto
A12: 45499 | B12: INVERSIONES BRICKET C A | C12: INT. 201 | D12: 1998189 | E12: 1362015 | F12: 636174 | G12: Diseño y Proyecto
A13: 45503 | B13: COMPAÑIA OPERADORA DEL AGUA TECCA SAS | C13: B0100002594 | D13: 348690 | E13: 190115 | F13: 158575 | G13: Diseño y Proyecto
F14: =SUM(F8:F13) -> 2877278.3 | G14: Diseño y Proyecto
A16: 45469 | B16: RANCEL SANTIAGO VASQUEZ AZAR | C16: PROV.INFORMAL | D16: 145920 | E16: 88920 | F16: 57000 | G16: Publicidad: Medios Tradicionales y Digitales
A17: 45488 | B17: PANAMERICAN CREATIVE MINDS INC | C17: INT-005828 | D17: 331089 | E17: 0 | F17: 331089 | G17: Publicidad: Medios Tradicionales y Digitales
A18: 45490 | B18: DANIELLA MARIA BETANCES COPELLO | C18: PROVEEDOR INFORMAL | D18: 156284.31 | E18: 0 | F18: 156284.31 | G18: Publicidad: Medios Tradicionales y Digitales
A19: 45500 | B19: PANAMERICAN CREATIVE MINDS INC | C19: INT-005849 | D19: 915092.18 | E19: 0 | F19: 915092.18 | G19: Publicidad: Medios Tradicionales y Digitales
F20: =SUM(F16:F19) -> 1459465.5 | G20: Publicidad: Medios Tradicionales y Digitales

Sheet ANTICIPO 07.24
A1: ContactName | B1: Reference | C1: InvoiceDate | D1: Total | E1: InvoiceAmountDue | F1: TrackingOption1
A2: DISENOS ESTRUCTURALES AL LIMITE D E L SRL | B2: ANTICIPO DISEÃ‘OS ESTRUCTURALES | C2: 45497 | D2: 222000 | E2: 222000 | F2: DiseÃ±o y Proyecto
A3: HIDROPOZO SRL | B3: ANTICIPO HIDROPOZOS | C3: 45266 | D3: 273000 | E3: 273000 | F3: DiseÃ±o y Proyecto
A4: ANDRES MONTERO LANDSCAPE ARCHITECTURE | B4: ANTICIPO ANDRES MONTERO | C4: 45343 | D4: 247800 | E4: 247800 | F4: DiseÃ±o y Proyecto
E5: =SUM(E2:E4) -> 742800 | F5: DiseÃ±o y Proyecto
A7: TECNICA MMHB SRL | B7: ANTICIPO TECNICA | C7: 45338 | D7: 8000000 | E7: 1674259.4 | F7: Permisos y Preliminares
A8: MINISTERIO DE MEDIO AMBIENTE Y RECURSOS NATURALES | B8: 30% REVISION AMBIENTAL | C8: 45392 | D8: 1050104.3 | E8: 1050104.3 | F8: Permisos y Preliminares
E9: =SUM(E7:E8) -> 2724363.7 | F9: Permisos y Preliminares

Sheet BCE 08.24
A1: Balance Sheet
A2: Fideicomiso Irrevocable de Desarrollo Inmobiliario y Administración Araya
A3: As at 31 August 2024
B5: Account | C5: 31 Aug 2024
A7: Assets
B8: Bank
B9: Banesco DOP -Cta. Corriente No.99100010856 | C9: 19880327
B10: Banesco USD -Cta. Ahorro No.99200013780 | C10: 170494.28 | D10: [FX]
B11: Total Bank | C11: =SUM(C9:C10) -> 20050821
B12: Current Assets
B13: Anticipos a Proveedores | C13: 5848990.6
B14: Total Current Assets | C14: =C13 -> 5848990.6
B15: Non-current Assets
B16: Costos de Construccion | C16: 30229369
B17: Costos Operativos | C17: 4836760.3
B18: Otros Costos (123906) | C18: 7854532.5
B19: Terreno | C19: 94172342
B20: Total Non-current Assets | C20: =SUM(C16:C19) -> 1.37093e+08
A21: Total Assets | C21: =(0 + ((C11 + C14) + C20)) -> 1.6299282e+08
A23: Liabilities
B24: Current Liabilities
B25: Cuentas por Pagar Comerciales | C25: 2359941.9
B26: Otras Cuentas por Pagar | C26: 340630
B27: Ret 100% ITBIS. Personas Fsicas | C27: 43200
B28: Retencin 30% ITBIS Juridica | C28: 7865.37
B29: Retencin ISR Exterior 27% | C29: 519003.67
B30: Retencin ISR Personas Fsicas 10% | C30: 24000
B31: Total Current Liabilities | C31: =SUM(C25:C30) -> 3294640.9
A32: Total Liabilities | C32: =(0 + C31) -> 3294640.9
B34: Net Assets | C34: =(C21 - C32) -> 1.5969817e+08
A36: Equity
B37: Aporte Fideicomitente AFI Universal | C37: 1.5969577e+08
B38: Current Year Earnings | C38: 2400.87
A39: Total Equity | C39: =SUM(C37:C38) -> 1.5969817e+08
A42: [FX] Exchange rates used to convert foreign currency into DOP are shown below. Rates are provided by XE.com unless otherwise stated.
A43: 31 Aug 2024
A44: 0.0167981 USD (United States Dollar) – on 1 Sep 2024

Sheet Resumen de Costos 08.24 
A1: Account Transactions
A2: Fideicomiso Irrevocable de Desarrollo Inmobiliario y Administración Araya
A3: For the period 1 March 2014 to 31 August 2024
A5: COSTOS DE OBRA | B5: Debit (DOP) | C5: Credit (DOP)
A7: 123902 - Terreno
A8: Terreno | B8: 94172342 | C8: 0
A9: Total 123902 - Terreno | B9: =SUM(B8:B8) -> 94172342 | C9: =SUM(C8:C8) -> 0
A11: 123903 - Costos de Construccion
A12: Costo Urbanismo | B12: 9038515.4 | C12: 0
A13: Diseño y Proyecto | B13: 20108040 | C13: 0
A14: Gerencia de Construcción | B14: 1082814.1 | C14: 0
A15: Total 123903 - Costos de Construccion | B15: =SUM(B12:B14) -> 30229369 | C15: =SUM(C12:C14) -> 0
A17: 123904 - Costos Operativos
A18: Publicidad: Medios Tradicionales y Digitales | B18: 4437730.5 | C18: 0
A19: Gerencia de la Promotora | B19: 161175.97 | C19: 0
A20: Administración Fiduciaria | B20: 237853.9 | C20: 0
A21: Total 123904 - Costos Operativos | B21: =SUM(B18:B20) -> 4836760.3 | C21: =SUM(C18:C20) -> 0
A23: 123906 - Otros Costos (123906)
A24: Permisos, Legales y Preliminares | B24: 7854532.5 | C24: 0
A25: Total 123906 - Otros Costos (123906) | B25: =SUM(B24:B24) -> 7854532.5 | C25: =SUM(C24:C24) -> 0
A27: Total | B27: =SUM(B9,B15,B21,B25) -> 1.37093e+08 | C27: =SUM(C9,C15,C21,C25) -> 0

Sheet CXP 08.24
A1: Aged Payables Summary
A2: Fideicomiso Irrevocable de Desarrollo Inmobiliario y Administración Araya
A3: As at 31 August 2024
A4: Ageing by due date
A6: Contact | B6: Total
A8: Costo Urbanismo, Gerencia de Construcción
A9: TECNICA MMHB SRL | B9: 190631.57
A10: Total Costo Urbanismo, Gerencia de Construcción | B10: =B9 -> 190631.57
A12: Diseño y Proyecto
A13: ADVANCEBAU LLC | B13: 60314.2
A14: COMPAÑIA OPERADORA DEL AGUA TECCA SAS | B14: 158575
A15: CONCONCRETOS PROYECTOS S A S | B15: 292109.02
A16: DISENOS ESTRUCTURALES AL LIMITE D E L SRL | B16: 166220
A17: ECOTURISMO MUNDIAL Y PROYECTOS AMBIENTALES SRL(EMPACA) | B17: 373780.56
A18: INVERSIONES BRICKET C A | B18: 636174
A19: OFICINA DE TASACIONES Y PROYECTOS ECONOMICOS SRL OTPRESA | B19: 53100
A20: Total Diseño y Proyecto | B20: =SUM(B13:B19) -> 1740272.8
A22: Publicidad: Medios Tradicionales y Digitales
A23: PANAMERICAN CREATIVE MINDS INC | B23: 376237.5
A24: RANCEL SANTIAGO VASQUEZ AZAR | B24: 52800
A25: Total Publicidad: Medios Tradicionales y Digitales | B25: =SUM(B23:B24) -> 429037.5
A27: Total | B27: =SUM(B10,B20,B25) -> 2359941.9
A29: Percentage of total | B29: =(SUM(B10,B20,B25) / SUM(B10,B20,B25)) -> 1

Sheet ANTICIPO 08.24
A1: ContactName | B1: Reference | C1: InvoiceDate | D1: LineAmount | E1: TrackingOption1
A2: FRANCISCO AQUINO & ASOCIADOS SRL | B2: ANTICIPO AQUINO | C2: 45504 | D2: 400 | E2: DiseÃ±o y Proyecto
A3: MARY VANGIE GRULLON CACERES | B3: ANTICIPO MARY | C3: 45469 | D3: 38250 | E3: DiseÃ±o y Proyecto
A4: ONEIDA MARIA FRIAS PADILLA | B4: PO--020 | C4: 45429 | D4: 40000 | E4: DiseÃ±o y Proyecto
A5: HIDROPOZO SRL | B5: ANTICIPO HIDROPOZOS | C5: 45266 | D5: 273000 | E5: DiseÃ±o y Proyecto
D6: =SUM(D2:D5) -> 351650 | E6: DiseÃ±o y Proyecto
A8: MINISTERIO DE MEDIO AMBIENTE Y RECURSOS NATURALES | C8: 45392 | D8: 1050104.3 | E8: Permisos, Legales y Preliminares
D9: =SUM(D8) -> 1050104.3 | E9: Permisos, Legales y Preliminares
A11: TECNICA MMHB SRL | B11: ANTICIPO TECNICA | C11: 45510 | D11: 2025354.1 | E11: Preliminares de Obra
D12: =SUM(D11) -> 2025354.1 | E12: Preliminares de Obra
A14: LMCAD ESTUDIO DE ANIMACION SRL | C14: 45512 | D14: 747236.25 | E14: Publicidad: Medios Tradicionales y Digitales
A15: TECNICA MMHB SRL | B15: ANTICIPO TECNICA | C15: 45510 | D15: 1674645.9 | E15: Publicidad: Medios Tradicionales y Digitales
D16: =SUM(D14:D15) -> 2421882.2 | E16: Publicidad: Medios Tradicionales y Digitales
D18: =+D6+D9+D12+D16 -> 5848990.6

Sheet PRESENTACIÓN Al 31082024
M1: IMAGEN DEL ADI archivo : Flujo_de_caja_PUNTA_CANA_462_MAR2024_V.0.XLSX al 02/05/24
E2: a | J2: d | K2: e
B3: PRESUPUESTO JUNIO 2024 | D3: 59 | E3: COMPROMETIDO | F3: EJECUTADO | G3: CXP DE LO EJECUTADO | H3: ANTICIPOS PAGADOS | I3: PAGADO | J3: POR EJECUTAR DE LO COMPROMETIDO | K3: PROYECTADO PARA TERMINAR
B4: PARTIDA | C4: DOP | D4: US $
A5: 1 | B5: Terreno | C5: =SUM('budget (11)'!D2:D3) -> 103385169 | D5: =C5/D3 -> 1752291 | E5: =+'Finanzas 08.24'!C2 -> 94172342 | F5: =+'Resumen de Costos 08.24 '!B8 -> 94172342 | G5: 0 | I5: =+F5-G5+H5 -> 94172342 | J5: =E5-I5 -> 0 | K5: =+#REF!-7030718.17 -> #REF! | L5: =C5-(E5+K5) -> #REF!
B6: Costo Urbanismo | C6: =SUM('budget (11)'!D11:D24) -> 4.51759e+08 | D6: =C6/$D$3 -> 7656932.2 | E6: =+'Finanzas 08.24'!C4 -> 11556815 | F6: =+'Resumen de Costos 08.24 '!B12 -> 9038515.4 | H6: =+'ANTICIPO 08.24'!D12 -> 2025354.1 | I6: =+F6-G6+H6 -> 11063869 | J6: =E6-I6 -> 492945.71 | K6: =+#REF! -> #REF! | L6: =C6-(E6+K6) -> #REF!
B7: Costo Vivienda | C7: =SUM('budget (11)'!D25:D39) -> 1265953920 | D7: =C7/$D$3 -> 21456846 | E7: =SUM('budget (11)'!E25:E39) -> 0 | I7: =+F7-G7+H7 -> 0 | J7: =E7-I7 -> 0 | K7: =+#REF! -> #REF! | L7: =C7-(E7+K7) -> #REF!
B8: Gerencia Construcción: | C8: =SUM('budget (11)'!D40:D41) -> 171771292 | D8: =C8/$D$3 -> 2911377.8 | E8: =+'Finanzas 08.24'!C6 -> 171771292 | F8: =+'Resumen de Costos 08.24 '!B14 -> 1082814.1 | G8: =+'CXP 08.24'!B10 -> 190631.57 | I8: =+F8-G8+H8 -> 892182.53 | J8: =E8-I8 -> 1.7087911e+08 | K8: =+#REF! -> #REF! | L8: =C8-(E8+K8) -> #REF!
B9: Indirectos de Obra | C9: =SUM('budget (11)'!D42) -> 34354258 | D9: =C9/$D$3 -> 582275.56 | E9: =SUM('budget (11)'!E42) -> 0 | I9: =+F9-G9+H9 -> 0 | J9: =E9-I9 -> 0 | K9: =+#REF! -> #REF! | L9: =C9-(E9+K9) -> #REF!
B10: Total Costos Construcción | C10: =SUM(C6:C9) -> 1923838470 | D10: =SUM(D6:D9) -> 32607432 | E10: =SUM(E6:E9) -> 1.8332811e+08 | F10: =SUM(F6:F9) -> 10121329 | G10: =SUM(G6:G9) -> 190631.57 | H10: =SUM(H6:H9) -> 2025354.1 | I10: =SUM(I6:I9) -> 11956052 | J10: =SUM(J6:J9) -> 1.7137206e+08 | K10: =SUM(K6:K9) -> #REF! | L10: =C10-(E10+K10) -> #REF!
B11: Gerencia de la Promotora | C11: =SUM('budget (11)'!D43) -> 137417034 | D11: =C11/$D$3 -> 2329102.3 | E11: =+'Finanzas 08.24'!C8 -> 137416238 | F11: =+'Resumen de Costos 08.24 '!B19 -> 161175.97 | I11: =+F11-G11+H11 -> 161175.97 | J11: =E11-I11 -> 1.3725506e+08 | K11: =+#REF! -> #REF! | L11: =C11-(E11+K11) -> #REF!
B12: Gerencia de Ventas | C12: =SUM('budget (11)'!D45:D46) -> 281704919 | D12: =C12/$D$3 -> 4774659.6 | E12: =+'Finanzas 08.24'!C9 -> 35151584 | I12: =+F12-G12+H12 -> 0 | J12: =E12-I12 -> 35151584 | K12: =+#REF! -> #REF! | L12: =C12-(E12+K12) -> #REF!
B13: Administración Fiducia | C13: =SUM('budget (11)'!D47) -> 67334346 | D13: =C13/$D$3 -> 1141260.1 | E13: =+'Finanzas 08.24'!C10 -> 237853.9 | F13: =+'Resumen de Costos 08.24 '!B20 -> 237853.9 | I13: =+F13-G13+H13 -> 237853.9 | J13: =E13-I13 -> 0 | K13: =+#REF! -> #REF! | L13: =C13-(E13+K13) -> #REF!
A14: 1 | B14: Publicidad | C14: =SUM('budget (11)'!D48:D49) -> 51531388 | D14: =C14/$D$3 -> 873413.36 | E14: =+'Finanzas 08.24'!C11 -> 9589709 | F14: =+'Resumen de Costos 08.24 '!B18 -> 4437730.5 | G14: =+'CXP 08.24'!B25 -> 429037.5 | H14: =+'ANTICIPO 08.24'!D16 -> 2421882.2 | I14: =+F14-G14+H14 -> 6430575.1 | J14: =E14-I14 -> 3159133.9 | K14: =+#REF! -> #REF! | L14: =C14-(E14+K14) -> #REF!
B15: Post Ventas | C15: =SUM('budget (11)'!D50) -> 19238385 | D15: =C15/$D$3 -> 326074.32 | E15: =SUM('budget (11)'!E50) -> 0 | I15: =+F15-G15+H15 -> 0 | J15: =E15-I15 -> 0 | K15: =+#REF! -> #REF! | L15: =C15-(E15+K15) -> #REF!
B16: Total Gastos Operativos | C16: =SUM(C11:C15) -> 5.5722607e+08 | D16: =SUM(D11:D15) -> 9444509.7 | E16: =SUM(E11:E15) -> 1.8239538e+08 | F16: =SUM(F11:F15) -> 4836760.3 | G16: =SUM(G11:G15) -> 429037.5 | H16: =SUM(H11:H15) -> 2421882.2 | I16: =SUM(I11:I15) -> 6829605 | J16: =SUM(J11:J15) -> 1.7556578e+08 | K16: =SUM(K11:K15) -> #REF! | L16: =C16-(E16+K16) -> #REF!
B17: Permisos legales y Preliminares | C17: =SUM('budget (11)'!D51:D52) -> 15000000 | D17: =C17/$D$3 -> 254237.29 | E17: 18740000 | F17: =+'Resumen de Costos 07.24 '!B24 -> 7854532.5 | H17: =+'ANTICIPO 08.24'!D9 -> 1050104.3 | I17: =+F17-G17+H17 -> 8904636.8 | J17: =E17-I17 -> 9835363.2 | K17: =+#REF! -> #REF! | L17: =C17-(E17+K17) -> #REF!
B18: Diseño y Proyecto | C18: =SUM('budget (11)'!D4:D10) -> 20790000 | D18: =C18/$D$3 -> 352372.88 | E18: =+'Finanzas 08.24'!C3 -> 20784948 | F18: =+'Resumen de Costos 08.24 '!B13 -> 20108040 | G18: =+'CXP 08.24'!B20 -> 1740272.8 | H18: =+'ANTICIPO 08.24'!D6 -> 351650 | I18: =+F18-G18+H18 -> 18719417 | J18: =E18-I18 -> 2065530.8 | K18: =+#REF! -> #REF! | L18: =C18-(E18+K18) -> #REF!
B19: Gastos Financieros | C19: =SUM('budget (11)'!D54) -> 192383847 | D19: =C19/$D$3 -> 3260743.2 | E19: =SUM('budget (11)'!E54) -> 0 | I19: =+F19-G19+H19 -> 0 | J19: =E19-I19 -> 0 | K19: =+#REF! -> #REF! | L19: =C19-(E19+K19) -> #REF!
B20: Imprevistos | C20: =SUM('budget (11)'!D53) -> 19238385 | D20: =C20/$D$3 -> 326074.32 | E20: =SUM('budget (11)'!E53) -> 0 | I20: =+F20-G20+H20 -> 0 | J20: =E20-I20 -> 0 | K20: =+#REF! -> #REF! | L20: =C20-(E20+K20) -> #REF!
B21: Total Otros Gastos | C21: =SUM(C17:C20) -> 247412232 | D21: =SUM(D17:D20) -> 4193427.7 | E21: =SUM(E17:E20) -> 39524948 | F21: =SUM(F17:F20) -> 27962572 | G21: =SUM(G17:G20) -> 1740272.8 | H21: =SUM(H17:H20) -> 1401754.3 | I21: =SUM(I17:I20) -> 27624054 | J21: =SUM(J17:J20) -> 11900894 | K21: =SUM(K17:K20) -> #REF! | L21: =C21-(E21+K21) -> #REF!
B22: TOTALES | C22: =C5+C10+C16+C21 -> 2.8318619e+09 | D22: =D5+D10+D16+D21 -> 47997660 | E22: =E21+E16+E10+E5 -> 4.9942078e+08 | F22: =F21+F16+F10+F5 -> 1.37093e+08 | G22: =G21+G16+G10+G5 -> 2359941.9 | H22: =H21+H16+H10+H5 -> 5848990.6 | I22: =I21+I16+I10+I5 -> 1.4058205e+08 | J22: =J21+J16+J10+J5 -> 3.5883873e+08 | K22: =K21+K16+K10+K5 -> #REF! | L22: =L21+L16+L10+L5 -> #REF!
E23: =+E22-E8-E11-E12 -> 1.5508167e+08 | J23: =J17 -> 9835363.2
E24: 12132268 | G24: Aportes AFI | H24: =+'BCE 08.24'!C37 -> 1.5969577e+08 | I24: 160000000 | K24: permisos por iniciar | N24: Dato del ADI | O24: 2.8318619e+09
E25: =+E17-E24 -> 6607731.5 | G25: Balance Bancos | H25: =-'BCE 08.24'!C11 -> -20050821 | I25: =I24-I22 -> 19417948 | J25: =E18-I18 -> 2065530.8 | K25: diseño por pagar | N25: Dato Procore | O25: =C22 -> 2.8318619e+09
E26: =+E22-E25 -> 492813050 | G26: Retenciones por pagar | H26: =+'BCE 08.24'!C27+'BCE 08.24'!C28+'BCE 08.24'!C29+'BCE 08.24'!C30 -> 594069.04 | I26: =+J13+J14+J17+J18+J6 -> 15552974 | J26: =E14-I14 -> 3159133.9 | K26: Publicidade por pagar | N26: Diferencia | O26: =O24-O25 -> -0.55799961
E27: diponible | G27: Pagado según balanza | H27: =SUM(H24:H26) -> 1.4023902e+08 | I27: =I25-I26 -> 3864974
G28: Pagado según reportes | H28: =+I22 -> 1.4058205e+08
G29: Diferencial cambiario | H29: =+H27-H28 -> -343030.87 | I29: =+'BCE 08.24'!C38+'PRESENTACIÓN Al 31082024'!H29 -> -340630
B32: Total Gastos Operativos
B33: Permisos legales y Preliminares
B34: Diseño y Proyecto
B35: Gastos Financieros
B36: Imprevistos
B37: Total Otros Gastos
B38: TOTALES
B41: APORTE AFI | C41: 160000000
B42: Gastado y comprometido | C42: =I22+I26 -> 156135026 | D42: =C42/C41 -> 0.97584391
B43: Disponible | C43: =C41-C42 -> 3864974 | D43: =C43/C41 -> 0.024156087

Sheet FLUJO Y DISPONIBLE 08.24
D2: 59.9
B3: 160000000 | C3: =B3-C4 -> 65967960 | D3: =C3-(SUM(D5:D8)) -> 41084982
B4: TERRENO | C4: 94032040
B5: DISENO Y PROYECTO | D5: =D10*$D$2 -> 9215810.2
B6: PRELIMINARES DEL PROYECTO | D6: =D11*$D$2 -> 781278.1
B7: PERMISOS | D7: =D12*$D$2 -> 11511124
B8: PUBLICIDAD | D8: =D13*$D$2 -> 3374766
D10: 153853.26
D11: 13043.04
D12: 192172.35
D13: 56340
C16: FECHA1 | D16: ACUMULADO AGOSTO 2024 | E16: 45536 | F16: 45566 | G16: 45597 | H16: 45627 | I16: 45658 | J16: 45689 | K16: 45717
B17: APORTE INICIAL | C17: 160000000
B18: DISPONIBLE | D18: =C17-D19 -> 19417948 | E18: =D18-E19 -> 13916161 | F18: =E18-F19 -> 3441789.4 | G18: =F18-G19 -> -1367051.3 | H18: =G18-H19 -> -5775892.1 | I18: =H18-I19 -> -7725892.1 | J18: =I18-J19 -> -9675892.1 | K18: =J18-K19 -> -11625892
B19: TOTAL GASTO | D19: =SUM(D21:D31) -> 1.4058205e+08 | E19: =SUM(E21:E31) -> 5501786.5 | F19: =SUM(F21:F31) -> 10474372 | G19: =SUM(G21:G31) -> 4808840.8 | H19: =SUM(H21:H31) -> 4408840.8 | I19: =SUM(I21:I31) -> 1950000 | J19: =SUM(J21:J31) -> 1950000 | K19: =SUM(K21:K31) -> 1950000
B21: TERRENO | D21: =+'PRESENTACIÓN Al 31082024'!I5 -> 94172342
B22: DISENO Y PROYECTO | D22: =+'PRESENTACIÓN Al 31082024'!I18 -> 18719417 | E22: 1000000 | F22: =+'PRESENTACIÓN Al 31082024'!J18-'FLUJO Y DISPONIBLE 08.24'!E22 -> 1065530.8
B23: PRELIMINARES DEL PROYECTO | D23: =+'PRESENTACIÓN Al 31082024'!I17+'PRESENTACIÓN Al 31082024'!I13 -> 9142490.8 | E23: 2458840.8 | F23: 2458840.8 | G23: 2458840.8 | H23: 2458840.8
B24: URBANISMO | D24: =+'PRESENTACIÓN Al 31082024'!I6 -> 11063869 | E24: =+'PRESENTACIÓN Al 31082024'!J6 -> 492945.71
B25: PROMOCION Y PUBLICIDAD | D25: =+'PRESENTACIÓN Al 31082024'!I14 -> 6430575.1 | E25: 800000 | F25: 3200000 | G25: 1600000 | H25: 1200000 | I25: 1200000 | J25: 1200000 | K25: 1200000
B28: Gerencias | D28: =+'PRESENTACIÓN Al 31082024'!I8+'PRESENTACIÓN Al 31082024'!I11 -> 1053358.5 | E28: 750000 | F28: 750000 | G28: 750000 | H28: 750000 | I28: 750000 | J28: 750000 | K28: 750000
B29: Impuesto de transferencia
B30: IFC (lote 1 y lote 2) | F30: 3000000
E33: =SUM(E28:E32) -> 750000
B39: 4837716.2
B40: 6800000 | C40: permisos por iniciar
B41: 8480849.8 | C41: diseño por pagar
B42: 2390947.5 | C42: Publicidade por pagar
B43: =SUM(B39:B42) -> 22509514

Sheet CXP 09.24
A1: Aged Payables Summary
A2: Fideicomiso Irrevocable de Desarrollo Inmobiliario y Administración Araya
A3: As at 30 September 2024
A4: Ageing by due date
A6: Contact | B6: Total
A8: Costo Urbanismo, Gerencia de Construcción, Publicidad: Medios Tradicionales y Digitales
A9: TECNICA MMHB SRL | B9: 307672.8
A10: Total Costo Urbanismo, Gerencia de Construcción, Publicidad: Medios Tradicionales y Digitales | B10: =B9 -> 307672.8
A12: Diseño y Proyecto
A13: ADVANCEBAU LLC | B13: 60314.2
A14: ECOTURISMO MUNDIAL Y PROYECTOS AMBIENTALES SRL(EMPACA) | B14: 373780.56
A15: Total Diseño y Proyecto | B15: =SUM(B13:B14) -> 434094.76
A17: Eventos Publicitarios y Material Promocional
A18: INMOBILIARIA PEREZ & PINEDA SRL | B18: 4374
A19: Total Eventos Publicitarios y Material Promocional | B19: =B18 -> 4374
A21: Total | B21: =SUM(B10,B15,B19) -> 746141.56
A23: Percentage of total | B23: =(SUM(B10,B15,B19) / SUM(B10,B15,B19)) -> 1

Sheet Finanzas 09.24
A1: Budget Code > Cost Code Tier 2 Description | B1: Columnas personalizadas > Monto Total Presupuestado | C1: Commitment Line Item > Amount | D1: Commitment > Payments Issued | E1: Columnas personalizadas > Restante
A2: TERRENO | B2: 103385169 | C2: 94172342 | D2: 94172342 | E2: =+C2-D2 -> 0
A3: DISEÑO Y PROYECTO | B3: 20790000 | C3: 20360290 | D3: 19304682 | E3: =+C3-D3 -> 1055607.8
A4: URBANISMO | B4: 451759000 | C4: 10652617 | D4: 9997047.4 | E4: =+C4-D4 -> 655570.06
A5: EDIFICACIONES | B5: 1265953920 | E5: =+C5-D5 -> 0
A6: GERENCIA DE CONSTRUCCION | B6: 171771292 | C6: 1525635.1 | D6: 1406538 | E6: =+C6-D6 -> 119097.14
A7: INDIRECTOS DE OBRA | B7: 34354258 | E7: =+C7-D7 -> 0
A8: GERENCIA DE LA PROMOTORA | B8: 137417034 | C8: 161175.97 | D8: 161175.97 | E8: =+C8-D8 -> 0
A9: GERENCIA DE VENTAS | B9: 281704919 | C9: 0 | D9: 0 | E9: =+C9-D9 -> 0
A10: ADMINISTRACION DE FIDUCIARIA | B10: 67334346 | C10: 237853.9 | D10: 237853.9 | E10: =+C10-D10 -> 0
A11: PUBLICIDAD Y PROMOCION | B11: 51531388 | C11: 10757675 | D11: 6276981.1 | E11: =+C11-D11 -> 4480694.3
A12: POST-VENTAS | B12: 19238385 | E12: =+C12-D12 -> 0
A13: PERMISOS LEGALES Y PRELIMINARES | B13: 15000000 | C13: 15920579 | D13: 9725292.8 | E13: =+C13-D13 -> 6195285.8
A14: IMPREVISTOS | B14: 19238385 | E14: =+C14-D14 -> 0
A15: GASTOS FINANCIEROS | B15: 192383847 | E15: =+C15-D15 -> 0
B16: =SUM(B2:B15) -> 2.8318619e+09 | C16: =SUM(C2:C15) -> 1.5378817e+08 | D16: =SUM(D2:D15) -> 1.4128191e+08 | E16: =SUM(E2:E15) -> 12506255

Sheet ANTICIPO 09.24
A1: Approved and paid
A2: Fideicomiso Irrevocable de Desarrollo Inmobiliario y Administración Araya
A3: For the period 1 September 2014 to 30 September 2024
A5: Source contains Payable Prepayment
A6: Status contains Accepted, Approved, Billed, Current, Invoiced, Sent
A8: Contact | B8: Reference | C8: Last Payment Date | D8: Net (DOP) | E8: Payments / Debits (DOP) | F8: Balance (Source) | G8: COSTOS DE OBRA
A9: HIDROPOZO SRL | B9: ANTICIPO HIDROPOZOS | C9: 45266 | D9: -273000 | E9: 0 | F9: -273000 | G9: Diseño y Proyecto
A10: ONEIDA MARIA FRIAS PADILLA | B10: PO--020 | C10: 45429 | D10: -40000 | E10: 0 | F10: -40000 | G10: Diseño y Proyecto
A11: MARY VANGIE GRULLON CACERES | B11: ANTICIPO MARY | C11: 45469 | D11: -38250 | E11: 0 | F11: -38250 | G11: Diseño y Proyecto
A12: INVERSIONES BRICKET C A | B12: PAGO DUPLICADO INV. BRICKET | C12: 45552 | D12: -650700 | E12: 0 | G12: Diseño y Proyecto
D13: =SUM(D9:D12) -> -1001950 | E13: =SUM(E9:E12) -> 0 | F13: =SUM(F9:F12) -> -351250
A15: LUCES INDUSTRIALES SRL | B15: ANTICIPO WORLD SIGN | C15: 45565 | D15: -144800 | E15: 0 | F15: =+D15-E15 -> -144800 | G15: Eventos Publicitarios y Material Promocional
A16: TECNICA MMHB SRL | B16: ANTICIPO TECNICA | C16: 45565 | D16: -1617766.3 | E16: -1181495.3 | F16: =+D16-E16 -> -436271.07 | G16: Preliminares de Obra
A17: TECNICA MMHB SRL | B17: ANTICIPO TECNICA | C17: 45565 | D17: -2082233.7 | E17: -1520707.4 | F17: =+D17-E17 -> -561526.27 | G17: Publicidad: Medios Tradicionales y Digitales
A18: LMCAD ESTUDIO DE ANIMACION SRL | C18: 45512 | D18: -747236.25 | E18: 0 | F18: =+D18-E18 -> -747236.25 | G18: Publicidad: Medios Tradicionales y Digitales
D19: =SUM(D15:D18) -> -4592036.2 | E19: =SUM(E15:E18) -> -2702202.7 | F19: =SUM(F15:F18) -> -1889833.6
A21: Total | D21: =+D13+D19 -> -5593986.2 | E21: =+E13+E19 -> -2702202.7 | F21: =+F13+F19 -> -2241083.6

Sheet BCE 09.24
A1: Balance Sheet
A2: Fideicomiso Irrevocable de Desarrollo Inmobiliario y Administración Araya
A3: As at 30 September 2024
B5: Account | C5: 30 Sep 2024
A7: Assets
B8: Bank
B9: Banesco DOP -Cta. Corriente No.99100010856 | C9: 16674524
B10: Banesco USD -Cta. Ahorro No.99200013780 | C10: 172810.98 | D10: [FX]
B11: Total Bank | C11: =SUM(C9:C10) -> 16847335
B12: Current Assets
B13: Anticipos a Proveedores | C13: 2892183.6
B14: Total Current Assets | C14: =C13 -> 2892183.6
B15: Non-current Assets
B16: Costos de Construccion | C16: 31528923
B17: Costos Operativos | C17: 6676011
B18: Otros Costos (123906) | C18: 8904636.8
B19: Terreno | C19: 94172342
B20: Total Non-current Assets | C20: =SUM(C16:C19) -> 1.4128191e+08
A21: Total Assets | C21: =(0 + ((C11 + C14) + C20)) -> 1.6102143e+08
A23: Liabilities
B24: Current Liabilities
B25: Cuentas por Pagar Comerciales | C25: 746141.56
B26: Otras Cuentas por Pagar | C26: 131350
B27: Ret 100% ITBIS. Personas Fsicas | C27: 36360
B28: Retencin 30% ITBIS Juridica | C28: 34167.35
B29: Retencin ISR Exterior 27% | C29: 260416.02
B30: Retencin ISR Personas Fsicas 10% | C30: 20200
B31: Total Current Liabilities | C31: =SUM(C25:C30) -> 1228634.9
A32: Total Liabilities | C32: =(0 + C31) -> 1228634.9
B34: Net Assets | C34: =(C21 - C32) -> 1.597928e+08
A36: Equity
B37: Aporte Fideicomitente AFI Universal | C37: 1.5969577e+08
B38: Current Year Earnings | C38: 97023.17
A39: Total Equity | C39: =SUM(C37:C38) -> 1.597928e+08
A42: [FX] Exchange rates used to convert foreign currency into DOP are shown below. Rates are provided by XE.com unless otherwise stated.
A43: 30 Sep 2024
A44: 0.0165736 USD (United States Dollar)

Sheet PRESENTACIÓN Al 30092024
M1: IMAGEN DEL ADI archivo : Flujo_de_caja_PUNTA_CANA_462_MAR2024_V.0.XLSX al 02/05/24
F2: a | K2: d | L2: e
B3: CONTROL PRESUPUESTAL | E3: 59 | F3: COMPROMETIDO | G3: EJECUTADO | H3: CXP DE LO EJECUTADO | I3: ANTICIPOS PAGADOS | J3: PAGADO | K3: POR EJECUTAR DE LO COMPROMETIDO | L3: PROYECTADO PARA TERMINAR
B4: PARTIDA | C4: ADI MARZO-24 | D4: ADI AGO-24 | E4: US $
A5: 1 | B5: Terreno | C5: =SUM('budget (11)'!D2:D3) -> 103385169 | D5: 103385169 | E5: =D5/E3 -> 1752291 | F5: =+'Finanzas 09.24'!C2 -> 94172342 | G5: =+'Finanzas 09.24'!D2 -> 94172342 | H5: 0 | J5: =+G5-H5+I5 -> 94172342 | K5: =F5-J5 -> 0 | L5: =+D5-F5 -> 9212827.2
B6: Costo Urbanismo | C6: =SUM('budget (11)'!D11:D24) -> 4.51759e+08 | D6: 4.51759e+08 | E6: =D6/$E$3 -> 7656932.2 | F6: =+'Finanzas 09.24'!C4 -> 10652617 | G6: =+'Finanzas 09.24'!D4 -> 9997047.4 | I6: =-'ANTICIPO 09.24'!F16 -> 436271.07 | J6: =+G6-H6+I6 -> 10433318 | K6: =F6-J6 -> 219298.99 | L6: =+D6-F6 -> 4.4110638e+08
B7: Costo Vivienda | C7: =SUM('budget (11)'!D25:D39) -> 1265953920 | D7: =1447934796 -> 1447934796 | E7: =D7/$E$3 -> 24541268 | F7: =SUM('budget (11)'!E25:E39) -> 0 | J7: =+G7-H7+I7 -> 0 | K7: =F7-J7 -> 0 | L7: =+D7-F7 -> 1447934796
B8: Fondo de Contingencia | C8: 0 | D8: 37993876 | E8: =D8/$E$3 -> 643964
B9: Gerencia Construcción: | C9: =SUM('budget (11)'!D40:D41) -> 171771292 | D9: 189969380 | E9: =D9/$E$3 -> 3219820 | F9: =+'Finanzas 09.24'!C6 -> 1525635.1 | G9: =+'Finanzas 09.24'!D6 -> 1406538 | H9: =+'CXP 09.24'!B10 -> 307672.8 | J9: =+G9-H9+I9 -> 1098865.2 | K9: =F9-J9 -> 426769.94 | L9: =+D9-F9 -> 1.8844374e+08
B10: Indirectos de Obra | C10: =SUM('budget (11)'!D42) -> 34354258 | D10: 37993876 | E10: =D10/$E$3 -> 643964 | F10: =SUM('budget (11)'!E42) -> 0 | J10: =+G10-H10+I10 -> 0 | K10: =F10-J10 -> 0 | L10: =+D10-F10 -> 37993876
B11: Total Costos Construcción | C11: =SUM(C6:C10) -> 1923838470 | D11: =SUM(D6:D10) -> 2165650928 | E11: =SUM(E6:E10) -> 36705948 | F11: =SUM(F6:F10) -> 12178253 | G11: =SUM(G6:G10) -> 11403585 | H11: =SUM(H6:H10) -> 307672.8 | I11: =SUM(I6:I10) -> 436271.07 | J11: =SUM(J6:J10) -> 11532184 | ... L11: =SUM(L6:L10) -> 2.1154788e+09
B12: Gerencia de la Promotora | C12: =SUM('budget (11)'!D43) -> 137417034 | D12: 151975504 | E12: =D12/$E$3 -> 2575856 | F12: =+'Finanzas 09.24'!C8 -> 161175.97 | G12: =+'Finanzas 09.24'!D8 -> 161175.97 | J12: =+G12-H12+I12 -> 161175.97 | K12: =F12-J12 -> 0 | L12: =+D12-F12 -> 1.5181433e+08
B13: Gerencia de Ventas | C13: =SUM('budget (11)'!D45:D46) -> 281704919 | D13: 308130334 | E13: =D13/$E$3 -> 5222548 | F13: =+'Finanzas 09.24'!C9 -> 0 | J13: =+G13-H13+I13 -> 0 | K13: =F13-J13 -> 0 | L13: =+D13-F13 -> 308130334
B14: Administración Fiducia | C14: =SUM('budget (11)'!D47) -> 67334346 | D14: 75797782 | E14: =D14/$E$3 -> 1284708.2 | F14: =+'Finanzas 09.24'!C10 -> 237853.9 | G14: =+'Finanzas 09.24'!D10 -> 237853.9 | J14: =+G14-H14+I14 -> 237853.9 | K14: =F14-J14 -> 0 | L14: =+D14-F14 -> 75559928
A15: 1 | B15: Publicidad | C15: =SUM('budget (11)'!D48:D49) -> 51531388 | D15: 56990814 | E15: =D15/$E$3 -> 965946 | F15: =+'Finanzas 09.24'!C11 -> 10757675 | G15: =+'Finanzas 09.24'!D11 -> 6276981.1 | H15: =+'CXP 09.24'!B19 -> 4374 | I15: =-'ANTICIPO 09.24'!F15-'ANTICIPO 09.24'!F17-'ANTICIPO 09.24'!F18 -> 1453562.5 | J15: =+G15-H15+I15 -> 7726169.6 | K15: =F15-J15 -> 3031505.8 | L15: =+D15-F15 -> 46233139
B16: Post Ventas | C16: =SUM('budget (11)'!D50) -> 19238385 | D16: 21656506 | E16: =D16/$E$3 -> 367059.42 | F16: =SUM('budget (11)'!E50) -> 0 | J16: =+G16-H16+I16 -> 0 | K16: =F16-J16 -> 0 | L16: =+D16-F16 -> 21656506
B17: Total Gastos Operativos | C17: =SUM(C12:C16) -> 5.5722607e+08 | D17: =SUM(D12:D16) -> 614550940 | E17: =SUM(E12:E16) -> 10416118 | F17: =SUM(F12:F16) -> 11156705 | G17: =SUM(G12:G16) -> 6676011 | H17: =SUM(H12:H16) -> 4374 | I17: =SUM(I12:I16) -> 1453562.5 | J17: =SUM(J12:J16) -> 8125199.5 | ... L17: =SUM(L12:L16) -> 6.0339423e+08
B18: Permisos legales y Preliminares | C18: =SUM('budget (11)'!D51:D52) -> 15000000 | D18: 30500000 | E18: =D18/$E$3 -> 516949.15 | F18: =+'Finanzas 09.24'!C13 -> 15920579 | G18: =+'Finanzas 09.24'!D13 -> 9725292.8 | J18: =+G18-H18+I18 -> 9725292.8 | K18: =F18-J18 -> 6195285.8 | L18: =+D18-F18 -> 14579421
B19: Diseño y Proyecto | C19: =SUM('budget (11)'!D4:D10) -> 20790000 | D19: 20790000 | E19: =D19/$E$3 -> 352372.88 | F19: =+'Finanzas 09.24'!C3 -> 20360290 | G19: =+'Finanzas 09.24'!D3 -> 19304682 | H19: =+'CXP 09.24'!B15 -> 434094.76 | I19: =-'ANTICIPO 09.24'!F13 -> 351250 | J19: =+G19-H19+I19 -> 19221837 | K19: =F19-J19 -> 1138452.6 | L19: =+D19-F19 -> 429710.44
B20: Gastos Financieros | C20: =SUM('budget (11)'!D54) -> 192383847 | D20: 216565093 | E20: =D20/$E$3 -> 3670594.8 | F20: =SUM('budget (11)'!E54) -> 0 | J20: =+G20-H20+I20 -> 0 | K20: =F20-J20 -> 0 | L20: =+D20-F20 -> 216565093
B21: Imprevistos | C21: =SUM('budget (11)'!D53) -> 19238385 | D21: 21656509 | E21: =D21/$E$3 -> 367059.47 | F21: =SUM('budget (11)'!E53) -> 0 | J21: =+G21-H21+I21 -> 0 | K21: =F21-J21 -> 0 | L21: =+D21-F21 -> 21656509
B22: Total Otros Gastos | C22: =SUM(C18:C21) -> 247412232 | D22: =SUM(D18:D21) -> 289511602 | E22: =SUM(E18:E21) -> 4906976.3 | F22: =SUM(F18:F21) -> 36280868 | G22: =SUM(G18:G21) -> 29029975 | H22: =SUM(H18:H21) -> 434094.76 | I22: =SUM(I18:I21) -> 351250 | J22: =SUM(J18:J21) -> 28947130 | ... L22: =SUM(L18:L21) -> 2.5323073e+08
B23: TOTALES | C23: =C5+C11+C17+C22 -> 2.8318619e+09 | D23: =D5+D11+D17+D22 -> 3173098639 | E23: =E5+E11+E17+E22 -> 53781333 | F23: =F22+F17+F11+F5 -> 1.5378817e+08 | G23: =G22+G17+G11+G5 -> 1.4128191e+08 | H23: =H22+H17+H11+H5 -> 746141.56 | I23: =I22+I17+I11+I5 -> 2241083.6 | J23: =J22+J17+J11+J5 -> 1.4277685e+08 | K23: =K22+K17+K11+K5 -> 11011313 | L23: =L22+L17+L11+L5 -> 2.9813166e+09
F24: =+F23-F9-F12-F13 -> 1.5210136e+08
F25: 15099923 | H25: Aportes AFI | I25: =+'BCE 09.24'!C37 -> 1.5969577e+08 | J25: 160000000 | N25: Dato del ADI | O25: 2.8318619e+09
F26: =+F18-F25 -> 820656 | H26: Balance Bancos | I26: =-'BCE 09.24'!C11-650700 -> -17498035 | J26: =J25-J23 -> 17223145 | N26: Dato Procore | O26: =C23 -> 2.8318619e+09
F27: =+F23-F26 -> 1.5296751e+08 | H27: Retenciones por pagar | I27: =+'BCE 09.24'!C26+'BCE 09.24'!C27+'BCE 09.24'!C28+'BCE 09.24'!C29+'BCE 09.24'!C30 -> 482493.37 | J27: =+K23 -> 11011313 | N27: Diferencia | O27: =O25-O26 -> -0.55799961
F28: diponible | H28: Pagado según balanza | I28: =SUM(I25:I27) -> 1.4268023e+08 | J28: =J26-J27 -> 6211832.1
H29: Pagado según reportes | I29: =+J23 -> 1.4277685e+08
H30: Diferencial cambiario | I30: =+I28-I29 -> -96623.17 | J30: =+'BCE 09.24'!C38 -> 97023.17 | K30: =+I30+J30 -> 400
B33: Total Gastos Operativos
B34: Permisos legales y Preliminares
B35: Diseño y Proyecto
B36: Gastos Financieros
B37: Imprevistos
B38: Total Otros Gastos
B39: TOTALES
B42: APORTE AFI | C42: 160000000
B43: Gastado y comprometido | C43: =J23+J27 -> 1.5378817e+08 | E43: =C43/C42 -> 0.96117605
B44: Disponible | C44: =C42-C43 -> 6211832.1 | E44: =C44/C42 -> 0.038823951

Sheet FLUJO Y DISPONIBLE 09.24
D2: 59.9
B3: 160000000 | C3: =B3-C4 -> 65967960 | D3: =C3-(SUM(D5:D8)) -> 41084982
B4: TERRENO | C4: 94032040
B5: DISENO Y PROYECTO | D5: =D10*$D$2 -> 9215810.2
B6: PRELIMINARES DEL PROYECTO | D6: =D11*$D$2 -> 781278.1
B7: PERMISOS | D7: =D12*$D$2 -> 11511124
B8: PUBLICIDAD | D8: =D13*$D$2 -> 3374766
D10: 153853.26
D11: 13043.04
D12: 192172.35
D13: 56340
C16: FECHA1 | D16: ACUMULADO SEPTIEMBRE 2024 | E16: 45566 | F16: 45597 | G16: 45627 | H16: 45658 | I16: 45689 | J16: 45717
B17: APORTE INICIAL | C17: 160000000
B18: DISPONIBLE | D18: =C17-D19 -> 17223145 | E18: =D18-E19 -> 11406553 | F18: =E18-F19 -> 197712.04 | G18: =F18-G19 -> -5561128.7 | H18: =G18-H19 -> -11011129 | I18: =H18-I19 -> -15061129 | J18: =I18-J19 -> -19111129
B19: TOTAL GASTO | D19: =SUM(D21:D33) -> 1.4277685e+08 | E19: =SUM(E21:E33) -> 5816592.3 | F19: =SUM(F21:F33) -> 11208841 | G19: =SUM(G21:G33) -> 5758840.8 | H19: =SUM(H21:H33) -> 5450000 | I19: =SUM(I21:I33) -> 4050000 | J19: =SUM(J21:J33) -> 4050000
B21: TERRENO | D21: =+'PRESENTACIÓN Al 30092024'!J5 -> 94172342
B22: DISENO Y PROYECTO | D22: =+'PRESENTACIÓN Al 30092024'!J19 -> 19221837 | E22: =+'PRESENTACIÓN Al 30092024'!K19 -> 1138452.6
B23: PERMISOS PRELIMINARES DEL PROYECTO | D23: =+'PRESENTACIÓN Al 30092024'!J14+'PRESENTACIÓN Al 30092024'!J18 -> 9963146.8 | E23: 2458840.8 | F23: 2458840.8 | G23: 2458840.8 | H23: 1400000
B24: URBANISMO | D24: =+'PRESENTACIÓN Al 30092024'!J6 -> 10433318 | E24: =+'PRESENTACIÓN Al 30092024'!K6 -> 219298.99
B25: PROMOCION Y PUBLICIDAD | D25: =+'PRESENTACIÓN Al 30092024'!J15 -> 7726169.6 | E25: 1000000 | F25: 3600000 | G25: 1650000 | H25: 1650000 | I25: 1650000 | J25: 1650000
B28: Gerencia Construcción | D28: =+'PRESENTACIÓN Al 30092024'!J9+'PRESENTACIÓN Al 30092024'!J12 -> 1260041.1 | E28: 500000 | F28: 500000 | G28: 500000 | H28: 1000000 | I28: 1000000 | J28: 1000000
B29: Gerencia Promotora | E29: 500000 | F29: 500000 | G29: 500000 | H29: 750000 | I29: 750000 | J29: 750000
B30: Gerencia de Ventas(Adm Ventas) | F30: 650000 | G30: 650000 | H30: 650000 | I30: 650000 | J30: 650000
B31: Comisiones de Ventas | F31: 500000
B32: Impuesto de transferencia
B33: IFC (lote 1 y lote 2) | F33: 3000000
B41: 4837716.2
B42: 6800000 | C42: permisos por iniciar
B43: 8480849.8 | C43: diseño por pagar
B44: 2390947.5 | C44: Publicidade por pagar
B45: =SUM(B41:B44) -> 22509514

Sheet CXP 11.24
A1: Aged Payables Detail
A2: Fideicomiso Irrevocable de Desarrollo Inmobiliario y Administración Araya
A3: As at 30 November 2024
A4: Ageing by due date
A6: Contact | B6: Invoice Date | C6: Invoice Reference | D6: Total
A8: Gerencia de Construcción
A9: TECNICA MMHB SRL | B9: 45626 | C9: B0100000159 | D9: 19672.22
A10: Total Gerencia de Construcción | D10: =D9 -> 19672.22
A12: Diseño y Proyecto
A13: ADVANCEBAU LLC | B13: 45453 | C13: INT.061024 | D13: 60314.2
A14: ANDRES MONTERO LANDSCAPE ARCHITECTURE | B14: 45623 | C14: 20241120 | D14: 123801.1
A15: Total Diseño y Proyecto | D15: =SUM(D13:D14) -> 184115.3
A17: Gerencia de Ventas
A18: MATASIETE SRL | B18: 45626 | C18: B0100000496 | D18: 279677.77
A19: Total Gerencia de Ventas | D19: =D18 -> 279677.77
A21: Publicidad: Medios Tradicionales y Digitales
A22: ESTRUCTURAS PUBLICITARIAS Y GRAFICOS EPUGRAF SRL | B22: 45614 | C22: B0100000046 | D22: 74800
A23: ESTRUCTURAS PUBLICITARIAS Y GRAFICOS EPUGRAF SRL | B23: 45616 | C23: B0100000048 | D23: 18802
A24: LUCES INDUSTRIALES SRL | B24: 45624 | C24: B0100008807 | D24: 88264
A25: TECNICA MMHB SRL | B25: 45624 | C25: B0100000158 | D25: 282126
A26: Total Publicidad: Medios Tradicionales y Digitales | D26: =SUM(D22:D25) -> 463992
A28: Total | D28: =SUM(D10,D15,D19,D26) -> 947457.29
A30: Percentage of total | D30: =(SUM(D10,D15,D19,D26) / SUM(D10,D15,D19,D26)) -> 1

Sheet Finanzas 11.24
A1: No | B1: Código de presupuesto | C1: Monto del presupuesto original | D1: Cambio de presupuesto | E1: Monto Total Presupuestado | F1: Monto Total Comprometido | G1: Trabajo Ejectutado
A2: 1 | B2: TERRENO | C2: 103385169 | E2: 103385169 | F2: 94172342 | G2: 94172342
A3: 2 | B3: DISEÑO Y PROYECTO | C3: 20790000 | D3: 0 | E3: 20790000 | F3: 20953109 | G3: 20098510
A4: 3 | B4: URBANISMO | C4: 451759000 | E4: 451759000 | F4: 9219083.6 | G4: 9219083.6
A5: 4 | B5: EDIFICACIONES | C5: 1265953920 | E5: 1265953920 | F5: 0
A6: 5 | B6: GERENCIA DE CONSTRUCCION | C6: 171771292 | D6: 18198088 | E6: 189969380 | F6: 1644662 | G6: 1644662
A7: 6 | B7: INDIRECTOS DE OBRA | C7: 34354258 | D7: 3639618 | E7: 37993876 | F7: 0
A8: 7 | B8: FONDO DE CONTINGENCIA | C8: 0 | D8: 37993876 | E8: 37993876 | F8: 0
A9: 8 | B9: GERENCIA DE LA PROMOTORA | C9: 137417034 | D9: 14558470 | E9: 151975504 | F9: 161175.97 | G9: 161175.97
A10: 9 | B10: ADMINISTRACION DE FIDUCIARIA | C10: 67334346 | D10: 8463436 | E10: 75797782 | F10: 330277.4 | G10: 330277.4
A11: 10 | B11: GERENCIA DE VENTAS | C11: 281704919 | D11: 26425415 | E11: 308130334 | F11: 279677.77 | G11: 279677.77
A12: 11 | B12: PUBLICIDAD Y PROMOCION | C12: 51531388 | D12: 5459426 | E12: 56990814 | F12: 14045810 | G12: 11180540
A13: 12 | B13: POST-VENTAS | C13: 19238385 | D13: 2418121 | E13: 21656506 | F13: 0
A14: 13 | B14: IMPREVISTOS | C14: 19238385 | D14: 2418124 | E14: 21656509 | F14: 0
A15: 14 | B15: GASTOS FINANCIEROS | C15: 192383847 | D15: 24181246 | E15: 216565093 | F15: 0
A16: 15 | B16: PERMISOS LEGALES Y PRELIMINARES | C16: 15000000 | D16: 15500000 | E16: 30500000 | F16: 16703974 | G16: 12591931
B17: Grand Totals | C17: =SUM(C2:C16) -> 2.8318619e+09 | D17: =SUM(D2:D16) -> 1.5925582e+08 | E17: =SUM(E2:E16) -> 2991117763 | F17: =SUM(F2:F16) -> 1.5751011e+08 | G17: =SUM(G2:G16) -> 1.496782e+08

Sheet ANTICIPO 11.24
A1: Approved and paid
A2: Fideicomiso Irrevocable de Desarrollo Inmobiliario y Administración Araya
A3: For the period 1 September 2014 to 30 September 2024
A5: Source contains Payable Prepayment
A6: Status contains Accepted, Approved, Billed, Current, Invoiced, Sent
A8: Contact | B8: Reference | C8: Last Payment Date | D8: Net (DOP) | E8: COSTOS DE OBRA
A9: HIDROPOZO SRL | B9: ANTICIPO HIDROPOZOS | C9: 45266 | D9: -273000 | E9: Diseño y Proyecto
A10: ONEIDA MARIA FRIAS PADILLA | B10: PO--020 | C10: 45429 | D10: -40000 | E10: Diseño y Proyecto
A11: MARY VANGIE GRULLON CACERES | B11: ANTICIPO MARY | C11: 45469 | D11: -38250 | E11: Diseño y Proyecto
A12: ECOTURISMO MUNDIAL Y PROYECTOS AMBIENTALES SRL(EMPACA) | B12: ANTICIPO EMPACA | C12: 45616 | D12: -195834.93 | E12: Diseño y Proyecto
D13: =SUM(D9:D12) -> -547084.93
A15: RIOS & ASOCIADOS ABOGADOS CONSULTORES S R L | B15: ANTICIPO RIOS LEGAL | C15: 45622 | D15: -352775.8 | E15: Permisos, Legales y Preliminares
A16: LMCAD ESTUDIO DE ANIMACION SRL | B16: ANTICIPO LMCAD | C16: 45616 | D16: -376562.5 | E16: Publicidad: Medios Tradicionales y Digitales
A17: LMCAD ESTUDIO DE ANIMACION SRL | C17: 45512 | D17: -747236.25 | E17: Publicidad: Medios Tradicionales y Digitales
D18: =SUM(D15:D17) -> -1476574.6
A20: Total | D20: =+D13+D18 -> -2023659.5

Sheet BCE 11.24
A1: Balance Sheet
A2: Fideicomiso Irrevocable de Desarrollo Inmobiliario y Administración Araya
A3: As at 30 November 2024
B5: Account | C5: 30 Nov 2024
A7: Assets
B8: Bank
B9: Banesco DOP -Cta. Corriente No.99100010856 | C9: 9171515.3
B10: Banesco USD -Cta. Ahorro No.99200013780 | C10: 723710.92 | D10: [FX]
B11: Cuentas por Cobrar Compañía Relacionada USD | C11: 297767.05 | D11: [FX]
B12: Total Bank | C12: =SUM(C9:C11) -> 10192993
B13: Current Assets
B14: Anticipos a Proveedores | C14: 2023659.5
B15: Total Current Assets | C15: =C14 -> 2023659.5
B16: Non-current Assets
B17: Costos de Construcción | C17: 33776105
B18: Costos Operativos | C18: 9945088.9
B19: Otros Costos | C19: 11784664
B20: Terreno | C20: 94172342
B21: Total Non-current Assets | C21: =SUM(C17:C20) -> 1.496782e+08
A22: Total Assets | C22: =(0 + ((C12 + C15) + C21)) -> 1.6189485e+08
A24: Liabilities
B25: Current Liabilities
B26: Cuentas por Pagar Comerciales | C26: 947457.29
B27: Depósitos Diferidos de Clientes | C27: 298015.71
B28: Otras Cuentas por Pagar | C28: 727875.8
B29: Retención 100% ITBIS. Personas Físicas | C29: 57506.01
B30: Retención 30% ITBIS Jurídica | C30: 20544.83
B31: Retención ISR Personas Físicas 10% | C31: 31947.78
B32: Total Current Liabilities | C32: =SUM(C26:C31) -> 2083347.4
A33: Total Liabilities | C33: =(0 + C32) -> 2083347.4
B35: Net Assets | C35: =(C22 - C33) -> 1.5981151e+08
A37: Equity
B38: Aporte Fideicomitente AFI Universal | C38: 1.5969577e+08
B39: Current Year Earnings | C39: 115731.52
A40: Total Equity | C40: =SUM(C38:C39) -> 1.5981151e+08
A43: [FX] Exchange rates used to convert foreign currency into DOP are shown below. Rates are provided by XE.com unless otherwise stated.
A44: 30 Nov 2024
A45: 0.0165700 USD (United States Dollar)

Sheet PRESENTACIÓN 11-24
M1: IMAGEN DEL ADI archivo : Flujo_de_caja_PUNTA_CANA_462_MAR2024_V.0.XLSX al 02/05/24
F2: a | K2: d | L2: e
B3: CONTROL PRESUPUESTAL | E3: 59 | F3: COMPROMETIDO | G3: EJECUTADO | H3: CXP DE LO EJECUTADO | I3: ANTICIPOS PAGADOS | J3: PAGADO | K3: POR PAGAR DE LO COMPROMETIDO | L3: PROYECTADO PARA TERMINAR
B4: PARTIDA | C4: ADI MARZO-24 | D4: ADI AGO-24 | E4: US $
A5: 1 | B5: Terreno | C5: =SUM('budget (11)'!D2:D3) -> 103385169 | D5: 103385169 | E5: =D5/E3 -> 1752291 | F5: =+'Finanzas 11.24'!F2 -> 94172342 | G5: =+'Finanzas 11.24'!G2 -> 94172342 | H5: 0 | J5: =+G5-H5+I5 -> 94172342 | K5: =F5-J5 -> 0 | L5: =+D5-F5 -> 9212827.2
B6: Costo Urbanismo | C6: =SUM('budget (11)'!D11:D24) -> 4.51759e+08 | D6: 4.51759e+08 | E6: =D6/$E$3 -> 7656932.2 | F6: =+'Finanzas 11.24'!F4 -> 9219083.6 | G6: =+'Finanzas 11.24'!G4 -> 9219083.6 | J6: =+G6-H6+I6 -> 9219083.6 | K6: =F6-J6 -> 0 | L6: =+D6-F6 -> 4.4253992e+08
B7: Costo Vivienda | C7: =SUM('budget (11)'!D25:D39) -> 1265953920 | D7: =1447934796 -> 1447934796 | E7: =D7/$E$3 -> 24541268 | F7: =SUM('budget (11)'!E25:E39) -> 0 | G7: =SUM('budget (11)'!F25:F39) -> 0 | J7: =+G7-H7+I7 -> 0 | K7: =F7-J7 -> 0 | L7: =+D7-F7 -> 1447934796
B8: Fondo de Contingencia | C8: 0 | D8: 37993876 | E8: =D8/$E$3 -> 643964
B9: Gerencia Construcción: | C9: =SUM('budget (11)'!D40:D41) -> 171771292 | D9: 189969380 | E9: =D9/$E$3 -> 3219820 | F9: =+'Finanzas 11.24'!F6 -> 1644662 | G9: =+'Finanzas 11.24'!G6 -> 1644662 | H9: =+'CXP 11.24'!D10 -> 19672.22 | J9: =+G9-H9+I9 -> 1624989.8 | K9: =F9-J9 -> 19672.22 | L9: =+D9-F9 -> 1.8832472e+08
B10: Indirectos de Obra | C10: =SUM('budget (11)'!D42) -> 34354258 | D10: 37993876 | E10: =D10/$E$3 -> 643964 | F10: =SUM('budget (11)'!E42) -> 0 | G10: =SUM('budget (11)'!F42) -> 0 | J10: =+G10-H10+I10 -> 0 | K10: =F10-J10 -> 0 | L10: =+D10-F10 -> 37993876
B11: Total Costos Construcción | C11: =SUM(C6:C10) -> 1923838470 | D11: =SUM(D6:D10) -> 2165650928 | E11: =SUM(E6:E10) -> 36705948 | F11: =SUM(F6:F10) -> 10863746 | G11: =SUM(G6:G10) -> 10863746 | H11: =SUM(H6:H10) -> 19672.22 | I11: =SUM(I6:I10) -> 0 | J11: =SUM(J6:J10) -> 10844073 | ... L11: =SUM(L6:L10) -> 2.1167933e+09
B12: Gerencia de la Promotora | C12: =SUM('budget (11)'!D43) -> 137417034 | D12: 151975504 | E12: =D12/$E$3 -> 2575856 | F12: =+'Finanzas 11.24'!F9 -> 161175.97 | G12: =+'Finanzas 11.24'!G9 -> 161175.97 | J12: =+G12-H12+I12 -> 161175.97 | K12: =F12-J12 -> 0 | L12: =+D12-F12 -> 1.5181433e+08
B13: Gerencia de Ventas | C13: =SUM('budget (11)'!D45:D46) -> 281704919 | D13: 308130334 | E13: =D13/$E$3 -> 5222548 | F13: =+'Finanzas 11.24'!F11 -> 279677.77 | G13: =+'Finanzas 11.24'!G11 -> 279677.77 | H13: =+'CXP 11.24'!D19 -> 279677.77 | J13: =+G13-H13+I13 -> 0 | K13: =F13-J13 -> 279677.77 | L13: =+D13-F13 -> 3.0785066e+08
B14: Administración Fiducia | C14: =SUM('budget (11)'!D47) -> 67334346 | D14: 75797782 | E14: =D14/$E$3 -> 1284708.2 | F14: =+'Finanzas 11.24'!F10 -> 330277.4 | G14: =+'Finanzas 11.24'!G10 -> 330277.4 | J14: =+G14-H14+I14 -> 330277.4 | K14: =F14-J14 -> 0 | L14: =+D14-F14 -> 75467505
A15: 1 | B15: Publicidad | C15: =SUM('budget (11)'!D48:D49) -> 51531388 | D15: 56990814 | E15: =D15/$E$3 -> 965946 | F15: =+'Finanzas 11.24'!F12 -> 14045810 | G15: =+'Finanzas 11.24'!G12 -> 11180540 | H15: =+'CXP 11.24'!D26 -> 463992 | I15: =-'ANTICIPO 11.24'!D16-'ANTICIPO 11.24'!D17 -> 1123798.8 | J15: =+G15-H15+I15 -> 11840347 | K15: =F15-J15 -> 2205463.1 | L15: =+D15-F15 -> 42945004
B16: Post Ventas | C16: =SUM('budget (11)'!D50) -> 19238385 | D16: 21656506 | E16: =D16/$E$3 -> 367059.42 | F16: =SUM('budget (11)'!E50) -> 0 | G16: =SUM('budget (11)'!F50) -> 0 | J16: =+G16-H16+I16 -> 0 | K16: =F16-J16 -> 0 | L16: =+D16-F16 -> 21656506
B17: Total Gastos Operativos | C17: =SUM(C12:C16) -> 5.5722607e+08 | D17: =SUM(D12:D16) -> 614550940 | E17: =SUM(E12:E16) -> 10416118 | F17: =SUM(F12:F16) -> 14816941 | G17: =SUM(G12:G16) -> 11951671 | H17: =SUM(H12:H16) -> 743669.77 | I17: =SUM(I12:I16) -> 1123798.8 | J17: =SUM(J12:J16) -> 12331800 | ... L17: =SUM(L12:L16) -> 5.99734e+08
B18: Permisos legales y Preliminares | C18: =SUM('budget (11)'!D51:D52) -> 15000000 | D18: 30500000 | E18: =D18/$E$3 -> 516949.15 | F18: =+'Finanzas 11.24'!F16 -> 16703974 | G18: =+'Finanzas 11.24'!G16 -> 12591931 | I18: =-'ANTICIPO 11.24'!D15 -> 352775.8 | J18: =+G18-H18+I18 -> 12944707 | K18: =F18-J18 -> 3759267.4 | L18: =+D18-F18 -> 13796026
B19: Diseño y Proyecto | C19: =SUM('budget (11)'!D4:D10) -> 20790000 | D19: 20790000 | E19: =D19/$E$3 -> 352372.88 | F19: =+'Finanzas 11.24'!F3 -> 20953109 | G19: =+'Finanzas 11.24'!G3 -> 20098510 | H19: =+'CXP 11.24'!D15 -> 184115.3 | I19: =-'ANTICIPO 11.24'!D13 -> 547084.93 | J19: =+G19-H19+I19 -> 20461479 | K19: =F19-J19 -> 491629.87 | L19: =+D19-F19 -> -163109.1
B20: Gastos Financieros | C20: =SUM('budget (11)'!D54) -> 192383847 | D20: 216565093 | E20: =D20/$E$3 -> 3670594.8 | F20: =SUM('budget (11)'!E54) -> 0 | G20: =SUM('budget (11)'!F54) -> 0 | J20: =+G20-H20+I20 -> 0 | K20: =F20-J20 -> 0 | L20: =+D20-F20 -> 216565093
B21: Imprevistos | C21: =SUM('budget (11)'!D53) -> 19238385 | D21: 21656509 | E21: =D21/$E$3 -> 367059.47 | F21: =SUM('budget (11)'!E53) -> 0 | G21: =SUM('budget (11)'!F53) -> 0 | J21: =+G21-H21+I21 -> 0 | K21: =F21-J21 -> 0 | L21: =+D21-F21 -> 21656509
B22: Total Otros Gastos | C22: =SUM(C18:C21) -> 247412232 | D22: =SUM(D18:D21) -> 289511602 | E22: =SUM(E18:E21) -> 4906976.3 | F22: =SUM(F18:F21) -> 37657084 | G22: =SUM(G18:G21) -> 32690441 | H22: =SUM(H18:H21) -> 184115.3 | I22: =SUM(I18:I21) -> 899860.73 | J22: =SUM(J18:J21) -> 33406186 | ... L22: =SUM(L18:L21) -> 2.5185452e+08
B23: TOTALES | C23: =C5+C11+C17+C22 -> 2.8318619e+09 | D23: =D5+D11+D17+D22 -> 3173098639 | E23: =E5+E11+E17+E22 -> 53781333 | F23: =F22+F17+F11+F5 -> 1.5751011e+08 | G23: =G22+G17+G11+G5 -> 1.496782e+08 | H23: =H22+H17+H11+H5 -> 947457.29 | I23: =I22+I17+I11+I5 -> 2023659.5 | J23: =J22+J17+J11+J5 -> 1.507544e+08 | K23: =K22+K17+K11+K5 -> 6755710.4 | L23: =L22+L17+L11+L5 -> 2.9775947e+09
H25: Aportes AFI | I25: =+'BCE 11.24'!C38 -> 1.5969577e+08 | J25: 160000000 | N25: Dato del ADI | O25: 2.8318619e+09
H26: Balance Bancos | I26: =-'BCE 11.24'!C9-'BCE 11.24'!C10 -> -9895226.2 | J26: =J25-J23 -> 9245598.1 | N26: Dato Procore | O26: =C23 -> 2.8318619e+09
H27: Retenciones por pagar | I27: =+'BCE 11.24'!C29+'BCE 11.24'!C30+'BCE 11.24'!C31+'BCE 11.24'!C28 -> 837874.42 | J27: =+K23 -> 6755710.4 | N27: Diferencia | O27: =O25-O26 -> -0.55799961
H28: Depósitos de Clientes | I28: =+'BCE 11.24'!C27 -> 298015.71
H29: Pagado según balanza | I29: =SUM(I25:I27) -> 1.5063842e+08 | J29: =J26-J27 -> 2489887.7
H30: Pagado según reportes | I30: =+J23 -> 1.507544e+08
H31: Diferencial cambiario | I31: =+I29-I30 -> -115980.11 | J31: =+'BCE 11.24'!C39 -> 115731.52 | K31: =+I31+J31 -> -248.59
B34: Total Gastos Operativos
B35: Permisos legales y Preliminares
B36: Diseño y Proyecto
B37: Gastos Financieros
B38: Imprevistos
B39: Total Otros Gastos
B40: TOTALES
B43: APORTE AFI | C43: 160000000
B44: Gastado y comprometido | C44: =J23+J27 -> 1.5751011e+08 | E44: =C44/C43 -> 0.9844382
B45: Disponible | C45: =C43-C44 -> 2489887.7 | E45: =C45/C43 -> 0.015561798

Sheet FLUJO Y DISPONIBLE 11.24
D2: 59.9
B3: 160000000 | C3: =B3-C4 -> 65967960 | D3: =C3-(SUM(D5:D8)) -> 41084982
B4: TERRENO | C4: 94032040
B5: DISENO Y PROYECTO | D5: =D10*$D$2 -> 9215810.2
B6: PRELIMINARES DEL PROYECTO | D6: =D11*$D$2 -> 781278.1
B7: PERMISOS | D7: =D12*$D$2 -> 11511124
B8: PUBLICIDAD | D8: =D13*$D$2 -> 3374766
D10: 153853.26
D11: 13043.04
D12: 192172.35
D13: 56340
C16: FECHA1 | D16: ACUMULADO NOVIEMBRE 2024 | E16: 45627 | F16: 45658 | G16: 45689 | H16: 45717
B17: APORTE INICIAL | C17: 160000000
B18: DISPONIBLE | D18: =C17-D19 -> 9245598 | E18: =D18-E19 -> 839887.68 | F18: =E18-F19 -> -10368953 | G18: =F18-G19 -> -16127794 | H18: =G18-H19 -> -21577794
B19: TOTAL GASTO | D19: =SUM(D21:D33) -> 1.507544e+08 | E19: =SUM(E21:E33) -> 8405710.4 | F19: =SUM(F21:F33) -> 11208841 | G19: =SUM(G21:G33) -> 5758840.8 | H19: =SUM(H21:H33) -> 5450000
B21: TERRENO | D21: =+'PRESENTACIÓN 11-24'!J5 -> 94172342 | E21: =+'PRESENTACIÓN 11-24'!K5 -> 0
B22: DISENO Y PROYECTO | D22: =+'PRESENTACIÓN 11-24'!J19 -> 20461479 | E22: =+'PRESENTACIÓN 11-24'!K19 -> 491629.87
B23: PERMISOS PRELIMINARES DEL PROYECTO | D23: =+'PRESENTACIÓN 11-24'!J18 -> 12944707 | E23: =+'PRESENTACIÓN 11-24'!K18 -> 3759267.4 | F23: 2458840.8 | G23: 2458840.8 | H23: 1400000
B24: URBANISMO | D24: =+'PRESENTACIÓN 11-24'!J6 -> 9219083.6 | E24: =+'PRESENTACIÓN 11-24'!K6 -> 0
B25: PROMOCION Y PUBLICIDAD | D25: =+'PRESENTACIÓN 11-24'!J15 -> 11840347 | E25: =+'PRESENTACIÓN 11-24'!K15 -> 2205463.1 | F25: 3600000 | G25: 1650000 | H25: 1650000
B26: ADMINISTRACION FIDUCIARIA | D26: =+'PRESENTACIÓN 11-24'!J14 -> 330277.4
B28: Gerencia Construcción | D28: =+'PRESENTACIÓN 11-24'!J9+'PRESENTACIÓN 11-24'!J12 -> 1786165.8 | E28: =+'PRESENTACIÓN 11-24'!K9+500000 -> 519672.22 | F28: 500000 | G28: 500000 | H28: 1000000
B29: Gerencia Promotora | E29: 500000 | F29: 500000 | G29: 500000 | H29: 750000
B30: Gerencia de Ventas(Adm Ventas) | E30: =+'PRESENTACIÓN 11-24'!K13+650000 -> 929677.77 | F30: 650000 | G30: 650000 | H30: 650000
B31: Comisiones de Ventas | F31: 500000
B32: Impuesto de transferencia
B33: IFC (lote 1 y lote 2) | F33: 3000000
B41: 4837716.2
B42: 6800000 | C42: permisos por iniciar
B43: 8480849.8 | C43: diseño por pagar
B44: 2390947.5 | C44: Publicidade por pagar
B45: =SUM(B41:B44) -> 22509514

Sheet BCE 12.24
A1: Balance Sheet
A2: Fideicomiso Irrevocable de Desarrollo Inmobiliario y Administración Araya
A3: As at 31 December 2024
B5: Account | C5: 31 Dec 2024
A7: Assets
B8: Bank
B9: Banesco DOP -Cta. Corriente No.99100010856 | C9: 7515475.3
B10: Banesco USD -Cta. Ahorro No.99200013780 | C10: 596734.87 | D10: [FX]
B11: Cuentas por Cobrar Compañía Relacionada USD | C11: 604757.16 | D11: [FX]
B12: Total Bank | C12: =SUM(C9:C11) -> 8716967.3
B13: Current Assets
B14: Anticipos a Proveedores | C14: 1827824.6
B15: Total Current Assets | C15: =C14 -> 1827824.6
B16: Non-current Assets
B17: Costos de Construcción | C17: 31843261
B18: Costos Operativos | C18: 12349086
B19: Otros Costos | C19: 12715384
B20: Terreno | C20: 94172342
B21: Total Non-current Assets | C21: =SUM(C17:C20) -> 1.5108007e+08
A22: Total Assets | C22: =(0 + ((C12 + C15) + C21)) -> 1.6162487e+08
A24: Liabilities
B25: Current Liabilities
B26: Cuentas por Pagar Comerciales | C26: 433593.97
B27: Depósitos Diferidos de Clientes | C27: 597566.75
B28: Otras Cuentas por Pagar | C28: 500375.8
B29: Retención 100% ITBIS. Personas Físicas | C29: 48750
B30: Retención 30% ITBIS Jurídica | C30: 37371.92
B31: Retención ISR Exterior 27% | C31: 146511.92
B32: Retención ISR Personas Físicas 10% | C32: 27083.33
B33: Total Current Liabilities | C33: =SUM(C26:C32) -> 1791253.7
A34: Total Liabilities | C34: =(0 + C33) -> 1791253.7
B36: Net Assets | C36: =(C22 - C34) -> 1.5983361e+08
A38: Equity
B39: Aporte Fideicomitente AFI Universal | C39: 1.5969577e+08
B40: Current Year Earnings | C40: 137838.47
A41: Total Equity | C41: =SUM(C39:C40) -> 1.5983361e+08
A44: [FX] Exchange rates used to convert foreign currency into DOP are shown below. Rates are provided by XE.com unless otherwise stated.
A45: 31 Dec 2024
A46: 0.0163669 USD (United States Dollar)

Sheet Finanzas 12.24
A1: No | B1: Código de presupuesto | C1: Monto del presupuesto original | D1: Cambio de presupuesto | E1: Monto Total Presupuestado | F1: Monto Total Comprometido | G1: Trabajo Ejectutado
A2: 1 | B2: 1-1 - TERRENO | C2: 103385169 | E2: 103385169 | F2: 94172342 | G2: 94172342
A3: 2 | B3: 1-2 - DISEÑO Y PROYECTO | C3: 20790000 | D3: 0 | E3: 20790000 | F3: 21610963 | G3: 20979516
A4: 3 | B4: 1-4 - URBANISMO | C4: 451759000 | E4: 4.51759e+08 | F4: 9219083.6 | G4: 9219083.6
A5: 4 | B5: 1-5 - EDIFICACIONES | C5: 1265953920 | E5: 1265953920 | F5: 0 | G5: 0
A6: 5 | B6: 1-6 - GERENCIA DE CONSTRUCCION | C6: 171771292 | D6: 18198088 | E6: 171771292 | F6: 1644662 | G6: 1644662
A7: 6 | B7: 1-7 - INDIRECTOS DE OBRA | C7: 34354258 | D7: 3639618 | E7: 34354258 | F7: 0 | G7: 0
A8: 7 | B8: 1-8 - FONDO DE CONTINGENCIA | C8: 0 | D8: 37993876 | E8: 0 | F8: 0 | G8: 0
A9: 8 | B9: 2-1 - GERENCIA DE LA PROMOTORA | C9: 137417034 | D9: 14558470 | E9: 137417034 | F9: 161175.97 | G9: 161175.97
A10: 9 | B10: 2-2 - GERENCIA DE VENTAS | C10: 67334346 | D10: 8463436 | E10: 281704919 | F10: 559355.54 | G10: 559355.54
A11: 10 | B11: 2-3 - ADMINISTRACION DE FIDUCIARIA | C11: 281704919 | D11: 26425415 | E11: 67334346 | F11: 373034.61 | G11: 373034.61
A12: 11 | B12: 2-4 - PUBLICIDAD Y PROMOCION | C12: 51531388 | D12: 5459426 | E12: 51531388 | F12: 14415200 | G12: 11255520
A13: 12 | B13: 2-5 - POST-VENTAS | C13: 19238385 | D13: 2418121 | E13: 19238385 | F13: 0 | G13: 0
A14: 13 | B14: 3-1 - PERMISOS LEGALES Y PRELIMINARES | C14: 19238385 | D14: 2418124 | E14: 15000000 | F14: 16827428 | G14: 12715384
A15: 14 | B15: 3-2 - IMPREVISTOS | C15: 192383847 | D15: 24181246 | E15: 19238385 | F15: 0 | G15: 0
A16: 15 | B16: 3-3 - GASTOS FINANCIEROS | C16: 15000000 | D16: 15500000 | E16: 192383847 | F16: 0 | G16: 0
B17: Grand Totals | C17: =SUM(C2:C16) -> 2.8318619e+09 | D17: =SUM(D2:D16) -> 1.5925582e+08 | E17: =SUM(E2:E16) -> 2.8318619e+09 | F17: =SUM(F2:F16) -> 1.5898324e+08 | G17: =SUM(G2:G16) -> 1.5108007e+08

Sheet ANTICIPOS 12.24
A3: ContactName | B3: Reference | C3: InvoiceDate | D3: Total | E3: InvoiceAmountDue | F3: Description | G3: TrackingName1 | H3: TrackingOption1
A4: RIOS & ASOCIADOS ABOGADOS CONSULTORES S R L | B4: ANTICIPO RIOS LEGAL | C4: 45622 | D4: 352775.8 | E4: 352775.8 | F4: Para Registrar el anticipo realizado por Tecnica MMHB por gestion Confotur. Pendiente reembolso PO--036 | G4: COSTOS DE OBRA | H4: Permisos, Legales y Preliminares
A5: LMCAD ESTUDIO DE ANIMACION SRL | B5: ANTICIPO LMCAD | C5: 45616 | D5: 376562.5 | E5: 376562.5 | F5: Avance 25% PO--018 Renders y Maqueta Digital Araya | G5: COSTOS DE OBRA | H5: Publicidad: Medios Tradicionales y Digitales
A6: LMCAD ESTUDIO DE ANIMACION SRL | C6: 45512 | D6: 747236.25 | E6: 747236.25 | F6: 562949957178318 | G6: COSTOS DE OBRA | H6: Publicidad: Medios Tradicionales y Digitales
A7: MARY VANGIE GRULLON CACERES | B7: ANTICIPO MARY | C7: 45469 | D7: 38250 | E7: 38250 | F7: PO--021 | G7: COSTOS DE OBRA | H7: DiseÃ±o y Proyecto
A8: ONEIDA MARIA FRIAS PADILLA | B8: PO--020 | C8: 45429 | D8: 40000 | E8: 40000 | F8: PO--020 | G8: COSTOS DE OBRA | H8: DiseÃ±o y Proyecto
A9: HIDROPOZO SRL | B9: ANTICIPO HIDROPOZOS | C9: 45266 | D9: 273000 | E9: 273000 | F9: ANTICIPO COT 94 PRUEBA DE INFILTRACION Y BOMBEO ARAYA | G9: COSTOS DE OBRA | H9: DiseÃ±o y Proyecto
D10: =SUM(D4:D9) -> 1827824.6 | E10: =SUM(E4:E9) -> 1827824.6

Sheet CXP 12.24
A1: Aged Payables Detail
A2: Fideicomiso Irrevocable de Desarrollo Inmobiliario y Administración Araya
A3: As at 31 December 2024
A4: Ageing by due date
A6: Invoice Date | B6: Due Date | C6: Invoice Reference | D6: < 1 Month | E6: 1 Month | F6: 2 Months | G6: 3 Months | H6: Older | I6: Total | J6: COSTO DE OBRA
A8: ADVANCEBAU LLC
A9: 45453 | B9: 45473 | C9: INT.061024 | D9: 0 | E9: 0 | F9: 0 | G9: 0 | H9: 60314.2 | I9: 60314.2 | J9: Diseño y Proyecto
A10: Total ADVANCEBAU LLC | D10: =D9 -> 0 | E10: =E9 -> 0 | F10: =F9 -> 0 | G10: =G9 -> 0 | H10: =H9 -> 60314.2 | I10: =I9 -> 60314.2
A12: ESTRUCTURAS PUBLICITARIAS Y GRAFICOS EPUGRAF SRL
